Workbook
Name ALL_BRANCH_CODES: LK_DropdownLists!$FB$2:$FB$21
Name ALL_BRANCH_NAMES: LK_DropdownLists!$FA$2:$FA$21
Name ALL_BRANCH_SWIFTS: LK_DropdownLists!$FC$2:$FC$21
Name ALL_DEPT_KEYS: LK_DropdownLists!$V$2:$V$87
Name ALL_DEPT_NAMES: LK_DropdownLists!$U$2:$U$87
Name ALL_PROV_KEYS: LK_DropdownLists!$DJ$2:$DJ$36
Name ALL_PROV_NAMES: LK_DropdownLists!$DI$2:$DI$36
Name BANK_KEYS: LK_DropdownLists!$EU$2:$EU$6
Name BANK_LIST: LK_DropdownLists!$FL$2:$FL$29
Name BRANCH_ABL: LK_DropdownLists!$GA$2:$GA$4
Name BRANCH_ANZ: LK_DropdownLists!$GL$2:$GL$2
Name BRANCH_APB: LK_DropdownLists!$FO$2:$FO$8
Name BRANCH_BAY: LK_DropdownLists!$GI$2:$GI$2
Name BRANCH_BBL: LK_DropdownLists!$GH$2:$GH$2
Name BRANCH_BCEL: LK_DropdownLists!$FM$2:$FM$13
Name BRANCH_BFL: LK_DropdownLists!$FS$2:$FS$3
Name BRANCH_BIC: LK_DropdownLists!$FV$2:$FV$3
Name BRANCH_BOC: LK_DropdownLists!$GN$2:$GN$2
Name BRANCH_CAB: LK_DropdownLists!$GB$2:$GB$2
Name BRANCH_ICB: LK_DropdownLists!$FX$2:$FX$2
Name BRANCH_ICBC: LK_DropdownLists!$GM$2:$GM$2
Name BRANCH_JDB: LK_DropdownLists!$FQ$2:$FQ$6
Name BRANCH_KTB: LK_DropdownLists!$GJ$2:$GJ$2
Name BRANCH_LCNB: LK_DropdownLists!$FT$2:$FT$4
Name BRANCH_LDB: LK_DropdownLists!$FN$2:$FN$8
Name BRANCH_LMI: LK_DropdownLists!$FY$2:$FY$2
Name BRANCH_LVB: LK_DropdownLists!$FR$2:$FR$4
Name BRANCH_MJBL: LK_DropdownLists!$FZ$2:$FZ$3
Name BRANCH_NBB: LK_DropdownLists!$FP$2:$FP$4
Name BRANCH_PBL: LK_DropdownLists!$GC$2:$GC$2
Name BRANCH_PSV: LK_DropdownLists!$FU$2:$FU$7
Name BRANCH_SCBV: LK_DropdownLists!$GK$2:$GK$2
Name BRANCH_SCL: LK_DropdownLists!$GD$2:$GD$3
Name BRANCH_SHB: LK_DropdownLists!$GE$2:$GE$2
Name BRANCH_STB: LK_DropdownLists!$FW$2:$FW$3
Name BRANCH_VCB: LK_DropdownLists!$GF$2:$GF$2
Name BRANCH_VTB: LK_DropdownLists!$GG$2:$GG$2
Name COUNTRY_KEYS: LK_DropdownLists!$DF$2:$DF$3
Name COUNTRY_LIST: LK_DropdownLists!$DE$2:$DE$3
Name DEPT_CHAM: LK_DropdownLists!$Q$2:$Q$5
Name DEPT_KHAMM: LK_DropdownLists!$T$2:$T$5
Name DEPT_LUANGPB: LK_DropdownLists!$R$2:$R$5
Name DEPT_MFA: LK_DropdownLists!$H$2:$H$6
Name DEPT_MLSW: LK_DropdownLists!$J$2:$J$6
Name DEPT_MOAF: LK_DropdownLists!$I$2:$I$6
Name DEPT_MOES: LK_DropdownLists!$E$2:$E$7
Name DEPT_MOF: LK_DropdownLists!$C$2:$C$7
Name DEPT_MOH: LK_DropdownLists!$D$2:$D$7
Name DEPT_MOHA: LK_DropdownLists!$F$2:$F$6
Name DEPT_MOIC: LK_DropdownLists!$L$2:$L$5
Name DEPT_MOJ: LK_DropdownLists!$M$2:$M$5
Name DEPT_MONRE: LK_DropdownLists!$K$2:$K$5
Name DEPT_MPI: LK_DropdownLists!$N$2:$N$5
Name DEPT_MPWT: LK_DropdownLists!$G$2:$G$6
Name DEPT_NA: LK_DropdownLists!$O$2:$O$7
Name DEPT_SAVAN: LK_DropdownLists!$S$2:$S$5
Name DEPT_VTCAP: LK_DropdownLists!$P$2:$P$6
Name DIST_ATP: LK_DropdownLists!$EA$2:$EA$6
Name DIST_BKO: LK_DropdownLists!$DO$2:$DO$6
Name DIST_BLK: LK_DropdownLists!$DU$2:$DU$7

Sheet HOME
A2: LAO PDR GOVERNMENT PAYROLL INFORMATION TOOLKIT
A6: 📂 NAVIGATE TO SHEETS
A8: =HYPERLINK("#'HOME'!A1","🏠 Home") -> 🏠 Home | D8: =HYPERLINK("#'INSTRUCTIONS'!A1","📋 Instructions") -> 📋 Instructions | G8: =HYPERLINK("#'EMPLOYEE_MASTER'!A1","👤 Employee Master") -> 👤 Employee Master | J8: =HYPERLINK("#'PAYROLL_CALC'!A1","💵 Payroll Calc") -> 💵 Payroll Calc
A9: This navigation page | D9: What to update & workflow | G9: 500 records – main input sheet | J9: Monthly payroll output
A11: =HYPERLINK("#'LK_OrgMaster'!A1","🏛️ Org Master") -> 🏛️ Org Master | D11: =HYPERLINK("#'LK_LocationMaster'!A1","📍 Location Master") -> 📍 Location Master | G11: =HYPERLINK("#'LK_BankMaster'!A1","🏦 Bank Master") -> 🏦 Bank Master | J11: =HYPERLINK("#'LK_GradeDerivation'!A1","🎓 Grade Derivation") -> 🎓 Grade Derivation
A12: Ministry→Dept→Division hierarchy | D12: Country→Province→District | G12: Bank→Branch hierarchy | J12: Edu×Experience→Grade/Step
A14: =HYPERLINK("#'LK_GradeStep'!A1","📊 Grade/Step Rates") -> 📊 Grade/Step Rates | D14: =HYPERLINK("#'LK_AllowanceRates'!A1","💰 Allowance Rates") -> 💰 Allowance Rates | G14: =HYPERLINK("#'LK_PIT'!A1","🧮 PIT Brackets") -> 🧮 PIT Brackets
A15: Multiplier lookup table | D15: All rates – update here | G15: Income tax brackets
A25: ⚠️ DISCLAIMER: This toolkit contains mock data for illustration and stakeholder review. All names, IDs and figures are fictitious. Finance departments must verify all rates against current MoF circulars, SSO decrees, and GDT orders before operational use.
A29: ສາທາລະນະລັດ ປະຊາທິປະໄຕ ປະຊາຊົນລາວ | Lao People's Democratic Republic

Sheet INSTRUCTIONS
A1: 📋 INSTRUCTIONS — Lao PDR Government Payroll Toolkit
A2: Read this sheet fully before making any changes to the workbook. 🟡 Yellow cells = manual input. 🟢 Green cells = auto-calculated (do NOT edit). All master lookup tables drive downstream calculations automatically — change a master table and every dependent field across all 500 records updates instantly.
A3: 1. COLOUR CODING GUIDE
A4: Element / Field | B4: Description | C4: Frequency / Trigger
A5: 🟡 Yellow background (Blue text) | B5: Editable INPUT cell — enter or update data here. These are the only cells stakeholders should write into. | C5: As required
A6: 🟢 Green background (Green text) | B6: AUTO-CALCULATED formula cell — driven by master tables or other inputs. DO NOT edit. Editing will break the chain of calculations. | C6: Never edit
A7: ⬜ White background | B7: Reference or display value — informational, not used in formulas. | C7: Read only
A8: 🔴 Red / Orange text in master tables | B8: Flagged value requiring attention (e.g. Is Remote = Yes, Is Hazardous = Yes in Location Master). | C8: Informational
A9: 2. DEPENDENT DROPDOWNS — HOW THEY WORK
A10: ℹ️ 159 named ranges power all dropdowns. They are stored in the hidden LK_DropdownLists sheet. Each dropdown is driven by INDIRECT() — selecting a value in the parent column automatically narrows the child dropdown to only relevant options.
A11: Element / Field | B11: Description | C11: Frequency / Trigger
A12: Ministry (Col T) → Dept (Col U) → Division (Col V) | B12: Select Ministry first. Department dropdown immediately narrows to only that ministry's departments. Then select Department — Division narrows to only that department's divisions. Driven by named ranges DEPT_<MinistryKey> and DIV_<DeptKey> in LK_DropdownLists. | C12: Org Master driven
A13: Service Country (Col W) → Province (Col X) → District (Col Y) | B13: Select Country (Lao PDR or Foreign/International) first. Province dropdown narrows to only that country's provinces or postings. Then select Province — District narrows to that province's districts. Driven by PROV_<CountryKey> and DIST_<ProvinceKey> named ranges. | C13: Location Master driven
A14: Position (Col M) → driven by Profession (Col Z) | B14: Position dropdown shows only positions relevant to the employee's Profession Category. Profession (Col Z) is auto-derived from Ministry via LK_OrgMaster. Named ranges: POS_TEACHER, POS_MEDICAL, POS_FINANCE, POS_ADMINISTRATION, POS_TECHNICAL, POS_LEGAL, POS_DIPLOMATIC, POS_GENERAL. | C14: Org Master / Profession driven
A15: Bank Name (Col AJ) → Bank Branch (Col AK) | B15: Select Bank Name first. Branch dropdown narrows to only that bank's branches. Driven by BRANCH_<BankKey> named ranges (e.g. BRANCH_BCEL shows all 8 BCEL branches). Bank Master has 5 banks and 20 branches total. | C15: Bank Master driven
A16: Prior Experience (Col O) → Grade (Col P) → Step (Col Q) | B16: Prior Experience is the only manual grade input. Enter years worked before joining government. Grade and Step auto-derive via SUMPRODUCT against LK_GradeDerivation (Education × Exp band). If left blank, Grade defaults to the education baseline (0 prior exp row). | C16: Grade Derivation driven
A17: 3. MASTER LOOKUP TABLES — WHAT TO UPDATE & WHERE
A18: ⭐ RULE: Never change values in PAYROLL_CALC or EMPLOYEE_MASTER formula cells (green). All changes go into the master tables below. One update here flows to all 500 employee records automatically.
A19: Element / Field | B19: Description | C19: Frequency / Trigger
A20: LK_GradeStep ⭐ | B20: TWO INPUT COLUMNS: Col D = Multiplier | Col E = Index Value (LAK). Basic Salary = Index Value × Multiplier for each employee's grade/step. ► Update Col E (Index Value) when MoF issues a new ຄ່າດັດສະນີ circular — set the same LAK amount across all 100 rows for a uniform index, or enter different values per grade row if MoF ever introduces a tiered/grade-differentiated index. ► Update Col D (Multiplier) when Civil Service Authority revises the multiplier table. | C20: Per MoF circular (Index Value) / Per CSA order (Multiplier)
A21: LK_GradeDerivation ⭐ | B21: Maps Education Level × Prior Experience band → Grade & Step. 126 rows (6 education levels × 21 experience bands). ► Update Col D (Grade) and Col E (Step) if CSA revises entry grade rules. ► Do NOT change Col A (Education) or Cols B/C (Exp Min/Max) unless adding new bands — these are the lookup keys used by Employee Master SUMPRODUCT formulas. | C21: Per CSA revision
A22: LK_OrgMaster ⭐ | B22: Full Ministry → Department → Division hierarchy (18 orgs, 86 dept rows). Three derived fields in Employee Master source from here: (1) Profession Category (Col F) → drives Position dropdown and Teaching/Medical allowances. (2) NA Allowance Eligible (Col G) → drives Is NA Member and NA Member Allowance. (3) Field Allowance Type (Col H) → Teaching = Teaching Allowance, Medical = Medical Allowance. ► Add new ministries/departments as new rows. ► Change profession/allowance type in Cols F-H as needed. DO NOT change Ministry Key (Col C) or Dept Key (Col E) — these power dependent dropdowns. | C22: When org structure changes
A23: LK_LocationMaster ⭐ | B23: All 18 Lao PDR provinces + 17 foreign postings, each expanded to district level (154 rows). Three flags auto-derive in Employee Master from this table: (1) Is Remote (Col G) → Remote Area Allowance. (2) Is Hazardous (Col H) → Hardship & Hazardous Allowance. (3) Is Foreign (derived from Country = Foreign/International) → Foreign Living Allowance. ► Update Col G or H when MoHA/MoF gazette revises province classification. DO NOT change Province Key (Col C) — it powers dependent district dropdowns. | C23: Per MoHA/MoF gazette
A24: LK_BankMaster | B24: 5 banks, 20 branches. Bank Name and Branch Name drive dependent dropdowns in Employee Master. Bank Branch Code (Col D) and SWIFT/BIC Code (Col E) are auto-looked up in Employee Master. ► Add new branches as new rows — keep bank name in Col A exactly matching existing entries. Col H (helper key) is auto-calculated — do not edit. | C24: When new branch added
A25: LK_AllowanceRates | B25: All cash allowance amounts and SSO/PIT-related rates. ► Update Col B (Amount) for any allowance when MoF issues revised rates. Note: Index Value (ຄ່າດັດສະນີ) is NO LONGER here — it is now in LK_GradeStep Col E. ► Update Row 26 (SSO Employee Rate %) and Row 27 (SSO Employer Rate %) when SSO revises rates. DO NOT change the allowance names in Col A — these are VLOOKUP keys used by PAYROLL_CALC. | C25: Per MoF circular / SSO decree
A26: LK_PIT | B26: Personal Income Tax progressive brackets for Lao PDR. ► Update Col D (Rate %) and Col F (Cumulative Tax at lower bound) if GDT/MoF revises tax slabs. PIT is calculated on Taxable Income = Gross Earnings minus SSO Employee Contribution. | C26: Per GDT/MoF order
A27: 4. EMPLOYEE MASTER — FIELD-BY-FIELD ENTRY GUIDE
A28: Element / Field | B28: Description | C28: Frequency / Trigger
A29: PERSONAL & EMPLOYMENT DETAILS (Cols A–L)
A30: Employee Code (Col A) | B30: Unique identifier — format LAO00001. Pre-populated in mock data. Do not duplicate. | C30: One-time, system assigned
A31: Title (Col B) | B31: Mr. / Ms. / Mrs. / Dr. | C31: On record
A32: First Name (Col C), Last Name (Col D) | B32: Employee's name in English. | C32: On record
A33: Gender (Col E) | B33: Dropdown: Male / Female. | C33: On record
A34: Date of Birth (Col F) | B34: DD-MMM-YYYY. Drives auto-calculation of Date of Retirement (age 60) in Col K. | C34: On record
A35: Date of Joining (Col I) | B35: Date employee joined government service. Drives auto-calculation of Years of Service (Col J). | C35: On record
A36: Years of Service (Col J) | B36: 🟢 AUTO — DATEDIF formula from Date of Joining to today. Do not edit. | C36: Automatic
A37: Date of Retirement (Col K) | B37: 🟢 AUTO — Date of Birth + 60 years. Do not edit. | C37: Automatic
A38: Employment Type (Col L) | B38: Dropdown: Permanent / Probationary / Contract / Intern. | C38: On joining / change
A39: GRADE & SALARY INPUTS (Cols M–Q)
A40: Position / Designation (Col M) | B40: 🔗 DEPENDENT DROPDOWN — shows positions for this employee's Profession Category (Col Z). Profession is auto-derived from Ministry via LK_OrgMaster. Select Ministry first, then choose the position title. | C40: On joining / promotion
A41: Education Qualification (Col N) | B41: Dropdown: Below Secondary / Secondary / Diploma / Bachelor's / Master's / PhD. Drives Grade derivation — more senior education = higher base grade. | C41: On record / change
A42: Prior Experience (Col O) | B42: 🟡 KEY INPUT — enter total years worked in any sector BEFORE joining government service. E.g., if employee worked in private sector for 5 years before joining, enter 5. Directly drives Grade (Col P) and Step (Col Q) via LK_GradeDerivation. If blank, Grade defaults to the education baseline with 0 prior experience. | C42: On joining / verification
A43: Grade (Col P) | B43: 🟢 AUTO — SUMPRODUCT formula matching Education (Col N) and Prior Experience (Col O) against LK_GradeDerivation table. Updates instantly when either input changes. | C43: Automatic
A44: Step (Col Q) | B44: 🟢 AUTO — same SUMPRODUCT formula as Grade. Updates with Grade. | C44: Automatic
A45: ORGANISATION (Cols T–V) — Dependent Dropdowns
A46: Ministry / Province / Central Org (Col T) | B46: 🔗 DROPDOWN from master list of 18 organisations. Selecting this drives: (a) Department dropdown, (b) Profession Category, (c) NA Member flag, (d) Field Allowance Type — all auto-derived. | C46: On joining / transfer
A47: Department (Col U) | B47: 🔗 DEPENDENT on Ministry — shows only departments under the selected ministry. Do not type manually. Clear and re-select if ministry changes. | C47: On joining / transfer
A48: Division (Col V) | B48: 🔗 DEPENDENT on Department — shows only divisions under the selected department. Do not type manually. | C48: On joining / transfer
A49: SERVICE LOCATION (Cols W–AC) — Dependent Dropdowns + Auto-Derived
A50: Service Country (Col W) | B50: 🔗 DROPDOWN: Lao PDR or Foreign/International. Drives Province dropdown. | C50: On posting
A51: Service Province / Posting (Col X) | B51: 🔗 DEPENDENT on Country — shows provinces (Lao PDR) or diplomatic postings (Foreign). This single field drives three auto-derived flags below. | C51: On posting
A52: Service District (Col Y) | B52: 🔗 DEPENDENT on Province — shows districts for the selected province. | C52: On posting
A53: Profession Category (Col Z) | B53: 🟢 AUTO — VLOOKUP on Ministry in LK_OrgMaster. Drives Position dropdown and Teaching/Medical allowances. | C53: Automatic
A54: Is Remote Area (Col AA) | B54: 🟢 AUTO — VLOOKUP of Service Province in LK_LocationMaster Col G. Drives Remote Area Allowance in payroll. | C54: Automatic
A55: Is Foreign Posting (Col AB) | B55: 🟢 AUTO — Yes if Service Country = Foreign/International. Drives Foreign Living Allowance. | C55: Automatic
A56: Is Hazardous Area (Col AC) | B56: 🟢 AUTO — VLOOKUP of Service Province in LK_LocationMaster Col H. Drives Hardship & Hazardous Allowance. | C56: Automatic
A57: BANK DETAILS (Cols AJ–AN) — Dependent Dropdowns + Auto-Derived
A58: Bank Name (Col AJ) | B58: 🔗 DROPDOWN from list of 5 approved banks. Drives Branch dropdown. | C58: On joining / change
A59: Bank Branch (Col AK) | B59: 🔗 DEPENDENT on Bank — shows only branches for the selected bank. E.g. selecting BCEL shows all 8 BCEL branches. | C59: On joining / change
A60: Bank Branch Code (Col AL) | B60: 🟢 AUTO — INDEX/MATCH on Bank Name + Branch Name against LK_BankMaster helper column. Do not edit. | C60: Automatic
A61: Bank Account No. (Col AM) | B61: 🟡 Manual input — employee's actual account number for salary crediting. | C61: On joining / change
A62: SWIFT / BIC Code (Col AN) | B62: 🟢 AUTO — VLOOKUP of Bank Name in LK_BankMaster. Do not edit. | C62: Automatic
A63: PAYROLL FLAGS (Cols AO–AS) — Manual + Auto-Derived
A64: Has Spouse (Col AO) | B64: 🟡 Manual dropdown: Yes / No. Drives Spouse Benefit in payroll calculation. | C64: On change
A65: No. of Eligible Children (Col AP) | B65: 🟡 Manual — enter 0 to 3. Maximum 3 children recognised per MoF guidelines. Drives Child Benefit. | C65: On change
A66: Position Level (Col AQ) | B66: 🟢 AUTO — nested IF formula on Position title keywords. Maps to: General Staff / Section Chief / Division Chief / Deputy Director / Director / Deputy Minister / Minister. Drives Position Allowance via VLOOKUP in PAYROLL_CALC. | C66: Automatic
A67: Is NA Member (Col AR) | B67: 🟢 AUTO — VLOOKUP on Ministry in LK_OrgMaster Col G. Yes only for National Assembly org. Drives NA Member Allowance. | C67: Automatic
A68: Field Allowance Type (Col AS) | B68: 🟢 AUTO — VLOOKUP on Ministry in LK_OrgMaster Col H. Teaching = Teaching Profession Allowance. Medical = Medical Personnel Allowance. None = neither. | C68: Automatic
A69: 5. PAYROLL_CALC — HOW THE CALCULATION WORKS
A70: Element / Field | B70: Description | C70: Frequency / Trigger
A71: Basic Salary (Col L) | B71: Index Value (from LK_GradeStep Col E for employee's grade/step) × Multiplier (from LK_GradeStep Col D). Fully dynamic — change either value in LK_GradeStep and all 500 basic salaries update. | C71: Automatic
A72: Earnings / Allowances (Cols M–X) | B72: 12 allowance columns, each conditionally calculated: Position Allowance = VLOOKUP of Position Level (Col AQ). Years of Service = stepped IF on years served. Teaching / Medical = triggered by Field Allowance Type (Col AS). NA Member = triggered by Is NA Member (Col AR). Hazardous / Remote / Foreign = triggered by Cols AA, AB, AC. Fuel Benefit = if Grade ≥ 8. Spouse + Child = from manual flags. | C72: Automatic
A73: Gross Earnings (Col Z) | B73: Basic Salary + Total Allowances. All earnings before deductions. | C73: Automatic
A74: SSO Employee Contribution (Col AA) | B74: 5.5% of Basic Salary (rate from LK_AllowanceRates Row 26). Deducted from gross. | C74: Automatic
A75: Taxable Income (Col AB) | B75: Gross Earnings − SSO Employee Contribution. | C75: Automatic
A76: PIT Amount (Col AC) | B76: Progressive Lao PDR income tax on Taxable Income. Brackets from LK_PIT. Deducted from gross. | C76: Automatic
A77: NET SALARY (Col AE) | B77: Gross Earnings − Total Deductions (SSO + PIT). The take-home salary figure. | C77: Automatic
A78: Grand Totals Row | B78: Row 504. SUM of all 500 employees for each column. Useful for ministry-level payroll aggregates. | C78: Automatic
A79: 6. ADDING NEW EMPLOYEES
A80: Element / Field | B80: Description | C80: Frequency / Trigger
A81: Step 1 — Employee Master | B81: Go to EMPLOYEE_MASTER. Scroll to row 504 (after the last mock record). Enter a new Employee Code (e.g. LAO00501). Fill all yellow input cells using the dropdowns provided. | C81: On new hire
A82: Step 2 — Verify auto-derived fields | B82: Check that green cells (Grade, Profession, Is Remote etc.) have populated correctly. If a dropdown shows blank, check that Ministry/Province matches the master table spelling exactly. | C82: On new hire
A83: Step 3 — Payroll Calc | B83: Go to PAYROLL_CALC. In row 504, enter the Employee Code in Col A. Copy the entire formula row from row 503 down to row 504 (select row 503, copy, select row 504, paste formulas only). | C83: On new hire
A84: Step 4 — Verify payroll | B84: Confirm the new row shows correct basic salary, allowances, and net salary. | C84: On new hire
A85: 7. IMPORTANT RULES & WARNINGS
A86: Element / Field | B86: Description | C86: Frequency / Trigger
A87: ⛔ Never delete rows | B87: Deleting rows in EMPLOYEE_MASTER breaks all PAYROLL_CALC formula references. Hide rows instead (right-click → Hide). | C87: Always
A88: ⛔ Never rename or move sheets | B88: All cross-sheet VLOOKUP and SUMPRODUCT formulas reference sheets by exact name. Renaming breaks them. | C88: Always
A89: ⛔ Never edit green cells | B89: All green cells are formula-driven. Editing them will overwrite formulas permanently and break the calculation chain. | C89: Always
A90: ⛔ Never change keys in master tables | B90: Ministry Key (LK_OrgMaster Col C), Dept Key (Col E), Province Key (LK_LocationMaster Col C), Bank Key (LK_BankMaster Col B) — these power named ranges for all dependent dropdowns. Changing them breaks all dropdowns. | C90: Always
A91: ✅ Always update master tables first | B91: Change LK_GradeStep, LK_AllowanceRates, LK_OrgMaster, LK_LocationMaster first. Employee Master and Payroll Calc will reflect changes automatically. | C91: Before payroll run
A92: ✅ Save a backup before bulk changes | B92: Save the file under a new name before making large edits to master tables or adding many employees. | C92: Before bulk edits
A93: ✅ Currency | B93: All monetary values are in LAK (Lao Kip). Thousands separators are applied for readability. Do not enter amounts in other currencies. | C93: Always
A94: ✅ Mock data | B94: All 500 employee records are fictitious. Replace with actual employee data as confirmed by HR departments. | C94: One-time migration
A95: =HYPERLINK("#HOME!A1","⬅ Back to HOME Dashboard") -> ⬅ Back to HOME Dashboard
A97: 8. FREE FIELDS IN PAYROLL_CALC + AUDIT TRAIL IN MASTER TABLES
A98: PAYROLL_CALC Cols Y-AA (Other Allowances 1-3) | B98: 🔓 FREE INPUT FIELDS — Enter any additional allowances not covered by the standard columns. Blue background. Enter the LAK amount directly. Examples: special project bonus, performance incentive, one-off MoF-approved subsidy. These are included in Total Allowances and Gross Earnings. | C98: Per month / as needed
A99: PAYROLL_CALC Cols AG-AH (Additional Deductions 1-2) | B99: 🔓 FREE INPUT FIELDS — Enter any additional deductions not covered by SSO or PIT. Light red background. Enter the LAK amount directly. Examples: employee loan repayment, salary advance recovery, voluntary savings contribution, disciplinary fine. These are included in Total Deductions and reduce Net Salary. | C99: Per month / as needed
A100: Audit Trail Cols in All Master Tables | B100: 📅 Six audit columns added to every master lookup table (LK_OrgMaster, LK_LocationMaster, LK_BankMaster, LK_GradeStep, LK_AllowanceRates, LK_PIT, LK_GradeDerivation): • Effective From — Date this record became effective • Effective To — Date this record was superseded (blank = still active) • Last Updated — Date of most recent change • Last Updated By — Name or staff code of who changed it • Circular / Reference — MoF circular or gazette number authorising the value • Change Remarks — Brief note on what changed and why RULE: Update these 6 fields EVERY TIME you change any value in a master table row. | C100: Update whenever master data changes
A101: Audit Trail — Best Practice | B101: When a rate changes (e.g. Index Value rises): (1) Set Effective To on the old row to the last date it applied. (2) Add a NEW row with the new values and the new Effective From date. (3) Never delete old rows — they form the historical record. This allows you to reconstruct any month's payroll from the correct historical rates. | C101: Always — never delete history

Sheet NOTES
A1: =HYPERLINK("#HOME!A1","🏠 HOME") -> 🏠 HOME | C1: =HYPERLINK("#INSTRUCTIONS!A1","📋 GUIDE") -> 📋 GUIDE
A2: Plain language explanations for the users.
B3: WHAT IS THIS FILE?
B4: What is this toolkit? | C4: This Excel file is a payroll preparation tool for the Lao PDR Government. It holds personal, employment, and salary information for 500 civil servants (mock data). When the correct data is entered, it automatically calculates every employee's monthly salary, allowances, deductions, and take-home pay — without any manual arithmetic.
B6: YELLOW AND GREEN CELLS EXPLAINED
B7: Yellow cells — YOU fill these in | C7: Yellow cells are where staff enter or update data. Examples: Employee name, date of birth, date of joining government Education qualification and years of prior work experience Ministry, department, and division (select from dropdown) Service province (select from dropdown) Bank name and branch (select from dropdown) Has Spouse: Yes / No Number of eligible children (0 to 3) RULE: Yellow cells are the ONLY cells you should type into.
B8: Green cells — the file fills automatically | C8: Green cells contain formulas. You never need to type into them. Examples: Grade and Step — calculated from education + years of prior experience Profession Category — identified from the ministry the employee works in Is Remote Area / Is Hazardous — checked from the province of posting Is Foreign Posting — Yes if posted outside Lao PDR Basic Salary — Index Value times Multiplier (from the grade/step table) All allowances and deductions — from rates in master tables Net Salary — Gross Earnings minus total deductions RULE: NEVER type into a green cell. Doing so will break the formula.
B10: HOW SALARY IS CALCULATED — STEP BY STEP
B11: Step 1 — Grade and Step | C11: Every civil servant has a Grade (1 to 10) and a Step (1 to 10). Grade is based on your highest education level: Below Secondary = Grade 1 | Secondary School = Grade 2 Diploma = Grade 3 | Bachelor Degree = Grade 4 Master Degree = Grade 6 | Doctorate (PhD) = Grade 8 Step goes up by 1 for every 2 years of work experience BEFORE joining government. Example: Bachelor degree + 6 years prior experience = Grade 5, Step 4.
B12: Step 2 — Basic Salary | C12: Basic Salary = Index Value x Multiplier Index Value is a LAK amount set by MoF per grade: Grade 1 = 820,000 LAK | Grade 5 = 920,000 LAK | Grade 10 = 1,250,000 LAK Multiplier increases with each grade and step: Grade 1 Step 1 = 1.45x | Grade 10 Step 10 = 8.35x Example: Grade 4, Step 3 = 890,000 LAK x 3.10 = 2,759,000 LAK basic salary
B13: Step 3 — Allowances added on top | C13: These allowances are added to basic salary based on the employee's situation: Position Allowance — based on job title (General Staff up to Minister level) Years of Service Allowance — increases at 5, 10, 15, 20 and 25 years Teaching Allowance — for all Ministry of Education staff Medical Allowance — for all Ministry of Health staff NA Member Allowance — for National Assembly staff Remote Area Allowance — if posted to a remote province Hazardous Area Allowance — if posted to a UXO / security zone province Foreign Living Allowance — if posted abroad Fuel Benefit — if Grade 8 or above Spouse Benefit and Child Benefit — if married or have eligible children
B14: Step 4 — Deductions | C14: Two deductions are made from Gross Earnings: 1. SSO Employee Contribution = 5.5% of Basic Salary (paid to Social Security Organisation / MLSW) 2. Personal Income Tax (PIT) using progressive Lao PDR rates: Taxable Income = Gross Earnings minus SSO Contribution Up to 1,300,000 LAK = 0% (exempt) 1,300,001 to 5,000,000 LAK = 5% 5,000,001 to 10,000,000 LAK = 10% 10,000,001 to 20,000,000 LAK = 15% 20,000,001 to 40,000,000 LAK = 20% Above 40,000,000 LAK = 24%
B15: Step 5 — Net (Take-Home) Salary | C15: Net Salary = Gross Earnings minus Total Deductions (SSO + PIT). This is the amount credited to the employee's bank account each month. Shown in column AE of the PAYROLL_CALC sheet.
B17: DEPENDENT DROPDOWNS — HOW TO USE THEM
B18: How dropdowns work | C18: Many cells have a dropdown arrow. Click the cell, then click the arrow to see the list. The dropdowns are smart — selecting one option narrows choices in the next column: Ministry → Department → Division Country → Province → District Bank → Branch Example: Selecting Ministry of Health shows only MoH departments in the next dropdown. IMPORTANT: Always select in order — Ministry first, then Department, then Division. If you change Ministry after selecting Department, clear Department and re-select.
B19: Position dropdown | C19: The Position dropdown shows only positions relevant to the employee's profession. Ministry of Health staff — see: Doctor, Nurse, Pharmacist, etc. Ministry of Education staff — see: Teacher, Lecturer, Principal, etc. Finance Ministry staff — see: Accountant, Budget Officer, Tax Officer, etc. Profession is automatically detected from the Ministry selected.
B21: WHEN AND HOW TO UPDATE MASTER TABLES
B22: When MoF issues a new salary circular | C22: 1. Go to sheet LK_GradeStep. 2. Find the grade row(s) that changed. 3. Update Column E (Index Value) with the new LAK amount. Same amount for all grades: update all 10 grade rows (G1 through G10). Different amounts per grade: update each grade row separately. 4. All 500 basic salaries update instantly.
B23: When SSO changes the contribution rate | C23: 1. Go to sheet LK_AllowanceRates. 2. Find row 26 (SSO Employee Contribution Rate %). 3. Change the value in Column B to the new rate (e.g. enter 6 for 6%). 4. All 500 SSO deductions update automatically.
B24: When an employee is promoted | C24: 1. Go to EMPLOYEE_MASTER, find the employee's row. 2. If Prior Experience changed, update Column O. Grade and Step will auto-update from education + prior experience. 3. If position title changed, update Column M. Position Level (for allowance) will auto-derive from the new title. 4. PAYROLL_CALC reflects the new salary automatically.
B25: When an employee transfers to a new location | C25: 1. Go to EMPLOYEE_MASTER, find the employee's row. 2. Update Column W (Country), Column X (Province), Column Y (District). Use the dropdowns in order: Country, then Province, then District. 3. Is Remote, Is Hazardous, Is Foreign update automatically from Location Master. 4. Relevant allowances in PAYROLL_CALC turn on or off automatically.
B26: When a new employee joins | C26: 1. Go to EMPLOYEE_MASTER, scroll to row 504 (after last record). 2. Enter a new Employee Code (e.g. LAO00501). 3. Fill all yellow cells using the dropdowns. 4. Enter Prior Experience in Column O — Grade and Step auto-calculate. 5. Go to PAYROLL_CALC row 504, enter the employee code in Column A. 6. Copy the formula row from row 503 and paste (formulas only) into row 504.
B28: WHAT EACH SHEET DOES
B29: EMPLOYEE_MASTER | C29: Main data entry sheet. One row per employee, 45 columns. Covers personal details, employment, grade inputs, organisation, location, bank, and payroll flags. This is the sheet HR officers update most frequently.
B30: PAYROLL_CALC | C30: Monthly payroll output. All cells are formulas — nothing is typed here directly. Each row shows one employee's full salary breakdown: Basic Salary, 12 Allowances, Gross Earnings, SSO, PIT, and Net Salary. Row 504 shows grand totals for all 500 employees.
B31: LK_GradeStep | C31: Rate table for basic salary. 100 rows: 10 grades x 10 steps. Two editable values per row: Column D = Multiplier, Column E = Index Value in LAK. Basic Salary = Index Value x Multiplier.
B32: LK_OrgMaster | C32: Organisation hierarchy: all 18 ministries and provinces with their departments and divisions. Also records profession type and allowance types per organisation. Powers the Ministry to Department to Division dropdown chain.
B33: LK_LocationMaster | C33: Geography table: every province and district in Lao PDR, plus all foreign postings. Each province is tagged Remote (Yes/No) and Hazardous (Yes/No). Powers the Country to Province to District dropdown chain.
B34: LK_BankMaster | C34: Approved banks and branches: 5 banks, 20 branches. Includes branch codes and SWIFT codes. Powers the Bank to Branch dropdown. Branch code and SWIFT auto-fill when selected.
B35: DB_STTM | C35: Database Standard Technical Table Metadata. Technical reference for IT and database teams. Specifies column names, data types, lengths, constraints, primary/foreign keys, and derivation rules for all 9 tables in the payroll database schema.
B36: PROMPT_LOG | C36: Build history of this file. Records every user prompt that led to this toolkit, the version it produced, estimated generation time, and what was built or changed in each iteration.

Sheet EMPLOYEE_MASTER
A1: EMPLOYEE MASTER DATA — Lao PDR Government Payroll | 500 Mock Records | Yellow = Input | Green = Auto-Derived | 🔵 Blue = Audit Trail (Cols AT-AY)
A2: PERSONAL INFORMATION | I2: SERVICE DATES | L2: EMPLOYMENT & GRADE (P/Q AUTO) | R2: IDENTITY CARDS | T2: ORGANISATION ← Dependent Dropdowns | W2: SERVICE LOCATION ← Dependent Dropdowns + Auto-Derived | AD2: RESIDENTIAL ADDRESS | AJ2: BANK DETAILS ← Dependent Dropdowns + Auto-Derived | AO2: PAYROLL FLAGS (Auto-Derived) | AT2: 📅 AUDIT TRAIL — Effective Dates & Change History
A3: Employee Code | B3: Title | C3: First Name | D3: Last Name | E3: Gender | F3: Date of Birth | G3: Email Address | H3: Mobile Number | I3: Date of Joining | J3: Years of Service | K3: Date of Retirement | L3: Employment Type | M3: Position / Designation | N3: Education Qualification | O3: Prior Experience (Yrs before Govt) | P3: Grade | Q3: Step | R3: Civil Service Card ID | S3: Social Security No. | T3: Ministry / Province / Central Org | U3: Department | V3: Division | W3: Service Country | X3: Service Province / Posting | Y3: Service District | Z3: Profession Category | AA3: Is Remote Area | AB3: Is Foreign Posting | AC3: Is Hazardous Area | AD3: House No. | AE3: Street | AF3: Area / Baan | AG3: Province of Residence | AH3: PIN Code | AI3: Country | AJ3: Bank Name | AK3: Bank Branch | AL3: Bank Branch Code | AM3: Bank Account No. | AN3: SWIFT / BIC Code | AO3: Has Spouse | AP3: No. of Eligible Children (max 3) | AQ3: Position Level (for Allowance) | AR3: Is NA Member | AS3: Field Allowance Type | AT3: Effective From (Record Active Date) | AU3: Effective To (Superseded Date) | AV3: Record Created (Date) | AW3: Last Updated (Date) | AX3: Last Updated By (Name / Code) | AY3: Change Remarks
A4: LAO00001 | B4: Mrs. | C4: Khamsone | D4: Bounseng | E4: Female | F4: 25302 | G4: khamsone.bounseng@gov.la | H4: +856 20 94519179 | I4: 43300 | J4: =IFERROR(DATEDIF(I4,TODAY(),"Y"),0) -> 7 | K4: =IFERROR(DATE(YEAR(F4)+60,MONTH(F4),DAY(F4)),"") -> 47217 | L4: Permanent | M4: School Principal | N4: Bachelor's Degree | O4: 25 | P4: =IFERROR(SUMPRODUCT((LK_GradeDerivation!$A$4:$A$135=N4)*(IF(O4="",0,O4)>=LK_GradeDerivation!$B$4:$B$135)*(IF(O4="",0,O4)<=LK_GradeDerivation!$C$4:$C$135)*LK_GradeDerivation!$D$4:$D$135),1) -> 4 | Q4: =IFERROR(SUMPRODUCT((LK_GradeDerivation!$A$4:$A$135=N4)*(IF(O4="",0,O4)>=LK_GradeDerivation!$B$4:$B$135)*(IF(O4="",0,O4)<=LK_GradeDerivation!$C$4:$C$135)*LK_GradeDerivation!$E$4:$E$135),1) -> 13 | R4: CSC000001 | S4: SSO6266630 | T4: Ministry of Education and Sports (MoES) | U4: Department of Primary Education | V4: Curriculum Division | W4: Lao PDR | X4: Sekong | Y4: Lamam | Z4: =IFERROR(VLOOKUP(T4,LK_OrgMaster!$B$4:$H$89,5,FALSE()),"Administration") -> Teacher | AA4: =IFERROR(VLOOKUP(X4,LK_LocationMaster!$D$4:$G$157,4,FALSE()),"No") -> Yes | AB4: =IF(W4="Foreign / International","Yes","No") -> No | AC4: =IFERROR(VLOOKUP(X4,LK_LocationMaster!$D$4:$H$157,5,FALSE()),"No") -> Yes | AD4: No. 738 | AE4: Street 20 | AF4: Baan Kaisone | AG4: Phongsali | AH4: 769100 | AI4: Lao PDR | AJ4: BIC Bank Laos | AK4: BIC Head Office - Vientiane | AL4: =IFERROR(INDEX(LK_BankMaster!$D$4:$D$23,MATCH(AJ4&"|"&AK4,LK_BankMaster!$H$4:$H$23,0)),"") | AM4: 491079829 | AN4: =IFERROR(VLOOKUP(AJ4,LK_BankMaster!$A$4:$E$23,5,FALSE()),"") | AO4: Yes | AP4: 2 | AQ4: =IF(ISNUMBER(SEARCH("Deputy Minister",M4)),"Position Allowance - Deputy Minister",IF(AND(ISNUMBER(SEARCH("Minister",M4)),NOT(ISNUMBER(SEARCH("Deputy",M4)))),"Position Allowance - Minister",IF(ISNUMBER(SEARCH("Deputy Director",M4)),"Position Allowance - Deputy Director",IF(AND(ISNUMBER(SEARCH("Director",M4)),NOT(ISNUMBER(SEARCH("Deputy",M4)))),"Position Allowance - Director",IF(ISNUMBER(SEARCH("Division Chief",M4)),"Position Allowance - Division Chief",IF(ISNUMBER(SEARCH("Section Chief",M4)),"Position Allowance - Section Chief","Position Allowance - General Staff")))))) -> Position Allowance - General Staff | AR4: =IFERROR(VLOOKUP(T4,LK_OrgMaster!$B$4:$G$89,6,FALSE()),"No") -> No | AS4: =IFERROR(VLOOKUP(T4,LK_OrgMaster!$B$4:$H$89,7,FALSE()),"None") -> Teaching | AT4: 43300 | AV4: 43300 | AW4: 46023 | AX4: Initial Load | AY4: Record created during payroll system initial data load (Jan 2026).
A5: LAO00002 | B5: Ms. | C5: Sisamone | D5: Vilayvong | E5: Female | F5: 33143 | G5: sisamone.vilayvon@gov.la | H5: +856 20 81204829 | I5: 32641 | J5: =IFERROR(DATEDIF(I5,TODAY(),"Y"),0) -> 36 | K5: =IFERROR(DATE(YEAR(F5)+60,MONTH(F5),DAY(F5)),"") -> 55058 | L5: Permanent | M5: Senior Officer | N5: Master's Degree | O5: 0 | P5: =IFERROR(SUMPRODUCT((LK_GradeDerivation!$A$4:$A$135=N5)*(IF(O5="",0,O5)>=LK_GradeDerivation!$B$4:$B$135)*(IF(O5="",0,O5)<=LK_GradeDerivation!$C$4:$C$135)*LK_GradeDerivation!$D$4:$D$135),1) -> 5 | Q5: =IFERROR(SUMPRODUCT((LK_GradeDerivation!$A$4:$A$135=N5)*(IF(O5="",0,O5)>=LK_GradeDerivation!$B$4:$B$135)*(IF(O5="",0,O5)<=LK_GradeDerivation!$C$4:$C$135)*LK_GradeDerivation!$E$4:$E$135),1) -> 1 | R5: CSC000002 | S5: SSO6406444 | T5: National Assembly (NA) | U5: Committee on Economy & Finance | V5: Administrative Division | W5: Lao PDR | X5: Vientiane Capital | Y5: Chanthabouli | Z5: =IFERROR(VLOOKUP(T5,LK_OrgMaster!$B$4:$H$89,5,FALSE()),"Administration") -> Administration | AA5: =IFERROR(VLOOKUP(X5,LK_LocationMaster!$D$4:$G$157,4,FALSE()),"No") -> No | AB5: =IF(W5="Foreign / International","Yes","No") -> No | AC5: =IFERROR(VLOOKUP(X5,LK_LocationMaster!$D$4:$H$157,5,FALSE()),"No") -> No | AD5: No. 453 | AE5: Setthathirath Road | AF5: Baan Nongping | AG5: Sayabouli | AH5: 875200 | AI5: Lao PDR | AJ5: Agriculture Promotion Bank (APB) | AK5: APB Luang Prabang Branch | AL5: =IFERROR(INDEX(LK_BankMaster!$D$4:$D$23,MATCH(AJ5&"|"&AK5,LK_BankMaster!$H$4:$H$23,0)),"") | AM5: 325681936 | AN5: =IFERROR(VLOOKUP(AJ5,LK_BankMaster!$A$4:$E$23,5,FALSE()),"") | AO5: Yes | AP5: 3 | AQ5: =IF(ISNUMBER(SEARCH("Deputy Minister",M5)),"Position Allowance - Deputy Minister",IF(AND(ISNUMBER(SEARCH("Minister",M5)),NOT(ISNUMBER(SEARCH("Deputy",M5)))),"Position Allowance - Minister",IF(ISNUMBER(SEARCH("Deputy Director",M5)),"Position Allowance - Deputy Director",IF(AND(ISNUMBER(SEARCH("Director",M5)),NOT(ISNUMBER(SEARCH("Deputy",M5)))),"Position Allowance - Director",IF(ISNUMBER(SEARCH("Division Chief",M5)),"Position Allowance - Division Chief",IF(ISNUMBER(SEARCH("Section Chief",M5)),"Position Allowance - Section Chief","Position Allowance - General Staff")))))) -> Position Allowance - General Staff | AR5: =IFERROR(VLOOKUP(T5,LK_OrgMaster!$B$4:$G$89,6,FALSE()),"No") -> Yes | AS5: =IFERROR(VLOOKUP(T5,LK_OrgMaster!$B$4:$H$89,7,FALSE()),"None") -> None | AT5: 32641 | AV5: 32641 | AW5: 46023 | AX5: Initial Load | AY5: Record created during payroll system initial data load (Jan 2026).
A6: LAO00003 | B6: Dr. | C6: Keovilay | D6: Sisouvath | E6: Male | F6: 29953 | G6: keovilay.sisouvat@gov.la | H6: +856 20 98207378 | I6: 40638 | J6: =IFERROR(DATEDIF(I6,TODAY(),"Y"),0) -> 14 | K6: =IFERROR(DATE(YEAR(F6)+60,MONTH(F6),DAY(F6)),"") -> 51868 | L6: Permanent | M6: Nurse | N6: Secondary School (Grade 12) | O6: 11 | P6: =IFERROR(SUMPRODUCT((LK_GradeDerivation!$A$4:$A$135=N6)*(IF(O6="",0,O6)>=LK_GradeDerivation!$B$4:$B$135)*(IF(O6="",0,O6)<=LK_GradeDerivation!$C$4:$C$135)*LK_GradeDerivation!$D$4:$D$135),1) -> 2 | Q6: =IFERROR(SUMPRODUCT((LK_GradeDerivation!$A$4:$A$135=N6)*(IF(O6="",0,O6)>=LK_GradeDerivation!$B$4:$B$135)*(IF(O6="",0,O6)<=LK_GradeDerivation!$C$4:$C$135)*LK_GradeDerivation!$E$4:$E$135),1) -> 6 | R6: CSC000003 | S6: SSO4262081 | T6: Ministry of Health (MoH) | U6: Department of Planning & Finance | V6: Health Financing Division | W6: Lao PDR | X6: Champasak | Y6: Khong | Z6: =IFERROR(VLOOKUP(T6,LK_OrgMaster!$B$4:$H$89,5,FALSE()),"Administration") -> Medical | AA6: =IFERROR(VLOOKUP(X6,LK_LocationMaster!$D$4:$G$157,4,FALSE()),"No") -> No | AB6: =IF(W6="Foreign / International","Yes","No") -> No | AC6: =IFERROR(VLOOKUP(X6,LK_LocationMaster!$D$4:$H$157,5,FALSE()),"No") -> No | AD6: No. 507 | AE6: Setthathirath Road | AF6: Baan Dongpalane | AG6: Huaphan | AH6: 109000 | AI6: Lao PDR | AJ6: BCEL (Banque pour le Commerce Exterieur Lao) | AK6: BCEL Oudomxay Branch | AL6: =IFERROR(INDEX(LK_BankMaster!$D$4:$D$23,MATCH(AJ6&"|"&AK6,LK_BankMaster!$H$4:$H$23,0)),"") | AM6: 545002643 | AN6: =IFERROR(VLOOKUP(AJ6,LK_BankMaster!$A$4:$E$23,5,FALSE()),"") | AO6: No | AP6: 0 | AQ6: =IF(ISNUMBER(SEARCH("Deputy Minister",M6)),"Position Allowance - Deputy Minister",IF(AND(ISNUMBER(SEARCH("Minister",M6)),NOT(ISNUMBER(SEARCH("Deputy",M6)))),"Position Allowance - Minister",IF(ISNUMBER(SEARCH("Deputy Director",M6)),"Position Allowance - Deputy Director",IF(AND(ISNUMBER(SEARCH("Director",M6)),NOT(ISNUMBER(SEARCH("Deputy",M6)))),"Position Allowance - Director",IF(ISNUMBER(SEARCH("Division Chief",M6)),"Position Allowance - Division Chief",IF(ISNUMBER(SEARCH("Section Chief",M6)),"Position Allowance - Section Chief","Position Allowance - General Staff")))))) -> Position Allowance - General Staff | AR6: =IFERROR(VLOOKUP(T6,LK_OrgMaster!$B$4:$G$89,6,FALSE()),"No") -> No | AS6: =IFERROR(VLOOKUP(T6,LK_OrgMaster!$B$4:$H$89,7,FALSE()),"None") -> Medical | AT6: 40638 | AV6: 40638 | AW6: 46023 | AX6: Initial Load | AY6: Record created during payroll system initial data load (Jan 2026).
A7: LAO00004 | B7: Dr. | C7: Sengphet | D7: Sengmixay | E7: Male | F7: 31646 | G7: sengphet.sengmixa@gov.la | H7: +856 20 78638087 | I7: 43317 | J7: =IFERROR(DATEDIF(I7,TODAY(),"Y"),0) -> 7 | K7: =IFERROR(DATE(YEAR(F7)+60,MONTH(F7),DAY(F7)),"") -> 53561 | L7: Permanent | M7: Primary School Teacher | N7: Bachelor's Degree | O7: 9 | P7: =IFERROR(SUMPRODUCT((LK_GradeDerivation!$A$4:$A$135=N7)*(IF(O7="",0,O7)>=LK_GradeDerivation!$B$4:$B$135)*(IF(O7="",0,O7)<=LK_GradeDerivation!$C$4:$C$135)*LK_GradeDerivation!$D$4:$D$135),1) -> 4 | Q7: =IFERROR(SUMPRODUCT((LK_GradeDerivation!$A$4:$A$135=N7)*(IF(O7="",0,O7)>=LK_GradeDerivation!$B$4:$B$135)*(IF(O7="",0,O7)<=LK_GradeDerivation!$C$4:$C$135)*LK_GradeDerivation!$E$4:$E$135),1) -> 5 | R7: CSC000004 | S7: SSO9468772 | T7: Ministry of Education and Sports (MoES) | U7: Department of Primary Education | V7: Administrative Division | W7: Lao PDR | X7: Xaysomboun | Y7: Longcheng | Z7: =IFERROR(VLOOKUP(T7,LK_OrgMaster!$B$4:$H$89,5,FALSE()),"Administration") -> Teacher | AA7: =IFERROR(VLOOKUP(X7,LK_LocationMaster!$D$4:$G$157,4,FALSE()),"No") -> Yes | AB7: =IF(W7="Foreign / International","Yes","No") -> No | AC7: =IFERROR(VLOOKUP(X7,LK_LocationMaster!$D$4:$H$157,5,FALSE()),"No") -> Yes | AD7: No. 919 | AE7: Nong Bone Road | AF7: Baan Saphanthong | AG7: Sayabouli | AH7: 524600 | AI7: Lao PDR | AJ7: Agriculture Promotion Bank (APB) | AK7: APB Khammuane Branch | AL7: =IFERROR(INDEX(LK_BankMaster!$D$4:$D$23,MATCH(AJ7&"|"&AK7,LK_BankMaster!$H$4:$H$23,0)),"") | AM7: 757830420 | AN7: =IFERROR(VLOOKUP(AJ7,LK_BankMaster!$A$4:$E$23,5,FALSE()),"") | AO7: No | AP7: 0 | AQ7: =IF(ISNUMBER(SEARCH("Deputy Minister",M7)),"Position Allowance - Deputy Minister",IF(AND(ISNUMBER(SEARCH("Minister",M7)),NOT(ISNUMBER(SEARCH("Deputy",M7)))),"Position Allowance - Minister",IF(ISNUMBER(SEARCH("Deputy Director",M7)),"Position Allowance - Deputy Director",IF(AND(ISNUMBER(SEARCH("Director",M7)),NOT(ISNUMBER(SEARCH("Deputy",M7)))),"Position Allowance - Director",IF(ISNUMBER(SEARCH("Division Chief",M7)),"Position Allowance - Division Chief",IF(ISNUMBER(SEARCH("Section Chief",M7)),"Position Allowance - Section Chief","Position Allowance - General Staff")))))) -> Position Allowance - General Staff | AR7: =IFERROR(VLOOKUP(T7,LK_OrgMaster!$B$4:$G$89,6,FALSE()),"No") -> No | AS7: =IFERROR(VLOOKUP(T7,LK_OrgMaster!$B$4:$H$89,7,FALSE()),"None") -> Teaching | AT7: 43317 | AV7: 43317 | AW7: 46023 | AX7: Initial Load | AY7: Record created during payroll system initial data load (Jan 2026).
A8: LAO00005 | B8: Mrs. | C8: Vilaychith | D8: Phommachack | E8: Female | F8: 30485 | G8: vilaychith.phommach@gov.la | H8: +856 20 72205074 | I8: 40309 | J8: =IFERROR(DATEDIF(I8,TODAY(),"Y"),0) -> 15 | K8: =IFERROR(DATE(YEAR(F8)+60,MONTH(F8),DAY(F8)),"") -> 52400 | L8: Permanent | M8: Dental Officer | N8: Secondary School (Grade 12) | O8: 8 | P8: =IFERROR(SUMPRODUCT((LK_GradeDerivation!$A$4:$A$135=N8)*(IF(O8="",0,O8)>=LK_GradeDerivation!$B$4:$B$135)*(IF(O8="",0,O8)<=LK_GradeDerivation!$C$4:$C$135)*LK_GradeDerivation!$D$4:$D$135),1) -> 2 | Q8: =IFERROR(SUMPRODUCT((LK_GradeDerivation!$A$4:$A$135=N8)*(IF(O8="",0,O8)>=LK_GradeDerivation!$B$4:$B$135)*(IF(O8="",0,O8)<=LK_GradeDerivation!$C$4:$C$135)*LK_GradeDerivation!$E$4:$E$135),1) -> 5 | R8: CSC000005 | S8: SSO7838382 | T8: Ministry of Health (MoH) | U8: Department of Hygiene & Health Promotion | V8: Environmental Health Division | W8: Lao PDR | X8: Bokeo | Y8: Ton Pheung | Z8: =IFERROR(VLOOKUP(T8,LK_OrgMaster!$B$4:$H$89,5,FALSE()),"Administration") -> Medical | AA8: =IFERROR(VLOOKUP(X8,LK_LocationMaster!$D$4:$G$157,4,FALSE()),"No") -> Yes | AB8: =IF(W8="Foreign / International","Yes","No") -> No | AC8: =IFERROR(VLOOKUP(X8,LK_LocationMaster!$D$4:$H$157,5,FALSE()),"No") -> No | AD8: No. 426 | AE8: Setthathirath Road | AF8: Baan Phonthong | AG8: Sayabouli | AH8: 738100 | AI8: Lao PDR | AJ8: Joint Development Bank (JDB) | AK8: JDB Vientiane Branch | AL8: =IFERROR(INDEX(LK_BankMaster!$D$4:$D$23,MATCH(AJ8&"|"&AK8,LK_BankMaster!$H$4:$H$23,0)),"") | AM8: 858511779 | AN8: =IFERROR(VLOOKUP(AJ8,LK_BankMaster!$A$4:$E$23,5,FALSE()),"") | AO8: Yes | AP8: 3 | AQ8: =IF(ISNUMBER(SEARCH("Deputy Minister",M8)),"Position Allowance - Deputy Minister",IF(AND(ISNUMBER(SEARCH("Minister",M8)),NOT(ISNUMBER(SEARCH("Deputy",M8)))),"Position Allowance - Minister",IF(ISNUMBER(SEARCH("Deputy Director",M8)),"Position Allowance - Deputy Director",IF(AND(ISNUMBER(SEARCH("Director",M8)),NOT(ISNUMBER(SEARCH("Deputy",M8)))),"Position Allowance - Director",IF(ISNUMBER(SEARCH("Division Chief",M8)),"Position Allowance - Division Chief",IF(ISNUMBER(SEARCH("Section Chief",M8)),"Position Allowance - Section Chief","Position Allowance - General Staff")))))) -> Position Allowance - General Staff | AR8: =IFERROR(VLOOKUP(T8,LK_OrgMaster!$B$4:$G$89,6,FALSE()),"No") -> No | AS8: =IFERROR(VLOOKUP(T8,LK_OrgMaster!$B$4:$H$89,7,FALSE()),"None") -> Medical | AT8: 40309 | AV8: 40309 | AW8: 46023 | AX8: Initial Load | AY8: Record created during payroll system initial data load (Jan 2026).
A9: LAO00006 | B9: Mrs. | C9: Phonethip | D9: Phommavong | E9: Female | F9: 27663 | G9: phonethip.phommavo@gov.la | H9: +856 20 94887348 | I9: 33596 | J9: =IFERROR(DATEDIF(I9,TODAY(),"Y"),0) -> 34 | K9: =IFERROR(DATE(YEAR(F9)+60,MONTH(F9),DAY(F9)),"") -> 49578 | L9: Permanent | M9: Senior Doctor | N9: Master's Degree | O9: 0 | P9: =IFERROR(SUMPRODUCT((LK_GradeDerivation!$A$4:$A$135=N9)*(IF(O9="",0,O9)>=LK_GradeDerivation!$B$4:$B$135)*(IF(O9="",0,O9)<=LK_GradeDerivation!$C$4:$C$135)*LK_GradeDerivation!$D$4:$D$135),1) -> 5 | Q9: =IFERROR(SUMPRODUCT((LK_GradeDerivation!$A$4:$A$135=N9)*(IF(O9="",0,O9)>=LK_GradeDerivation!$B$4:$B$135)*(IF(O9="",0,O9)<=LK_GradeDerivation!$C$4:$C$135)*LK_GradeDerivation!$E$4:$E$135),1) -> 1 | R9: CSC000006 | S9: SSO6639317 | T9: Ministry of Health (MoH) | U9: Department of Personnel & Organisation | V9: Recruitment Division | W9: Lao PDR | X9: Sayabouli | Y9: Kenethao | Z9: =IFERROR(VLOOKUP(T9,LK_OrgMaster!$B$4:$H$89,5,FALSE()),"Administration") -> Medical | AA9: =IFERROR(VLOOKUP(X9,LK_LocationMaster!$D$4:$G$157,4,FALSE()),"No") -> Yes | AB9: =IF(W9="Foreign / International","Yes","No") -> No | AC9: =IFERROR(VLOOKUP(X9,LK_LocationMaster!$D$4:$H$157,5,FALSE()),"No") -> No | AD9: No. 742 | AE9: Nong Bone Road | AF9: Baan Dongpalane | AG9: Huaphan | AH9: 975100 | AI9: Lao PDR | AJ9: Lao Development Bank (LDB) | AK9: LDB Pakse Branch | AL9: =IFERROR(INDEX(LK_BankMaster!$D$4:$D$23,MATCH(AJ9&"|"&AK9,LK_BankMaster!$H$4:$H$23,0)),"") | AM9: 567975319 | AN9: =IFERROR(VLOOKUP(AJ9,LK_BankMaster!$A$4:$E$23,5,FALSE()),"") | AO9: Yes | AP9: 3 | AQ9: =IF(ISNUMBER(SEARCH("Deputy Minister",M9)),"Position Allowance - Deputy Minister",IF(AND(ISNUMBER(SEARCH("Minister",M9)),NOT(ISNUMBER(SEARCH("Deputy",M9)))),"Position Allowance - Minister",IF(ISNUMBER(SEARCH("Deputy Director",M9)),"Position Allowance - Deputy Director",IF(AND(ISNUMBER(SEARCH("Director",M9)),NOT(ISNUMBER(SEARCH("Deputy",M9)))),"Position Allowance - Director",IF(ISNUMBER(SEARCH("Division Chief",M9)),"Position Allowance - Division Chief",IF(ISNUMBER(SEARCH("Section Chief",M9)),"Position Allowance - Section Chief","Position Allowance - General Staff")))))) -> Position Allowance - General Staff | AR9: =IFERROR(VLOOKUP(T9,LK_OrgMaster!$B$4:$G$89,6,FALSE()),"No") -> No | AS9: =IFERROR(VLOOKUP(T9,LK_OrgMaster!$B$4:$H$89,7,FALSE()),"None") -> Medical | AT9: 33596 | AV9: 33596 | AW9: 46023 | AX9: Initial Load | AY9: Record created during payroll system initial data load (Jan 2026).
A10: LAO00007 | B10: Dr. | C10: Phonesavanh | D10: Soulinthong | E10: Male | F10: 33031 | G10: phonesavanh.soulinth@gov.la | H10: +856 20 51300790 | I10: 44694 | J10: =IFERROR(DATEDIF(I10,TODAY(),"Y"),0) -> 3 | K10: =IFERROR(DATE(YEAR(F10)+60,MONTH(F10),DAY(F10)),"") -> 54946 | L10: Permanent | M10: Department Director | N10: Master's Degree | O10: 6 | P10: =IFERROR(SUMPRODUCT((LK_GradeDerivation!$A$4:$A$135=N10)*(IF(O10="",0,O10)>=LK_GradeDerivation!$B$4:$B$135)*(IF(O10="",0,O10)<=LK_GradeDerivation!$C$4:$C$135)*LK_GradeDerivation!$D$4:$D$135),1) -> 5 | Q10: =IFERROR(SUMPRODUCT((LK_GradeDerivation!$A$4:$A$135=N10)*(IF(O10="",0,O10)>=LK_GradeDerivation!$B$4:$B$135)*(IF(O10="",0,O10)<=LK_GradeDerivation!$C$4:$C$135)*LK_GradeDerivation!$E$4:$E$135),1) -> 4 | R10: CSC000007 | S10: SSO8890439 | T10: Ministry of Industry & Commerce (MoIC) | U10: Department of Industry | V10: Administrative Division | W10: Lao PDR | X10: Bolikhamxay | Y10: Bolikhanh | Z10: =IFERROR(VLOOKUP(T10,LK_OrgMaster!$B$4:$H$89,5,FALSE()),"Administration") -> Administration | AA10: =IFERROR(VLOOKUP(X10,LK_LocationMaster!$D$4:$G$157,4,FALSE()),"No") -> No | AB10: =IF(W10="Foreign / International","Yes","No") -> No | AC10: =IFERROR(VLOOKUP(X10,LK_LocationMaster!$D$4:$H$157,5,FALSE()),"No") -> No | AD10: No. 975 | AE10: Setthathirath Road | AF10: Baan Nongchanh | AG10: Vientiane Capital | AH10: 165900 | AI10: Lao PDR | AJ10: Agriculture Promotion Bank (APB) | AK10: APB Khammuane Branch | AL10: =IFERROR(INDEX(LK_BankMaster!$D$4:$D$23,MATCH(AJ10&"|"&AK10,LK_BankMaster!$H$4:$H$23,0)),"") | AM10: 370874491 | AN10: =IFERROR(VLOOKUP(AJ10,LK_BankMaster!$A$4:$E$23,5,FALSE()),"") | AO10: No | AP10: 0 | AQ10: =IF(ISNUMBER(SEARCH("Deputy Minister",M10)),"Position Allowance - Deputy Minister",IF(AND(ISNUMBER(SEARCH("Minister",M10)),NOT(ISNUMBER(SEARCH("Deputy",M10)))),"Position Allowance - Minister",IF(ISNUMBER(SEARCH("Deputy Director",M10)),"Position Allowance - Deputy Director",IF(AND(ISNUMBER(SEARCH("Director",M10)),NOT(ISNUMBER(SEARCH("Deputy",M10)))),"Position Allowance - Director",IF(ISNUMBER(SEARCH("Division Chief",M10)),"Position Allowance - Division Chief",IF(ISNUMBER(SEARCH("Section Chief",M10)),"Position Allowance - Section Chief","Position Allowance - General Staff")))))) -> Position Allowance - Director | AR10: =IFERROR(VLOOKUP(T10,LK_OrgMaster!$B$4:$G$89,6,FALSE()),"No") -> No | AS10: =IFERROR(VLOOKUP(T10,LK_OrgMaster!$B$4:$H$89,7,FALSE()),"None") -> None | AT10: 44694 | AV10: 44694 | AW10: 46023 | AX10: Initial Load | AY10: Record created during payroll system initial data load (Jan 2026).
A11: LAO00008 | B11: Mr. | C11: Bounma | D11: Phongphichith | E11: Male | F11: 26168 | G11: bounma.phongphi@gov.la | H11: +856 20 57254384 | I11: 43380 | J11: =IFERROR(DATEDIF(I11,TODAY(),"Y"),0) -> 7 | K11: =IFERROR(DATE(YEAR(F11)+60,MONTH(F11),DAY(F11)),"") -> 48083 | L11: Permanent | M11: IT Officer | N11: Secondary School (Grade 12) | O11: 25 | P11: =IFERROR(SUMPRODUCT((LK_GradeDerivation!$A$4:$A$135=N11)*(IF(O11="",0,O11)>=LK_GradeDerivation!$B$4:$B$135)*(IF(O11="",0,O11)<=LK_GradeDerivation!$C$4:$C$135)*LK_GradeDerivation!$D$4:$D$135),1) -> 2 | Q11: =IFERROR(SUMPRODUCT((LK_GradeDerivation!$A$4:$A$135=N11)*(IF(O11="",0,O11)>=LK_GradeDerivation!$B$4:$B$135)*(IF(O11="",0,O11)<=LK_GradeDerivation!$C$4:$C$135)*LK_GradeDerivation!$E$4:$E$135),1) -> 13 | R11: CSC000008 | S11: SSO6218367 | T11: Ministry of Public Works & Transport (MPWT) | U11: Department of Roads | V11: Road Construction Division | W11: Lao PDR | X11: Khammuane | Y11: Nongbok | Z11: =IFERROR(VLOOKUP(T11,LK_OrgMaster!$B$4:$H$89,5,FALSE()),"Administration") -> Technical | AA11: =IFERROR(VLOOKUP(X11,LK_LocationMaster!$D$4:$G$157,4,FALSE()),"No") -> No | AB11: =IF(W11="Foreign / International","Yes","No") -> No | AC11: =IFERROR(VLOOKUP(X11,LK_LocationMaster!$D$4:$H$157,5,FALSE()),"No") -> Yes | AD11: No. 952 | AE11: Street 20 | AF11: Baan Phonthong | AG11: Vientiane Capital | AH11: 749800 | AI11: Lao PDR | AJ11: BIC Bank Laos | AK11: BIC Head Office - Vientiane | AL11: =IFERROR(INDEX(LK_BankMaster!$D$4:$D$23,MATCH(AJ11&"|"&AK11,LK_BankMaster!$H$4:$H$23,0)),"") | AM11: 935147672 | AN11: =IFERROR(VLOOKUP(AJ11,LK_BankMaster!$A$4:$E$23,5,FALSE()),"") | AO11: No | AP11: 0 | AQ11: =IF(ISNUMBER(SEARCH("Deputy Minister",M11)),"Position Allowance - Deputy Minister",IF(AND(ISNUMBER(SEARCH("Minister",M11)),NOT(ISNUMBER(SEARCH("Deputy",M11)))),"Position Allowance - Minister",IF(ISNUMBER(SEARCH("Deputy Director",M11)),"Position Allowance - Deputy Director",IF(AND(ISNUMBER(SEARCH("Director",M11)),NOT(ISNUMBER(SEARCH("Deputy",M11)))),"Position Allowance - Director",IF(ISNUMBER(SEARCH("Division Chief",M11)),"Position Allowance - Division Chief",IF(ISNUMBER(SEARCH("Section Chief",M11)),"Position Allowance - Section Chief","Position Allowance - General Staff")))))) -> Position Allowance - General Staff | AR11: =IFERROR(VLOOKUP(T11,LK_OrgMaster!$B$4:$G$89,6,FALSE()),"No") -> No | AS11: =IFERROR(VLOOKUP(T11,LK_OrgMaster!$B$4:$H$89,7,FALSE()),"None") -> None | AT11: 43380 | AV11: 43380 | AW11: 46023 | AX11: Initial Load | AY11: Record created during payroll system initial data load (Jan 2026).
A12: LAO00009 | B12: Mr. | C12: Khanthavy | D12: Sengmixay | E12: Male | F12: 29963 | G12: khanthavy.sengmixa@gov.la | H12: +856 20 57082593 | I12: 43399 | J12: =IFERROR(DATEDIF(I12,TODAY(),"Y"),0) -> 7 | K12: =IFERROR(DATE(YEAR(F12)+60,MONTH(F12),DAY(F12)),"") -> 51878 | L12: Permanent | M12: Nurse | N12: Bachelor's Degree | O12: 14 | P12: =IFERROR(SUMPRODUCT((LK_GradeDerivation!$A$4:$A$135=N12)*(IF(O12="",0,O12)>=LK_GradeDerivation!$B$4:$B$135)*(IF(O12="",0,O12)<=LK_GradeDerivation!$C$4:$C$135)*LK_GradeDerivation!$D$4:$D$135),1) -> 4 | Q12: =IFERROR(SUMPRODUCT((LK_GradeDerivation!$A$4:$A$135=N12)*(IF(O12="",0,O12)>=LK_GradeDerivation!$B$4:$B$135)*(IF(O12="",0,O12)<=LK_GradeDerivation!$C$4:$C$135)*LK_GradeDerivation!$E$4:$E$135),1) -> 8 | R12: CSC000009 | S12: SSO9224219 | T12: Ministry of Health (MoH) | U12: Department of Planning & Finance | V12: Health Financing Division | W12: Lao PDR | X12: Khammuane | Y12: Mahaxay | Z12: =IFERROR(VLOOKUP(T12,LK_OrgMaster!$B$4:$H$89,5,FALSE()),"Administration") -> Medical | AA12: =IFERROR(VLOOKUP(X12,LK_LocationMaster!$D$4:$G$157,4,FALSE()),"No") -> No | AB12: =IF(W12="Foreign / International","Yes","No") -> No | AC12: =IFERROR(VLOOKUP(X12,LK_LocationMaster!$D$4:$H$157,5,FALSE()),"No") -> Yes | AD12: No. 984 | AE12: Nong Bone Road | AF12: Baan Dongpalane | AG12: Huaphan | AH12: 813500 | AI12: Lao PDR | AJ12: BIC Bank Laos | AK12: BIC Head Office - Vientiane | AL12: =IFERROR(INDEX(LK_BankMaster!$D$4:$D$23,MATCH(AJ12&"|"&AK12,LK_BankMaster!$H$4:$H$23,0)),"") | AM12: 113585139 | AN12: =IFERROR(VLOOKUP(AJ12,LK_BankMaster!$A$4:$E$23,5,FALSE()),"") | AO12: No | AP12: 0 | AQ12: =IF(ISNUMBER(SEARCH("Deputy Minister",M12)),"Position Allowance - Deputy Minister",IF(AND(ISNUMBER(SEARCH("Minister",M12)),NOT(ISNUMBER(SEARCH("Deputy",M12)))),"Position Allowance - Minister",IF(ISNUMBER(SEARCH("Deputy Director",M12)),"Position Allowance - Deputy Director",IF(AND(ISNUMBER(SEARCH("Director",M12)),NOT(ISNUMBER(SEARCH("Deputy",M12)))),"Position Allowance - Director",IF(ISNUMBER(SEARCH("Division Chief",M12)),"Position Allowance - Division Chief",IF(ISNUMBER(SEARCH("Section Chief",M12)),"Position Allowance - Section Chief","Position Allowance - General Staff")))))) -> Position Allowance - General Staff | AR12: =IFERROR(VLOOKUP(T12,LK_OrgMaster!$B$4:$G$89,6,FALSE()),"No") -> No | AS12: =IFERROR(VLOOKUP(T12,LK_OrgMaster!$B$4:$H$89,7,FALSE()),"None") -> Medical | AT12: 43399 | AV12: 43399 | AW12: 46023 | AX12: Initial Load | AY12: Record created during payroll system initial data load (Jan 2026).
A13: LAO00010 | B13: Dr. | C13: Manyvone | D13: Phiaylack | E13: Female | F13: 29806 | G13: manyvone.phiaylac@gov.la | H13: +856 20 67337736 | I13: 40218 | J13: =IFERROR(DATEDIF(I13,TODAY(),"Y"),0) -> 16 | K13: =IFERROR(DATE(YEAR(F13)+60,MONTH(F13),DAY(F13)),"") -> 51721 | L13: Permanent | M13: Senior Legal Advisor | N13: Master's Degree | O13: 3 | P13: =IFERROR(SUMPRODUCT((LK_GradeDerivation!$A$4:$A$135=N13)*(IF(O13="",0,O13)>=LK_GradeDerivation!$B$4:$B$135)*(IF(O13="",0,O13)<=LK_GradeDerivation!$C$4:$C$135)*LK_GradeDerivation!$D$4:$D$135),1) -> 5 | Q13: =IFERROR(SUMPRODUCT((LK_GradeDerivation!$A$4:$A$135=N13)*(IF(O13="",0,O13)>=LK_GradeDerivation!$B$4:$B$135)*(IF(O13="",0,O13)<=LK_GradeDerivation!$C$4:$C$135)*LK_GradeDerivation!$E$4:$E$135),1) -> 2 | R13: CSC000010 | S13: SSO6952975 | T13: Ministry of Justice (MoJ) | U13: Department of Judicial Administration | V13: Legal Aid Division | W13: Lao PDR | X13: Savannakhet | Y13: Champhone | Z13: =IFERROR(VLOOKUP(T13,LK_OrgMaster!$B$4:$H$89,5,FALSE()),"Administration") -> Legal | AA13: =IFERROR(VLOOKUP(X13,LK_LocationMaster!$D$4:$G$157,4,FALSE()),"No") -> No | AB13: =IF(W13="Foreign / International","Yes","No") -> No | AC13: =IFERROR(VLOOKUP(X13,LK_LocationMaster!$D$4:$H$157,5,FALSE()),"No") -> Yes | AD13: No. 287 | AE13: Samsenthai Road | AF13: Baan Nongping | AG13: Luang Prabang | AH13: 116600 | AI13: Lao PDR | AJ13: BCEL (Banque pour le Commerce Exterieur Lao) | AK13: BCEL Oudomxay Branch | AL13: =IFERROR(INDEX(LK_BankMaster!$D$4:$D$23,MATCH(AJ13&"|"&AK13,LK_BankMaster!$H$4:$H$23,0)),"") | AM13: 448981305 | AN13: =IFERROR(VLOOKUP(AJ13,LK_BankMaster!$A$4:$E$23,5,FALSE()),"") | AO13: Yes | AP13: 1 | AQ13: =IF(ISNUMBER(SEARCH("Deputy Minister",M13)),"Position Allowance - Deputy Minister",IF(AND(ISNUMBER(SEARCH("Minister",M13)),NOT(ISNUMBER(SEARCH("Deputy",M13)))),"Position Allowance - Minister",IF(ISNUMBER(SEARCH("Deputy Director",M13)),"Position Allowance - Deputy Director",IF(AND(ISNUMBER(SEARCH("Director",M13)),NOT(ISNUMBER(SEARCH("Deputy",M13)))),"Position Allowance - Director",IF(ISNUMBER(SEARCH("Division Chief",M13)),"Position Allowance - Division Chief",IF(ISNUMBER(SEARCH("Section Chief",M13)),"Position Allowance - Section Chief","Position Allowance - General Staff")))))) -> Position Allowance - General Staff | AR13: =IFERROR(VLOOKUP(T13,LK_OrgMaster!$B$4:$G$89,6,FALSE()),"No") -> No | AS13: =IFERROR(VLOOKUP(T13,LK_OrgMaster!$B$4:$H$89,7,FALSE()),"None") -> None | AT13: 40218 | AV13: 40218 | AW13: 46023 | AX13: Initial Load | AY13: Record created during payroll system initial data load (Jan 2026).
A14: LAO00011 | B14: Dr. | C14: Vongphet | D14: Bounseng | E14: Male | F14: 31639 | G14: vongphet.bounseng@gov.la | H14: +856 20 94557602 | I14: 35026 | J14: =IFERROR(DATEDIF(I14,TODAY(),"Y"),0) -> 30 | K14: =IFERROR(DATE(YEAR(F14)+60,MONTH(F14),DAY(F14)),"") -> 53554 | L14: Permanent | M14: Officer | N14: Bachelor's Degree | O14: 0 | P14: =IFERROR(SUMPRODUCT((LK_GradeDerivation!$A$4:$A$135=N14)*(IF(O14="",0,O14)>=LK_GradeDerivation!$B$4:$B$135)*(IF(O14="",0,O14)<=LK_GradeDerivation!$C$4:$C$135)*LK_GradeDerivation!$D$4:$D$135),1) -> 4 | Q14: =IFERROR(SUMPRODUCT((LK_GradeDerivation!$A$4:$A$135=N14)*(IF(O14="",0,O14)>=LK_GradeDerivation!$B$4:$B$135)*(IF(O14="",0,O14)<=LK_GradeDerivation!$C$4:$C$135)*LK_GradeDerivation!$E$4:$E$135),1) -> 1 | R14: CSC000011 | S14: SSO6137284 | T14: Vientiane Capital Administration | U14: Department of Administration | V14: Records Division | W14: Lao PDR | X14: Vientiane Capital | Y14: Chanthabouli | Z14: =IFERROR(VLOOKUP(T14,LK_OrgMaster!$B$4:$H$89,5,FALSE()),"Administration") -> Administration | AA14: =IFERROR(VLOOKUP(X14,LK_LocationMaster!$D$4:$G$157,4,FALSE()),"No") -> No | AB14: =IF(W14="Foreign / International","Yes","No") -> No | AC14: =IFERROR(VLOOKUP(X14,LK_LocationMaster!$D$4:$H$157,5,FALSE()),"No") -> No | AD14: No. 485 | AE14: Street 36 | AF14: Baan Thongpone | AG14: Luang Prabang | AH14: 797100 | AI14: Lao PDR | AJ14: BCEL (Banque pour le Commerce Exterieur Lao) | AK14: BCEL Khammuane Branch | AL14: =IFERROR(INDEX(LK_BankMaster!$D$4:$D$23,MATCH(AJ14&"|"&AK14,LK_BankMaster!$H$4:$H$23,0)),"") | AM14: 337937327 | AN14: =IFERROR(VLOOKUP(AJ14,LK_BankMaster!$A$4:$E$23,5,FALSE()),"") | AO14: Yes | AP14: 1 | AQ14: =IF(ISNUMBER(SEARCH("Deputy Minister",M14)),"Position Allowance - Deputy Minister",IF(AND(ISNUMBER(SEARCH("Minister",M14)),NOT(ISNUMBER(SEARCH("Deputy",M14)))),"Position Allowance - Minister",IF(ISNUMBER(SEARCH("Deputy Director",M14)),"Position Allowance - Deputy Director",IF(AND(ISNUMBER(SEARCH("Director",M14)),NOT(ISNUMBER(SEARCH("Deputy",M14)))),"Position Allowance - Director",IF(ISNUMBER(SEARCH("Division Chief",M14)),"Position Allowance - Division Chief",IF(ISNUMBER(SEARCH("Section Chief",M14)),"Position Allowance - Section Chief","Position Allowance - General Staff")))))) -> Position Allowance - General Staff | AR14: =IFERROR(VLOOKUP(T14,LK_OrgMaster!$B$4:$G$89,6,FALSE()),"No") -> No | AS14: =IFERROR(VLOOKUP(T14,LK_OrgMaster!$B$4:$H$89,7,FALSE()),"None") -> None | AT14: 35026 | AV14: 35026 | AW14: 46023 | AX14: Initial Load | AY14: Record created during payroll system initial data load (Jan 2026).
A15: LAO00012 | B15: Mrs. | C15: Lattana | D15: Souksavanh | E15: Female | F15: 31932 | G15: lattana.souksava@gov.la | H15: +856 20 98626076 | I15: 43441 | J15: =IFERROR(DATEDIF(I15,TODAY(),"Y"),0) -> 7 | K15: =IFERROR(DATE(YEAR(F15)+60,MONTH(F15),DAY(F15)),"") -> 53847 | L15: Permanent | M15: Division Chief | N15: Master's Degree | O15: 6 | P15: =IFERROR(SUMPRODUCT((LK_GradeDerivation!$A$4:$A$135=N15)*(IF(O15="",0,O15)>=LK_GradeDerivation!$B$4:$B$135)*(IF(O15="",0,O15)<=LK_GradeDerivation!$C$4:$C$135)*LK_GradeDerivation!$D$4:$D$135),1) -> 5 | Q15: =IFERROR(SUMPRODUCT((LK_GradeDerivation!$A$4:$A$135=N15)*(IF(O15="",0,O15)>=LK_GradeDerivation!$B$4:$B$135)*(IF(O15="",0,O15)<=LK_GradeDerivation!$C$4:$C$135)*LK_GradeDerivation!$E$4:$E$135),1) -> 4 | R15: CSC000012 | S15: SSO5638893 | T15: Vientiane Capital Administration | U15: Department of Administration | V15: IT Division | W15: Lao PDR | X15: Vientiane Capital | Y15: Mayparkngum | Z15: =IFERROR(VLOOKUP(T15,LK_OrgMaster!$B$4:$H$89,5,FALSE()),"Administration") -> Administration | AA15: =IFERROR(VLOOKUP(X15,LK_LocationMaster!$D$4:$G$157,4,FALSE()),"No") -> No | AB15: =IF(W15="Foreign / International","Yes","No") -> No | AC15: =IFERROR(VLOOKUP(X15,LK_LocationMaster!$D$4:$H$157,5,FALSE()),"No") -> No | AD15: No. 103 | AE15: Samsenthai Road | AF15: Baan Naxaythong | AG15: Bokeo | AH15: 691200 | AI15: Lao PDR | AJ15: Lao Development Bank (LDB) | AK15: LDB Savannakhet Branch | AL15: =IFERROR(INDEX(LK_BankMaster!$D$4:$D$23,MATCH(AJ15&"|"&AK15,LK_BankMaster!$H$4:$H$23,0)),"") | AM15: 332341238 | AN15: =IFERROR(VLOOKUP(AJ15,LK_BankMaster!$A$4:$E$23,5,FALSE()),"") | AO15: No | AP15: 0 | AQ15: =IF(ISNUMBER(SEARCH("Deputy Minister",M15)),"Position Allowance - Deputy Minister",IF(AND(ISNUMBER(SEARCH("Minister",M15)),NOT(ISNUMBER(SEARCH("Deputy",M15)))),"Position Allowance - Minister",IF(ISNUMBER(SEARCH("Deputy Director",M15)),"Position Allowance - Deputy Director",IF(AND(ISNUMBER(SEARCH("Director",M15)),NOT(ISNUMBER(SEARCH("Deputy",M15)))),"Position Allowance - Director",IF(ISNUMBER(SEARCH("Division Chief",M15)),"Position Allowance - Division Chief",IF(ISNUMBER(SEARCH("Section Chief",M15)),"Position Allowance - Section Chief","Position Allowance - General Staff")))))) -> Position Allowance - Division Chief | AR15: =IFERROR(VLOOKUP(T15,LK_OrgMaster!$B$4:$G$89,6,FALSE()),"No") -> No | AS15: =IFERROR(VLOOKUP(T15,LK_OrgMaster!$B$4:$H$89,7,FALSE()),"None") -> None | AT15: 43441 | AV15: 43441 | AW15: 46023 | AX15: Initial Load | AY15: Record created during payroll system initial data load (Jan 2026).
... A503: LAO00500 | B503: Mrs. | C503: Vilayhong | D503: Luanglath | E503: Female | F503: 26615 | G503: vilayhong.luanglat@gov.la | H503: +856 20 64051322 | I503: 39991 | J503: =IFERROR(DATEDIF(I503,TODAY(),"Y"),0) -> 16 | K503: =IFERROR(DATE(YEAR(F503)+60,MONTH(F503),DAY(F503)),"") -> 48530 | L503: Permanent | M503: Administrative Officer | N503: Bachelor's Degree | O503: 14 | P503: =IFERROR(SUMPRODUCT((LK_GradeDerivation!$A$4:$A$135=N503)*(IF(O503="",0,O503)>=LK_GradeDerivation!$B$4:$B$135)*(IF(O503="",0,O503)<=LK_GradeDerivation!$C$4:$C$135)*LK_GradeDerivation!$D$4:$D$135),1) -> 4 | Q503: =IFERROR(SUMPRODUCT((LK_GradeDerivation!$A$4:$A$135=N503)*(IF(O503="",0,O503)>=LK_GradeDerivation!$B$4:$B$135)*(IF(O503="",0,O503)<=LK_GradeDerivation!$C$4:$C$135)*LK_GradeDerivation!$E$4:$E$135),1) -> 8 | R503: CSC000500 | S503: SSO3694288 | T503: Ministry of Industry & Commerce (MoIC) | U503: Department of Domestic Trade | V503: Market Regulation Division | W503: Lao PDR | X503: Sayabouli | Y503: Xienghon | Z503: =IFERROR(VLOOKUP(T503,LK_OrgMaster!$B$4:$H$89,5,FALSE()),"Administration") -> Administration | AA503: =IFERROR(VLOOKUP(X503,LK_LocationMaster!$D$4:$G$157,4,FALSE()),"No") -> Yes | AB503: =IF(W503="Foreign / International","Yes","No") -> No | AC503: =IFERROR(VLOOKUP(X503,LK_LocationMaster!$D$4:$H$157,5,FALSE()),"No") -> No | AD503: No. 759 | AE503: Samsenthai Road | AF503: Baan Dongpalane | AG503: Luang Prabang | AH503: 918900 | AI503: Lao PDR | AJ503: Joint Development Bank (JDB) | AK503: JDB Vientiane Branch | AL503: =IFERROR(INDEX(LK_BankMaster!$D$4:$D$23,MATCH(AJ503&"|"&AK503,LK_BankMaster!$H$4:$H$23,0)),"") | AM503: 448442536 | AN503: =IFERROR(VLOOKUP(AJ503,LK_BankMaster!$A$4:$E$23,5,FALSE()),"") | AO503: Yes | AP503: 2 | AQ503: =IF(ISNUMBER(SEARCH("Deputy Minister",M503)),"Position Allowance - Deputy Minister",IF(AND(ISNUMBER(SEARCH("Minister",M503)),NOT(ISNUMBER(SEARCH("Deputy",M503)))),"Position Allowance - Minister",IF(ISNUMBER(SEARCH("Deputy Director",M503)),"Position Allowance - Deputy Director",IF(AND(ISNUMBER(SEARCH("Director",M503)),NOT(ISNUMBER(SEARCH("Deputy",M503)))),"Position Allowance - Director",IF(ISNUMBER(SEARCH("Division Chief",M503)),"Position Allowance - Division Chief",IF(ISNUMBER(SEARCH("Section Chief",M503)),"Position Allowance - Section Chief","Position Allowance - General Staff")))))) -> Position Allowance - General Staff | AR503: =IFERROR(VLOOKUP(T503,LK_OrgMaster!$B$4:$G$89,6,FALSE()),"No") -> No | AS503: =IFERROR(VLOOKUP(T503,LK_OrgMaster!$B$4:$H$89,7,FALSE()),"None") -> None | AT503: 39991 | AV503: 39991 | AW503: 46023 | AX503: Initial Load | AY503: Record created during payroll system initial data load (Jan 2026).

Sheet PAYROLL_CALC
A1: MONTHLY PAYROLL CALCULATION — Lao PDR Government | All amounts in LAK | Yellow = free input | Green = formula | Cols Y-AA = Other Allowances (free) | Cols AG-AH = Additional Deductions (free)
A2: Payroll Month → | B2: UPDATE MONTH HERE | E2: EMPLOYEE IDENTITY | F2: SALARY BASE | M2: ⬆ EARNINGS / ALLOWANCES | Y2: 🔓 OTHER ALLOWANCES | AB2: TOTAL ALLOW | AC2: GROSS | AG2: 🔓 OTHER DEDUCTIONS | AI2: TOTAL DED | AJ2: NET SALARY
A3: Emp Code | B3: First Name | C3: Last Name | D3: Ministry / Org | E3: Position | F3: Profession | G3: Grade | H3: Step | I3: Grade-Step Key | J3: Multiplier | K3: Index Value (LAK) | L3: Basic Salary (LAK) | M3: Position Allowance | N3: Yrs Service Allowance | O3: Teaching Allowance | P3: Medical Allowance | Q3: NA Member Allowance | R3: Hardship/ Hazardous | S3: Remote Area Allowance | T3: Foreign Living Allowance | U3: Fuel Benefit (Gr≥8) | V3: Spouse Benefit | W3: Child Benefit | X3: Other Subsidies | Y3: Other Allowance 1 (Description + Amount) | Z3: Other Allowance 2 (Description + Amount) | AA3: Other Allowance 3 (Description + Amount) | AB3: Total Allowances (LAK) | AC3: GROSS EARNINGS (LAK) | AD3: SSO Employee Contrib. | AE3: Taxable Income | AF3: PIT Amount (LAK) | AG3: Additional Deduction 1 (e.g. Loan Repayment) | AH3: Additional Deduction 2 (e.g. Advance Recovery) | AI3: TOTAL DEDUCTIONS (LAK) | AJ3: NET SALARY (LAK)
A4: =EMPLOYEE_MASTER!A4 -> LAO00001 | B4: =EMPLOYEE_MASTER!C4 -> Khamsone | C4: =EMPLOYEE_MASTER!D4 -> Bounseng | D4: =EMPLOYEE_MASTER!T4 -> Ministry of Education and Sports (MoES) | E4: =EMPLOYEE_MASTER!M4 -> School Principal | F4: =EMPLOYEE_MASTER!Z4 -> Teacher | G4: =EMPLOYEE_MASTER!P4 -> 4 | H4: =EMPLOYEE_MASTER!Q4 -> 13 | I4: ="G"&TEXT(G4,"00")&"-S"&TEXT(H4,"00") -> G04-S13 | J4: =IFERROR(VLOOKUP(I4,LK_GradeStep!$C$4:$D$85,2,0),0) -> 328 | K4: =IFERROR(VLOOKUP(I4,LK_GradeStep!$C$4:$E$85,3,0),10000) -> 10000 | L4: =IFERROR(J4*K4,0) -> 3280000 | M4: =IFERROR(VLOOKUP(EMPLOYEE_MASTER!AQ4,LK_AllowanceRates!$A$5:$B$11,2,0),0) -> 900000 | N4: =IFERROR(IF(EMPLOYEE_MASTER!J4<=5, EMPLOYEE_MASTER!J4*LK_AllowanceRates!$B$12,IF(EMPLOYEE_MASTER!J4<=15, EMPLOYEE_MASTER!J4*LK_AllowanceRates!$B$13,IF(EMPLOYEE_MASTER!J4<=25, EMPLOYEE_MASTER!J4*LK_AllowanceRates!$B$14,EMPLOYEE_MASTER!J4*LK_AllowanceRates!$B$15))),0) -> 140000 | O4: =IF(EMPLOYEE_MASTER!AS4="Teaching",L4*LK_AllowanceRates!$B$16,0) -> 656000 | P4: =IF(EMPLOYEE_MASTER!AS4="Medical",LK_AllowanceRates!$B$17,0) -> 0 | Q4: =IF(EMPLOYEE_MASTER!AR4="Yes",LK_AllowanceRates!$B$18,0) -> 0 | R4: =IF(EMPLOYEE_MASTER!AC4="Yes",LK_AllowanceRates!$B$19,0) -> 1000000 | S4: =IF(EMPLOYEE_MASTER!AA4="Yes",L4*LK_AllowanceRates!$B$20,0) -> 820000 | T4: =IF(EMPLOYEE_MASTER!AB4="Yes",LK_AllowanceRates!$B$21,0) -> 0 | U4: =IF(EMPLOYEE_MASTER!P4>=6,LK_AllowanceRates!$B$22,0) -> 0 | V4: =IF(EMPLOYEE_MASTER!AO4="Yes",LK_AllowanceRates!$B$23,0) -> 200000 | W4: =EMPLOYEE_MASTER!AP4*LK_AllowanceRates!$B$24 -> 400000 | X4: 0 | Y4: 0 | Z4: 0 | AA4: 0 | AB4: =SUM(M4:AA4) -> 4116000 | AC4: =L4+AB4 -> 7396000 | AD4: =ROUND(L4*LK_AllowanceRates!$B$25/100,0) -> 180400 | AE4: =IFERROR(AC4-AD4,0) -> 7215600 | AF4: =IFERROR(IF(AE4<=1300000,0,IF(AE4<=5000000,(AE4-1300000)*0.05,IF(AE4<=10000000,185000+(AE4-5000000)*0.1,IF(AE4<=20000000,685000+(AE4-10000000)*0.15,IF(AE4<=40000000,2185000+(AE4-20000000)*0.2,6185000+(AE4-40000000)*0.24))))),0) -> 406560 | AG4: 0 | AH4: 0 | AI4: =AD4+AF4+AG4+AH4 -> 586960 | AJ4: =IFERROR(AC4-AI4,0) -> 6809040
A5: =EMPLOYEE_MASTER!A5 -> LAO00002 | B5: =EMPLOYEE_MASTER!C5 -> Sisamone | C5: =EMPLOYEE_MASTER!D5 -> Vilayvong | D5: =EMPLOYEE_MASTER!T5 -> National Assembly (NA) | E5: =EMPLOYEE_MASTER!M5 -> Senior Officer | F5: =EMPLOYEE_MASTER!Z5 -> Administration | G5: =EMPLOYEE_MASTER!P5 -> 5 | H5: =EMPLOYEE_MASTER!Q5 -> 1 | I5: ="G"&TEXT(G5,"00")&"-S"&TEXT(H5,"00") -> G05-S01 | J5: =IFERROR(VLOOKUP(I5,LK_GradeStep!$C$4:$D$85,2,0),0) -> 308 | K5: =IFERROR(VLOOKUP(I5,LK_GradeStep!$C$4:$E$85,3,0),10000) -> 10000 | L5: =IFERROR(J5*K5,0) -> 3080000 | M5: =IFERROR(VLOOKUP(EMPLOYEE_MASTER!AQ5,LK_AllowanceRates!$A$5:$B$11,2,0),0) -> 900000 | N5: =IFERROR(IF(EMPLOYEE_MASTER!J5<=5, EMPLOYEE_MASTER!J5*LK_AllowanceRates!$B$12,IF(EMPLOYEE_MASTER!J5<=15, EMPLOYEE_MASTER!J5*LK_AllowanceRates!$B$13,IF(EMPLOYEE_MASTER!J5<=25, EMPLOYEE_MASTER!J5*LK_AllowanceRates!$B$14,EMPLOYEE_MASTER!J5*LK_AllowanceRates!$B$15))),0) -> 1440000 | O5: =IF(EMPLOYEE_MASTER!AS5="Teaching",L5*LK_AllowanceRates!$B$16,0) -> 0 | P5: =IF(EMPLOYEE_MASTER!AS5="Medical",LK_AllowanceRates!$B$17,0) -> 0 | Q5: =IF(EMPLOYEE_MASTER!AR5="Yes",LK_AllowanceRates!$B$18,0) -> 1000000 | R5: =IF(EMPLOYEE_MASTER!AC5="Yes",LK_AllowanceRates!$B$19,0) -> 0 | S5: =IF(EMPLOYEE_MASTER!AA5="Yes",L5*LK_AllowanceRates!$B$20,0) -> 0 | T5: =IF(EMPLOYEE_MASTER!AB5="Yes",LK_AllowanceRates!$B$21,0) -> 0 | U5: =IF(EMPLOYEE_MASTER!P5>=6,LK_AllowanceRates!$B$22,0) -> 0 | V5: =IF(EMPLOYEE_MASTER!AO5="Yes",LK_AllowanceRates!$B$23,0) -> 200000 | W5: =EMPLOYEE_MASTER!AP5*LK_AllowanceRates!$B$24 -> 600000 | X5: 0 | Y5: 0 | Z5: 0 | AA5: 0 | AB5: =SUM(M5:AA5) -> 4140000 | AC5: =L5+AB5 -> 7220000 | AD5: =ROUND(L5*LK_AllowanceRates!$B$25/100,0) -> 169400 | AE5: =IFERROR(AC5-AD5,0) -> 7050600 | AF5: =IFERROR(IF(AE5<=1300000,0,IF(AE5<=5000000,(AE5-1300000)*0.05,IF(AE5<=10000000,185000+(AE5-5000000)*0.1,IF(AE5<=20000000,685000+(AE5-10000000)*0.15,IF(AE5<=40000000,2185000+(AE5-20000000)*0.2,6185000+(AE5-40000000)*0.24))))),0) -> 390060 | AG5: 0 | AH5: 0 | AI5: =AD5+AF5+AG5+AH5 -> 559460 | AJ5: =IFERROR(AC5-AI5,0) -> 6660540
A6: =EMPLOYEE_MASTER!A6 -> LAO00003 | B6: =EMPLOYEE_MASTER!C6 -> Keovilay | C6: =EMPLOYEE_MASTER!D6 -> Sisouvath | D6: =EMPLOYEE_MASTER!T6 -> Ministry of Health (MoH) | E6: =EMPLOYEE_MASTER!M6 -> Nurse | F6: =EMPLOYEE_MASTER!Z6 -> Medical | G6: =EMPLOYEE_MASTER!P6 -> 2 | H6: =EMPLOYEE_MASTER!Q6 -> 6 | I6: ="G"&TEXT(G6,"00")&"-S"&TEXT(H6,"00") -> G02-S06 | J6: =IFERROR(VLOOKUP(I6,LK_GradeStep!$C$4:$D$85,2,0),0) -> 273 | K6: =IFERROR(VLOOKUP(I6,LK_GradeStep!$C$4:$E$85,3,0),10000) -> 10000 | L6: =IFERROR(J6*K6,0) -> 2730000 | M6: =IFERROR(VLOOKUP(EMPLOYEE_MASTER!AQ6,LK_AllowanceRates!$A$5:$B$11,2,0),0) -> 900000 | N6: =IFERROR(IF(EMPLOYEE_MASTER!J6<=5, EMPLOYEE_MASTER!J6*LK_AllowanceRates!$B$12,IF(EMPLOYEE_MASTER!J6<=15, EMPLOYEE_MASTER!J6*LK_AllowanceRates!$B$13,IF(EMPLOYEE_MASTER!J6<=25, EMPLOYEE_MASTER!J6*LK_AllowanceRates!$B$14,EMPLOYEE_MASTER!J6*LK_AllowanceRates!$B$15))),0) -> 280000 | O6: =IF(EMPLOYEE_MASTER!AS6="Teaching",L6*LK_AllowanceRates!$B$16,0) -> 0 | P6: =IF(EMPLOYEE_MASTER!AS6="Medical",LK_AllowanceRates!$B$17,0) -> 500000 | Q6: =IF(EMPLOYEE_MASTER!AR6="Yes",LK_AllowanceRates!$B$18,0) -> 0 | R6: =IF(EMPLOYEE_MASTER!AC6="Yes",LK_AllowanceRates!$B$19,0) -> 0 | S6: =IF(EMPLOYEE_MASTER!AA6="Yes",L6*LK_AllowanceRates!$B$20,0) -> 0 | T6: =IF(EMPLOYEE_MASTER!AB6="Yes",LK_AllowanceRates!$B$21,0) -> 0 | U6: =IF(EMPLOYEE_MASTER!P6>=6,LK_AllowanceRates!$B$22,0) -> 0 | V6: =IF(EMPLOYEE_MASTER!AO6="Yes",LK_AllowanceRates!$B$23,0) -> 0 | W6: =EMPLOYEE_MASTER!AP6*LK_AllowanceRates!$B$24 -> 0 | X6: 0 | Y6: 0 | Z6: 0 | AA6: 0 | AB6: =SUM(M6:AA6) -> 1680000 | AC6: =L6+AB6 -> 4410000 | AD6: =ROUND(L6*LK_AllowanceRates!$B$25/100,0) -> 150150 | AE6: =IFERROR(AC6-AD6,0) -> 4259850 | AF6: =IFERROR(IF(AE6<=1300000,0,IF(AE6<=5000000,(AE6-1300000)*0.05,IF(AE6<=10000000,185000+(AE6-5000000)*0.1,IF(AE6<=20000000,685000+(AE6-10000000)*0.15,IF(AE6<=40000000,2185000+(AE6-20000000)*0.2,6185000+(AE6-40000000)*0.24))))),0) -> 147992.5 | AG6: 0 | AH6: 0 | AI6: =AD6+AF6+AG6+AH6 -> 298142.5 | AJ6: =IFERROR(AC6-AI6,0) -> 4111857.5
A7: =EMPLOYEE_MASTER!A7 -> LAO00004 | B7: =EMPLOYEE_MASTER!C7 -> Sengphet | C7: =EMPLOYEE_MASTER!D7 -> Sengmixay | D7: =EMPLOYEE_MASTER!T7 -> Ministry of Education and Sports (MoES) | E7: =EMPLOYEE_MASTER!M7 -> Primary School Teacher | F7: =EMPLOYEE_MASTER!Z7 -> Teacher | G7: =EMPLOYEE_MASTER!P7 -> 4 | H7: =EMPLOYEE_MASTER!Q7 -> 5 | I7: ="G"&TEXT(G7,"00")&"-S"&TEXT(H7,"00") -> G04-S05 | J7: =IFERROR(VLOOKUP(I7,LK_GradeStep!$C$4:$D$85,2,0),0) -> 294 | K7: =IFERROR(VLOOKUP(I7,LK_GradeStep!$C$4:$E$85,3,0),10000) -> 10000 | L7: =IFERROR(J7*K7,0) -> 2940000 | M7: =IFERROR(VLOOKUP(EMPLOYEE_MASTER!AQ7,LK_AllowanceRates!$A$5:$B$11,2,0),0) -> 900000 | N7: =IFERROR(IF(EMPLOYEE_MASTER!J7<=5, EMPLOYEE_MASTER!J7*LK_AllowanceRates!$B$12,IF(EMPLOYEE_MASTER!J7<=15, EMPLOYEE_MASTER!J7*LK_AllowanceRates!$B$13,IF(EMPLOYEE_MASTER!J7<=25, EMPLOYEE_MASTER!J7*LK_AllowanceRates!$B$14,EMPLOYEE_MASTER!J7*LK_AllowanceRates!$B$15))),0) -> 140000 | O7: =IF(EMPLOYEE_MASTER!AS7="Teaching",L7*LK_AllowanceRates!$B$16,0) -> 588000 | P7: =IF(EMPLOYEE_MASTER!AS7="Medical",LK_AllowanceRates!$B$17,0) -> 0 | Q7: =IF(EMPLOYEE_MASTER!AR7="Yes",LK_AllowanceRates!$B$18,0) -> 0 | R7: =IF(EMPLOYEE_MASTER!AC7="Yes",LK_AllowanceRates!$B$19,0) -> 1000000 | S7: =IF(EMPLOYEE_MASTER!AA7="Yes",L7*LK_AllowanceRates!$B$20,0) -> 735000 | T7: =IF(EMPLOYEE_MASTER!AB7="Yes",LK_AllowanceRates!$B$21,0) -> 0 | U7: =IF(EMPLOYEE_MASTER!P7>=6,LK_AllowanceRates!$B$22,0) -> 0 | V7: =IF(EMPLOYEE_MASTER!AO7="Yes",LK_AllowanceRates!$B$23,0) -> 0 | W7: =EMPLOYEE_MASTER!AP7*LK_AllowanceRates!$B$24 -> 0 | X7: 0 | Y7: 0 | Z7: 0 | AA7: 0 | AB7: =SUM(M7:AA7) -> 3363000 | AC7: =L7+AB7 -> 6303000 | AD7: =ROUND(L7*LK_AllowanceRates!$B$25/100,0) -> 161700 | AE7: =IFERROR(AC7-AD7,0) -> 6141300 | AF7: =IFERROR(IF(AE7<=1300000,0,IF(AE7<=5000000,(AE7-1300000)*0.05,IF(AE7<=10000000,185000+(AE7-5000000)*0.1,IF(AE7<=20000000,685000+(AE7-10000000)*0.15,IF(AE7<=40000000,2185000+(AE7-20000000)*0.2,6185000+(AE7-40000000)*0.24))))),0) -> 299130 | AG7: 0 | AH7: 0 | AI7: =AD7+AF7+AG7+AH7 -> 460830 | AJ7: =IFERROR(AC7-AI7,0) -> 5842170
A8: =EMPLOYEE_MASTER!A8 -> LAO00005 | B8: =EMPLOYEE_MASTER!C8 -> Vilaychith | C8: =EMPLOYEE_MASTER!D8 -> Phommachack | D8: =EMPLOYEE_MASTER!T8 -> Ministry of Health (MoH) | E8: =EMPLOYEE_MASTER!M8 -> Dental Officer | F8: =EMPLOYEE_MASTER!Z8 -> Medical | G8: =EMPLOYEE_MASTER!P8 -> 2 | H8: =EMPLOYEE_MASTER!Q8 -> 5 | I8: ="G"&TEXT(G8,"00")&"-S"&TEXT(H8,"00") -> G02-S05 | J8: =IFERROR(VLOOKUP(I8,LK_GradeStep!$C$4:$D$85,2,0),0) -> 272 | K8: =IFERROR(VLOOKUP(I8,LK_GradeStep!$C$4:$E$85,3,0),10000) -> 10000 | L8: =IFERROR(J8*K8,0) -> 2720000 | M8: =IFERROR(VLOOKUP(EMPLOYEE_MASTER!AQ8,LK_AllowanceRates!$A$5:$B$11,2,0),0) -> 900000 | N8: =IFERROR(IF(EMPLOYEE_MASTER!J8<=5, EMPLOYEE_MASTER!J8*LK_AllowanceRates!$B$12,IF(EMPLOYEE_MASTER!J8<=15, EMPLOYEE_MASTER!J8*LK_AllowanceRates!$B$13,IF(EMPLOYEE_MASTER!J8<=25, EMPLOYEE_MASTER!J8*LK_AllowanceRates!$B$14,EMPLOYEE_MASTER!J8*LK_AllowanceRates!$B$15))),0) -> 300000 | O8: =IF(EMPLOYEE_MASTER!AS8="Teaching",L8*LK_AllowanceRates!$B$16,0) -> 0 | P8: =IF(EMPLOYEE_MASTER!AS8="Medical",LK_AllowanceRates!$B$17,0) -> 500000 | Q8: =IF(EMPLOYEE_MASTER!AR8="Yes",LK_AllowanceRates!$B$18,0) -> 0 | R8: =IF(EMPLOYEE_MASTER!AC8="Yes",LK_AllowanceRates!$B$19,0) -> 0 | S8: =IF(EMPLOYEE_MASTER!AA8="Yes",L8*LK_AllowanceRates!$B$20,0) -> 680000 | T8: =IF(EMPLOYEE_MASTER!AB8="Yes",LK_AllowanceRates!$B$21,0) -> 0 | U8: =IF(EMPLOYEE_MASTER!P8>=6,LK_AllowanceRates!$B$22,0) -> 0 | V8: =IF(EMPLOYEE_MASTER!AO8="Yes",LK_AllowanceRates!$B$23,0) -> 200000 | W8: =EMPLOYEE_MASTER!AP8*LK_AllowanceRates!$B$24 -> 600000 | X8: 0 | Y8: 0 | Z8: 0 | AA8: 0 | AB8: =SUM(M8:AA8) -> 3180000 | AC8: =L8+AB8 -> 5900000 | AD8: =ROUND(L8*LK_AllowanceRates!$B$25/100,0) -> 149600 | AE8: =IFERROR(AC8-AD8,0) -> 5750400 | AF8: =IFERROR(IF(AE8<=1300000,0,IF(AE8<=5000000,(AE8-1300000)*0.05,IF(AE8<=10000000,185000+(AE8-5000000)*0.1,IF(AE8<=20000000,685000+(AE8-10000000)*0.15,IF(AE8<=40000000,2185000+(AE8-20000000)*0.2,6185000+(AE8-40000000)*0.24))))),0) -> 260040 | AG8: 0 | AH8: 0 | AI8: =AD8+AF8+AG8+AH8 -> 409640 | AJ8: =IFERROR(AC8-AI8,0) -> 5490360
A9: =EMPLOYEE_MASTER!A9 -> LAO00006 | B9: =EMPLOYEE_MASTER!C9 -> Phonethip | C9: =EMPLOYEE_MASTER!D9 -> Phommavong | D9: =EMPLOYEE_MASTER!T9 -> Ministry of Health (MoH) | E9: =EMPLOYEE_MASTER!M9 -> Senior Doctor | F9: =EMPLOYEE_MASTER!Z9 -> Medical | G9: =EMPLOYEE_MASTER!P9 -> 5 | H9: =EMPLOYEE_MASTER!Q9 -> 1 | I9: ="G"&TEXT(G9,"00")&"-S"&TEXT(H9,"00") -> G05-S01 | J9: =IFERROR(VLOOKUP(I9,LK_GradeStep!$C$4:$D$85,2,0),0) -> 308 | K9: =IFERROR(VLOOKUP(I9,LK_GradeStep!$C$4:$E$85,3,0),10000) -> 10000 | L9: =IFERROR(J9*K9,0) -> 3080000 | M9: =IFERROR(VLOOKUP(EMPLOYEE_MASTER!AQ9,LK_AllowanceRates!$A$5:$B$11,2,0),0) -> 900000 | N9: =IFERROR(IF(EMPLOYEE_MASTER!J9<=5, EMPLOYEE_MASTER!J9*LK_AllowanceRates!$B$12,IF(EMPLOYEE_MASTER!J9<=15, EMPLOYEE_MASTER!J9*LK_AllowanceRates!$B$13,IF(EMPLOYEE_MASTER!J9<=25, EMPLOYEE_MASTER!J9*LK_AllowanceRates!$B$14,EMPLOYEE_MASTER!J9*LK_AllowanceRates!$B$15))),0) -> 1360000 | O9: =IF(EMPLOYEE_MASTER!AS9="Teaching",L9*LK_AllowanceRates!$B$16,0) -> 0 | P9: =IF(EMPLOYEE_MASTER!AS9="Medical",LK_AllowanceRates!$B$17,0) -> 500000 | Q9: =IF(EMPLOYEE_MASTER!AR9="Yes",LK_AllowanceRates!$B$18,0) -> 0 | R9: =IF(EMPLOYEE_MASTER!AC9="Yes",LK_AllowanceRates!$B$19,0) -> 0 | S9: =IF(EMPLOYEE_MASTER!AA9="Yes",L9*LK_AllowanceRates!$B$20,0) -> 770000 | T9: =IF(EMPLOYEE_MASTER!AB9="Yes",LK_AllowanceRates!$B$21,0) -> 0 | U9: =IF(EMPLOYEE_MASTER!P9>=6,LK_AllowanceRates!$B$22,0) -> 0 | V9: =IF(EMPLOYEE_MASTER!AO9="Yes",LK_AllowanceRates!$B$23,0) -> 200000 | W9: =EMPLOYEE_MASTER!AP9*LK_AllowanceRates!$B$24 -> 600000 | X9: 0 | Y9: 0 | Z9: 0 | AA9: 0 | AB9: =SUM(M9:AA9) -> 4330000 | AC9: =L9+AB9 -> 7410000 | AD9: =ROUND(L9*LK_AllowanceRates!$B$25/100,0) -> 169400 | AE9: =IFERROR(AC9-AD9,0) -> 7240600 | AF9: =IFERROR(IF(AE9<=1300000,0,IF(AE9<=5000000,(AE9-1300000)*0.05,IF(AE9<=10000000,185000+(AE9-5000000)*0.1,IF(AE9<=20000000,685000+(AE9-10000000)*0.15,IF(AE9<=40000000,2185000+(AE9-20000000)*0.2,6185000+(AE9-40000000)*0.24))))),0) -> 409060 | AG9: 0 | AH9: 0 | AI9: =AD9+AF9+AG9+AH9 -> 578460 | AJ9: =IFERROR(AC9-AI9,0) -> 6831540
A10: =EMPLOYEE_MASTER!A10 -> LAO00007 | B10: =EMPLOYEE_MASTER!C10 -> Phonesavanh | C10: =EMPLOYEE_MASTER!D10 -> Soulinthong | D10: =EMPLOYEE_MASTER!T10 -> Ministry of Industry & Commerce (MoIC) | E10: =EMPLOYEE_MASTER!M10 -> Department Director | F10: =EMPLOYEE_MASTER!Z10 -> Administration | G10: =EMPLOYEE_MASTER!P10 -> 5 | H10: =EMPLOYEE_MASTER!Q10 -> 4 | I10: ="G"&TEXT(G10,"00")&"-S"&TEXT(H10,"00") -> G05-S04 | J10: =IFERROR(VLOOKUP(I10,LK_GradeStep!$C$4:$D$85,2,0),0) -> 323 | K10: =IFERROR(VLOOKUP(I10,LK_GradeStep!$C$4:$E$85,3,0),10000) -> 10000 | L10: =IFERROR(J10*K10,0) -> 3230000 | M10: =IFERROR(VLOOKUP(EMPLOYEE_MASTER!AQ10,LK_AllowanceRates!$A$5:$B$11,2,0),0) -> 2500000 | N10: =IFERROR(IF(EMPLOYEE_MASTER!J10<=5, EMPLOYEE_MASTER!J10*LK_AllowanceRates!$B$12,IF(EMPLOYEE_MASTER!J10<=15, EMPLOYEE_MASTER!J10*LK_AllowanceRates!$B$13,IF(EMPLOYEE_MASTER!J10<=25, EMPLOYEE_MASTER!J10*LK_AllowanceRates!$B$14,EMPLOYEE_MASTER!J10*LK_AllowanceRates!$B$15))),0) -> 30000 | O10: =IF(EMPLOYEE_MASTER!AS10="Teaching",L10*LK_AllowanceRates!$B$16,0) -> 0 | P10: =IF(EMPLOYEE_MASTER!AS10="Medical",LK_AllowanceRates!$B$17,0) -> 0 | Q10: =IF(EMPLOYEE_MASTER!AR10="Yes",LK_AllowanceRates!$B$18,0) -> 0 | R10: =IF(EMPLOYEE_MASTER!AC10="Yes",LK_AllowanceRates!$B$19,0) -> 0 | S10: =IF(EMPLOYEE_MASTER!AA10="Yes",L10*LK_AllowanceRates!$B$20,0) -> 0 | T10: =IF(EMPLOYEE_MASTER!AB10="Yes",LK_AllowanceRates!$B$21,0) -> 0 | U10: =IF(EMPLOYEE_MASTER!P10>=6,LK_AllowanceRates!$B$22,0) -> 0 | V10: =IF(EMPLOYEE_MASTER!AO10="Yes",LK_AllowanceRates!$B$23,0) -> 0 | W10: =EMPLOYEE_MASTER!AP10*LK_AllowanceRates!$B$24 -> 0 | X10: 0 | Y10: 0 | Z10: 0 | AA10: 0 | AB10: =SUM(M10:AA10) -> 2530000 | AC10: =L10+AB10 -> 5760000 | AD10: =ROUND(L10*LK_AllowanceRates!$B$25/100,0) -> 177650 | AE10: =IFERROR(AC10-AD10,0) -> 5582350 | AF10: =IFERROR(IF(AE10<=1300000,0,IF(AE10<=5000000,(AE10-1300000)*0.05,IF(AE10<=10000000,185000+(AE10-5000000)*0.1,IF(AE10<=20000000,685000+(AE10-10000000)*0.15,IF(AE10<=40000000,2185000+(AE10-20000000)*0.2,6185000+(AE10-40000000)*0.24))))),0) -> 243235 | AG10: 0 | AH10: 0 | AI10: =AD10+AF10+AG10+AH10 -> 420885 | AJ10: =IFERROR(AC10-AI10,0) -> 5339115
A11: =EMPLOYEE_MASTER!A11 -> LAO00008 | B11: =EMPLOYEE_MASTER!C11 -> Bounma | C11: =EMPLOYEE_MASTER!D11 -> Phongphichith | D11: =EMPLOYEE_MASTER!T11 -> Ministry of Public Works & Transport (MPWT) | E11: =EMPLOYEE_MASTER!M11 -> IT Officer | F11: =EMPLOYEE_MASTER!Z11 -> Technical | G11: =EMPLOYEE_MASTER!P11 -> 2 | H11: =EMPLOYEE_MASTER!Q11 -> 13 | I11: ="G"&TEXT(G11,"00")&"-S"&TEXT(H11,"00") -> G02-S13 | J11: =IFERROR(VLOOKUP(I11,LK_GradeStep!$C$4:$D$85,2,0),0) -> 280 | K11: =IFERROR(VLOOKUP(I11,LK_GradeStep!$C$4:$E$85,3,0),10000) -> 10000 | L11: =IFERROR(J11*K11,0) -> 2800000 | M11: =IFERROR(VLOOKUP(EMPLOYEE_MASTER!AQ11,LK_AllowanceRates!$A$5:$B$11,2,0),0) -> 900000 | N11: =IFERROR(IF(EMPLOYEE_MASTER!J11<=5, EMPLOYEE_MASTER!J11*LK_AllowanceRates!$B$12,IF(EMPLOYEE_MASTER!J11<=15, EMPLOYEE_MASTER!J11*LK_AllowanceRates!$B$13,IF(EMPLOYEE_MASTER!J11<=25, EMPLOYEE_MASTER!J11*LK_AllowanceRates!$B$14,EMPLOYEE_MASTER!J11*LK_AllowanceRates!$B$15))),0) -> 140000 | O11: =IF(EMPLOYEE_MASTER!AS11="Teaching",L11*LK_AllowanceRates!$B$16,0) -> 0 | P11: =IF(EMPLOYEE_MASTER!AS11="Medical",LK_AllowanceRates!$B$17,0) -> 0 | Q11: =IF(EMPLOYEE_MASTER!AR11="Yes",LK_AllowanceRates!$B$18,0) -> 0 | R11: =IF(EMPLOYEE_MASTER!AC11="Yes",LK_AllowanceRates!$B$19,0) -> 1000000 | S11: =IF(EMPLOYEE_MASTER!AA11="Yes",L11*LK_AllowanceRates!$B$20,0) -> 0 | T11: =IF(EMPLOYEE_MASTER!AB11="Yes",LK_AllowanceRates!$B$21,0) -> 0 | U11: =IF(EMPLOYEE_MASTER!P11>=6,LK_AllowanceRates!$B$22,0) -> 0 | V11: =IF(EMPLOYEE_MASTER!AO11="Yes",LK_AllowanceRates!$B$23,0) -> 0 | W11: =EMPLOYEE_MASTER!AP11*LK_AllowanceRates!$B$24 -> 0 | X11: 0 | Y11: 0 | Z11: 0 | AA11: 0 | AB11: =SUM(M11:AA11) -> 2040000 | AC11: =L11+AB11 -> 4840000 | AD11: =ROUND(L11*LK_AllowanceRates!$B$25/100,0) -> 154000 | AE11: =IFERROR(AC11-AD11,0) -> 4686000 | AF11: =IFERROR(IF(AE11<=1300000,0,IF(AE11<=5000000,(AE11-1300000)*0.05,IF(AE11<=10000000,185000+(AE11-5000000)*0.1,IF(AE11<=20000000,685000+(AE11-10000000)*0.15,IF(AE11<=40000000,2185000+(AE11-20000000)*0.2,6185000+(AE11-40000000)*0.24))))),0) -> 169300 | AG11: 0 | AH11: 0 | AI11: =AD11+AF11+AG11+AH11 -> 323300 | AJ11: =IFERROR(AC11-AI11,0) -> 4516700
A12: =EMPLOYEE_MASTER!A12 -> LAO00009 | B12: =EMPLOYEE_MASTER!C12 -> Khanthavy | C12: =EMPLOYEE_MASTER!D12 -> Sengmixay | D12: =EMPLOYEE_MASTER!T12 -> Ministry of Health (MoH) | E12: =EMPLOYEE_MASTER!M12 -> Nurse | F12: =EMPLOYEE_MASTER!Z12 -> Medical | G12: =EMPLOYEE_MASTER!P12 -> 4 | H12: =EMPLOYEE_MASTER!Q12 -> 8 | I12: ="G"&TEXT(G12,"00")&"-S"&TEXT(H12,"00") -> G04-S08 | J12: =IFERROR(VLOOKUP(I12,LK_GradeStep!$C$4:$D$85,2,0),0) -> 303 | K12: =IFERROR(VLOOKUP(I12,LK_GradeStep!$C$4:$E$85,3,0),10000) -> 10000 | L12: =IFERROR(J12*K12,0) -> 3030000 | M12: =IFERROR(VLOOKUP(EMPLOYEE_MASTER!AQ12,LK_AllowanceRates!$A$5:$B$11,2,0),0) -> 900000 | N12: =IFERROR(IF(EMPLOYEE_MASTER!J12<=5, EMPLOYEE_MASTER!J12*LK_AllowanceRates!$B$12,IF(EMPLOYEE_MASTER!J12<=15, EMPLOYEE_MASTER!J12*LK_AllowanceRates!$B$13,IF(EMPLOYEE_MASTER!J12<=25, EMPLOYEE_MASTER!J12*LK_AllowanceRates!$B$14,EMPLOYEE_MASTER!J12*LK_AllowanceRates!$B$15))),0) -> 140000 | O12: =IF(EMPLOYEE_MASTER!AS12="Teaching",L12*LK_AllowanceRates!$B$16,0) -> 0 | P12: =IF(EMPLOYEE_MASTER!AS12="Medical",LK_AllowanceRates!$B$17,0) -> 500000 | Q12: =IF(EMPLOYEE_MASTER!AR12="Yes",LK_AllowanceRates!$B$18,0) -> 0 | R12: =IF(EMPLOYEE_MASTER!AC12="Yes",LK_AllowanceRates!$B$19,0) -> 1000000 | S12: =IF(EMPLOYEE_MASTER!AA12="Yes",L12*LK_AllowanceRates!$B$20,0) -> 0 | T12: =IF(EMPLOYEE_MASTER!AB12="Yes",LK_AllowanceRates!$B$21,0) -> 0 | U12: =IF(EMPLOYEE_MASTER!P12>=6,LK_AllowanceRates!$B$22,0) -> 0 | V12: =IF(EMPLOYEE_MASTER!AO12="Yes",LK_AllowanceRates!$B$23,0) -> 0 | W12: =EMPLOYEE_MASTER!AP12*LK_AllowanceRates!$B$24 -> 0 | X12: 0 | Y12: 0 | Z12: 0 | AA12: 0 | AB12: =SUM(M12:AA12) -> 2540000 | AC12: =L12+AB12 -> 5570000 | AD12: =ROUND(L12*LK_AllowanceRates!$B$25/100,0) -> 166650 | AE12: =IFERROR(AC12-AD12,0) -> 5403350 | AF12: =IFERROR(IF(AE12<=1300000,0,IF(AE12<=5000000,(AE12-1300000)*0.05,IF(AE12<=10000000,185000+(AE12-5000000)*0.1,IF(AE12<=20000000,685000+(AE12-10000000)*0.15,IF(AE12<=40000000,2185000+(AE12-20000000)*0.2,6185000+(AE12-40000000)*0.24))))),0) -> 225335 | AG12: 0 | AH12: 0 | AI12: =AD12+AF12+AG12+AH12 -> 391985 | AJ12: =IFERROR(AC12-AI12,0) -> 5178015
A13: =EMPLOYEE_MASTER!A13 -> LAO00010 | B13: =EMPLOYEE_MASTER!C13 -> Manyvone | C13: =EMPLOYEE_MASTER!D13 -> Phiaylack | D13: =EMPLOYEE_MASTER!T13 -> Ministry of Justice (MoJ) | E13: =EMPLOYEE_MASTER!M13 -> Senior Legal Advisor | F13: =EMPLOYEE_MASTER!Z13 -> Legal | G13: =EMPLOYEE_MASTER!P13 -> 5 | H13: =EMPLOYEE_MASTER!Q13 -> 2 | I13: ="G"&TEXT(G13,"00")&"-S"&TEXT(H13,"00") -> G05-S02 | J13: =IFERROR(VLOOKUP(I13,LK_GradeStep!$C$4:$D$85,2,0),0) -> 313 | K13: =IFERROR(VLOOKUP(I13,LK_GradeStep!$C$4:$E$85,3,0),10000) -> 10000 | L13: =IFERROR(J13*K13,0) -> 3130000 | M13: =IFERROR(VLOOKUP(EMPLOYEE_MASTER!AQ13,LK_AllowanceRates!$A$5:$B$11,2,0),0) -> 900000 | N13: =IFERROR(IF(EMPLOYEE_MASTER!J13<=5, EMPLOYEE_MASTER!J13*LK_AllowanceRates!$B$12,IF(EMPLOYEE_MASTER!J13<=15, EMPLOYEE_MASTER!J13*LK_AllowanceRates!$B$13,IF(EMPLOYEE_MASTER!J13<=25, EMPLOYEE_MASTER!J13*LK_AllowanceRates!$B$14,EMPLOYEE_MASTER!J13*LK_AllowanceRates!$B$15))),0) -> 480000 | O13: =IF(EMPLOYEE_MASTER!AS13="Teaching",L13*LK_AllowanceRates!$B$16,0) -> 0 | P13: =IF(EMPLOYEE_MASTER!AS13="Medical",LK_AllowanceRates!$B$17,0) -> 0 | Q13: =IF(EMPLOYEE_MASTER!AR13="Yes",LK_AllowanceRates!$B$18,0) -> 0 | R13: =IF(EMPLOYEE_MASTER!AC13="Yes",LK_AllowanceRates!$B$19,0) -> 1000000 | S13: =IF(EMPLOYEE_MASTER!AA13="Yes",L13*LK_AllowanceRates!$B$20,0) -> 0 | T13: =IF(EMPLOYEE_MASTER!AB13="Yes",LK_AllowanceRates!$B$21,0) -> 0 | U13: =IF(EMPLOYEE_MASTER!P13>=6,LK_AllowanceRates!$B$22,0) -> 0 | V13: =IF(EMPLOYEE_MASTER!AO13="Yes",LK_AllowanceRates!$B$23,0) -> 200000 | W13: =EMPLOYEE_MASTER!AP13*LK_AllowanceRates!$B$24 -> 200000 | X13: 0 | Y13: 0 | Z13: 0 | AA13: 0 | AB13: =SUM(M13:AA13) -> 2780000 | AC13: =L13+AB13 -> 5910000 | AD13: =ROUND(L13*LK_AllowanceRates!$B$25/100,0) -> 172150 | AE13: =IFERROR(AC13-AD13,0) -> 5737850 | AF13: =IFERROR(IF(AE13<=1300000,0,IF(AE13<=5000000,(AE13-1300000)*0.05,IF(AE13<=10000000,185000+(AE13-5000000)*0.1,IF(AE13<=20000000,685000+(AE13-10000000)*0.15,IF(AE13<=40000000,2185000+(AE13-20000000)*0.2,6185000+(AE13-40000000)*0.24))))),0) -> 258785 | AG13: 0 | AH13: 0 | AI13: =AD13+AF13+AG13+AH13 -> 430935 | AJ13: =IFERROR(AC13-AI13,0) -> 5479065
A14: =EMPLOYEE_MASTER!A14 -> LAO00011 | B14: =EMPLOYEE_MASTER!C14 -> Vongphet | C14: =EMPLOYEE_MASTER!D14 -> Bounseng | D14: =EMPLOYEE_MASTER!T14 -> Vientiane Capital Administration | E14: =EMPLOYEE_MASTER!M14 -> Officer | F14: =EMPLOYEE_MASTER!Z14 -> Administration | G14: =EMPLOYEE_MASTER!P14 -> 4 | H14: =EMPLOYEE_MASTER!Q14 -> 1 | I14: ="G"&TEXT(G14,"00")&"-S"&TEXT(H14,"00") -> G04-S01 | J14: =IFERROR(VLOOKUP(I14,LK_GradeStep!$C$4:$D$85,2,0),0) -> 286 | K14: =IFERROR(VLOOKUP(I14,LK_GradeStep!$C$4:$E$85,3,0),10000) -> 10000 | L14: =IFERROR(J14*K14,0) -> 2860000 | M14: =IFERROR(VLOOKUP(EMPLOYEE_MASTER!AQ14,LK_AllowanceRates!$A$5:$B$11,2,0),0) -> 900000 | N14: =IFERROR(IF(EMPLOYEE_MASTER!J14<=5, EMPLOYEE_MASTER!J14*LK_AllowanceRates!$B$12,IF(EMPLOYEE_MASTER!J14<=15, EMPLOYEE_MASTER!J14*LK_AllowanceRates!$B$13,IF(EMPLOYEE_MASTER!J14<=25, EMPLOYEE_MASTER!J14*LK_AllowanceRates!$B$14,EMPLOYEE_MASTER!J14*LK_AllowanceRates!$B$15))),0) -> 1200000 | O14: =IF(EMPLOYEE_MASTER!AS14="Teaching",L14*LK_AllowanceRates!$B$16,0) -> 0 | P14: =IF(EMPLOYEE_MASTER!AS14="Medical",LK_AllowanceRates!$B$17,0) -> 0 | Q14: =IF(EMPLOYEE_MASTER!AR14="Yes",LK_AllowanceRates!$B$18,0) -> 0 | R14: =IF(EMPLOYEE_MASTER!AC14="Yes",LK_AllowanceRates!$B$19,0) -> 0 | S14: =IF(EMPLOYEE_MASTER!AA14="Yes",L14*LK_AllowanceRates!$B$20,0) -> 0 | T14: =IF(EMPLOYEE_MASTER!AB14="Yes",LK_AllowanceRates!$B$21,0) -> 0 | U14: =IF(EMPLOYEE_MASTER!P14>=6,LK_AllowanceRates!$B$22,0) -> 0 | V14: =IF(EMPLOYEE_MASTER!AO14="Yes",LK_AllowanceRates!$B$23,0) -> 200000 | W14: =EMPLOYEE_MASTER!AP14*LK_AllowanceRates!$B$24 -> 200000 | X14: 0 | Y14: 0 | Z14: 0 | AA14: 0 | AB14: =SUM(M14:AA14) -> 2500000 | AC14: =L14+AB14 -> 5360000 | AD14: =ROUND(L14*LK_AllowanceRates!$B$25/100,0) -> 157300 | AE14: =IFERROR(AC14-AD14,0) -> 5202700 | AF14: =IFERROR(IF(AE14<=1300000,0,IF(AE14<=5000000,(AE14-1300000)*0.05,IF(AE14<=10000000,185000+(AE14-5000000)*0.1,IF(AE14<=20000000,685000+(AE14-10000000)*0.15,IF(AE14<=40000000,2185000+(AE14-20000000)*0.2,6185000+(AE14-40000000)*0.24))))),0) -> 205270 | AG14: 0 | AH14: 0 | AI14: =AD14+AF14+AG14+AH14 -> 362570 | AJ14: =IFERROR(AC14-AI14,0) -> 4997430
A15: =EMPLOYEE_MASTER!A15 -> LAO00012 | B15: =EMPLOYEE_MASTER!C15 -> Lattana | C15: =EMPLOYEE_MASTER!D15 -> Souksavanh | D15: =EMPLOYEE_MASTER!T15 -> Vientiane Capital Administration | E15: =EMPLOYEE_MASTER!M15 -> Division Chief | F15: =EMPLOYEE_MASTER!Z15 -> Administration | G15: =EMPLOYEE_MASTER!P15 -> 5 | H15: =EMPLOYEE_MASTER!Q15 -> 4 | I15: ="G"&TEXT(G15,"00")&"-S"&TEXT(H15,"00") -> G05-S04 | J15: =IFERROR(VLOOKUP(I15,LK_GradeStep!$C$4:$D$85,2,0),0) -> 323 | K15: =IFERROR(VLOOKUP(I15,LK_GradeStep!$C$4:$E$85,3,0),10000) -> 10000 | L15: =IFERROR(J15*K15,0) -> 3230000 | M15: =IFERROR(VLOOKUP(EMPLOYEE_MASTER!AQ15,LK_AllowanceRates!$A$5:$B$11,2,0),0) -> 1900000 | N15: =IFERROR(IF(EMPLOYEE_MASTER!J15<=5, EMPLOYEE_MASTER!J15*LK_AllowanceRates!$B$12,IF(EMPLOYEE_MASTER!J15<=15, EMPLOYEE_MASTER!J15*LK_AllowanceRates!$B$13,IF(EMPLOYEE_MASTER!J15<=25, EMPLOYEE_MASTER!J15*LK_AllowanceRates!$B$14,EMPLOYEE_MASTER!J15*LK_AllowanceRates!$B$15))),0) -> 140000 | O15: =IF(EMPLOYEE_MASTER!AS15="Teaching",L15*LK_AllowanceRates!$B$16,0) -> 0 | P15: =IF(EMPLOYEE_MASTER!AS15="Medical",LK_AllowanceRates!$B$17,0) -> 0 | Q15: =IF(EMPLOYEE_MASTER!AR15="Yes",LK_AllowanceRates!$B$18,0) -> 0 | R15: =IF(EMPLOYEE_MASTER!AC15="Yes",LK_AllowanceRates!$B$19,0) -> 0 | S15: =IF(EMPLOYEE_MASTER!AA15="Yes",L15*LK_AllowanceRates!$B$20,0) -> 0 | T15: =IF(EMPLOYEE_MASTER!AB15="Yes",LK_AllowanceRates!$B$21,0) -> 0 | U15: =IF(EMPLOYEE_MASTER!P15>=6,LK_AllowanceRates!$B$22,0) -> 0 | V15: =IF(EMPLOYEE_MASTER!AO15="Yes",LK_AllowanceRates!$B$23,0) -> 0 | W15: =EMPLOYEE_MASTER!AP15*LK_AllowanceRates!$B$24 -> 0 | X15: 0 | Y15: 0 | Z15: 0 | AA15: 0 | AB15: =SUM(M15:AA15) -> 2040000 | AC15: =L15+AB15 -> 5270000 | AD15: =ROUND(L15*LK_AllowanceRates!$B$25/100,0) -> 177650 | AE15: =IFERROR(AC15-AD15,0) -> 5092350 | AF15: =IFERROR(IF(AE15<=1300000,0,IF(AE15<=5000000,(AE15-1300000)*0.05,IF(AE15<=10000000,185000+(AE15-5000000)*0.1,IF(AE15<=20000000,685000+(AE15-10000000)*0.15,IF(AE15<=40000000,2185000+(AE15-20000000)*0.2,6185000+(AE15-40000000)*0.24))))),0) -> 194235 | AG15: 0 | AH15: 0 | AI15: =AD15+AF15+AG15+AH15 -> 371885 | AJ15: =IFERROR(AC15-AI15,0) -> 4898115
... A503: =EMPLOYEE_MASTER!A503 -> LAO00500 | B503: =EMPLOYEE_MASTER!C503 -> Vilayhong | C503: =EMPLOYEE_MASTER!D503 -> Luanglath | D503: =EMPLOYEE_MASTER!T503 -> Ministry of Industry & Commerce (MoIC) | E503: =EMPLOYEE_MASTER!M503 -> Administrative Officer | F503: =EMPLOYEE_MASTER!Z503 -> Administration | G503: =EMPLOYEE_MASTER!P503 -> 4 | H503: =EMPLOYEE_MASTER!Q503 -> 8 | I503: ="G"&TEXT(G503,"00")&"-S"&TEXT(H503,"00") -> G04-S08 | J503: =IFERROR(VLOOKUP(I503,LK_GradeStep!$C$4:$D$85,2,0),0) -> 303 | K503: =IFERROR(VLOOKUP(I503,LK_GradeStep!$C$4:$E$85,3,0),10000) -> 10000 | L503: =IFERROR(J503*K503,0) -> 3030000 | M503: =IFERROR(VLOOKUP(EMPLOYEE_MASTER!AQ503,LK_AllowanceRates!$A$5:$B$11,2,0),0) -> 900000 | N503: =IFERROR(IF(EMPLOYEE_MASTER!J503<=5, EMPLOYEE_MASTER!J503*LK_AllowanceRates!$B$12,IF(EMPLOYEE_MASTER!J503<=15, EMPLOYEE_MASTER!J503*LK_AllowanceRates!$B$13,IF(EMPLOYEE_MASTER!J503<=25, EMPLOYEE_MASTER!J503*LK_AllowanceRates!$B$14,EMPLOYEE_MASTER!J503*LK_AllowanceRates!$B$15))),0) -> 480000 | O503: =IF(EMPLOYEE_MASTER!AS503="Teaching",L503*LK_AllowanceRates!$B$16,0) -> 0 | P503: =IF(EMPLOYEE_MASTER!AS503="Medical",LK_AllowanceRates!$B$17,0) -> 0 | Q503: =IF(EMPLOYEE_MASTER!AR503="Yes",LK_AllowanceRates!$B$18,0) -> 0 | R503: =IF(EMPLOYEE_MASTER!AC503="Yes",LK_AllowanceRates!$B$19,0) -> 0 | S503: =IF(EMPLOYEE_MASTER!AA503="Yes",L503*LK_AllowanceRates!$B$20,0) -> 757500 | T503: =IF(EMPLOYEE_MASTER!AB503="Yes",LK_AllowanceRates!$B$21,0) -> 0 | U503: =IF(EMPLOYEE_MASTER!P503>=6,LK_AllowanceRates!$B$22,0) -> 0 | V503: =IF(EMPLOYEE_MASTER!AO503="Yes",LK_AllowanceRates!$B$23,0) -> 200000 | W503: =EMPLOYEE_MASTER!AP503*LK_AllowanceRates!$B$24 -> 400000 | X503: 0 | Y503: 0 | Z503: 0 | AA503: 0 | AB503: =SUM(M503:AA503) -> 2737500 | AC503: =L503+AB503 -> 5767500 | AD503: =ROUND(L503*LK_AllowanceRates!$B$25/100,0) -> 166650 | AE503: =IFERROR(AC503-AD503,0) -> 5600850 | AF503: =IFERROR(IF(AE503<=1300000,0,IF(AE503<=5000000,(AE503-1300000)*0.05,IF(AE503<=10000000,185000+(AE503-5000000)*0.1,IF(AE503<=20000000,685000+(AE503-10000000)*0.15,IF(AE503<=40000000,2185000+(AE503-20000000)*0.2,6185000+(AE503-40000000)*0.24))))),0) -> 245085 | AG503: 0 | AH503: 0 | AI503: =AD503+AF503+AG503+AH503 -> 411735 | AJ503: =IFERROR(AC503-AI503,0) -> 5355765
A504: GRAND TOTALS | G504: =SUM(G4:G503) -> 1870 | H504: =SUM(H4:H503) -> 2027 | I504: =SUM(I4:I503) -> 0 | J504: =SUM(J4:J503) -> 147857 | K504: =SUM(K4:K503) -> 5000000 | L504: =SUM(L4:L503) -> 1478570000 | M504: =SUM(M4:M503) -> 570200000 | N504: =SUM(N4:N503) -> 308880000 | ... AJ504: =SUM(AJ4:AJ503) -> 2.9365203e+09

Sheet LK_OrgMaster
A1: ORGANISATION MASTER — Ministry → Department → Division (LK_OrgMaster)
A2: ⭐ KEY DERIVATION TABLE. Employee Master derives: Profession Category (from Col D), Is NA Member (Col E), Field Allowance Type (Col F) via VLOOKUP on Ministry. Ministry Key (Col C) drives the dependent Department dropdown. Dept Key (Col D visible col = hidden helper) drives the dependent Division dropdown. DO NOT change Col B (Ministry), Col C (Ministry Key), Col D (Dept), Col E (Dept Key) — these are used as named range keys. Add new rows to extend.
A3: Row | B3: Ministry Name | C3: Ministry Key | D3: Department Name | E3: Dept Key | F3: Profession Category | G3: NA Allowance Eligible | H3: Field Allowance Type | I3: Effective From (Date) | J3: Effective To (Date) | K3: Last Updated (Date) | L3: Last Updated By (Name/Code) | M3: Circular / Reference | N3: Change Remarks
A4: 1 | B4: Ministry of Finance (MoF) | C4: MOF | D4: Department of Budget | E4: MOF_BUD | F4: Finance | G4: No | H4: None | I4: 46023 | K4: 46023 | L4: MoF System Update | M4: MoF No. 4904/MOF, 26 Dec 2025 | N4: Updated per MoF Guideline 4904/MOF (Jan 2026)
A5: 2 | B5: Ministry of Finance (MoF) | C5: MOF | D5: Department of Taxation | E5: MOF_TAX | F5: Finance | G5: No | H5: None | I5: 46023 | K5: 46023 | L5: MoF System Update | M5: MoF No. 4904/MOF, 26 Dec 2025 | N5: Updated per MoF Guideline 4904/MOF (Jan 2026)
A6: 3 | B6: Ministry of Finance (MoF) | C6: MOF | D6: Department of Treasury | E6: MOF_TRY | F6: Finance | G6: No | H6: None | I6: 46023 | K6: 46023 | L6: MoF System Update | M6: MoF No. 4904/MOF, 26 Dec 2025 | N6: Updated per MoF Guideline 4904/MOF (Jan 2026)
A7: 4 | B7: Ministry of Finance (MoF) | C7: MOF | D7: Department of Customs | E7: MOF_CUS | F7: Finance | G7: No | H7: None | I7: 46023 | K7: 46023 | L7: MoF System Update | M7: MoF No. 4904/MOF, 26 Dec 2025 | N7: Updated per MoF Guideline 4904/MOF (Jan 2026)
A8: 5 | B8: Ministry of Finance (MoF) | C8: MOF | D8: Department of Financial Regulation | E8: MOF_FIN | F8: Finance | G8: No | H8: None | I8: 46023 | K8: 46023 | L8: MoF System Update | M8: MoF No. 4904/MOF, 26 Dec 2025 | N8: Updated per MoF Guideline 4904/MOF (Jan 2026)
A9: 6 | B9: Ministry of Finance (MoF) | C9: MOF | D9: Department of State Assets | E9: MOF_AST | F9: Finance | G9: No | H9: None | I9: 46023 | K9: 46023 | L9: MoF System Update | M9: MoF No. 4904/MOF, 26 Dec 2025 | N9: Updated per MoF Guideline 4904/MOF (Jan 2026)
A10: 7 | B10: Ministry of Health (MoH) | C10: MOH | D10: Department of Curative Medicine | E10: MOH_CUR | F10: Medical | G10: No | H10: Medical | I10: 46023 | K10: 46023 | L10: MoF System Update | M10: MoF No. 4904/MOF, 26 Dec 2025 | N10: Updated per MoF Guideline 4904/MOF (Jan 2026)
A11: 8 | B11: Ministry of Health (MoH) | C11: MOH | D11: Department of Hygiene & Health Promotion | E11: MOH_HYG | F11: Medical | G11: No | H11: Medical | I11: 46023 | K11: 46023 | L11: MoF System Update | M11: MoF No. 4904/MOF, 26 Dec 2025 | N11: Updated per MoF Guideline 4904/MOF (Jan 2026)
A12: 9 | B12: Ministry of Health (MoH) | C12: MOH | D12: Department of Food and Drug | E12: MOH_FDD | F12: Medical | G12: No | H12: Medical | I12: 46023 | K12: 46023 | L12: MoF System Update | M12: MoF No. 4904/MOF, 26 Dec 2025 | N12: Updated per MoF Guideline 4904/MOF (Jan 2026)
A13: 10 | B13: Ministry of Health (MoH) | C13: MOH | D13: Department of Medical Equipment | E13: MOH_EQP | F13: Medical | G13: No | H13: Medical | I13: 46023 | K13: 46023 | L13: MoF System Update | M13: MoF No. 4904/MOF, 26 Dec 2025 | N13: Updated per MoF Guideline 4904/MOF (Jan 2026)
A14: 11 | B14: Ministry of Health (MoH) | C14: MOH | D14: Department of Personnel & Organisation | E14: MOH_PER | F14: Medical | G14: No | H14: Medical | I14: 46023 | K14: 46023 | L14: MoF System Update | M14: MoF No. 4904/MOF, 26 Dec 2025 | N14: Updated per MoF Guideline 4904/MOF (Jan 2026)
A15: 12 | B15: Ministry of Health (MoH) | C15: MOH | D15: Department of Planning & Finance | E15: MOH_PLN | F15: Medical | G15: No | H15: Medical | I15: 46023 | K15: 46023 | L15: MoF System Update | M15: MoF No. 4904/MOF, 26 Dec 2025 | N15: Updated per MoF Guideline 4904/MOF (Jan 2026)
... A89: 86 | B89: Khammuane Province Administration | C89: KHAMM | D89: Provincial Agriculture Office | E89: KMN_AGR | F89: Administration | G89: No | H89: None | I89: 46023 | K89: 46023 | L89: MoF System Update | M89: MoF No. 4904/MOF, 26 Dec 2025 | N89: Updated per MoF Guideline 4904/MOF (Jan 2026)

Sheet LK_LocationMaster
A1: LOCATION MASTER — Country → Province → District (LK_LocationMaster)
A2: ℹ️ Employee Master derives Is Remote (from Col G), Is Hazardous (Col H), and Is Foreign (derived from Country) via VLOOKUP on Service Province (col X in Employee Master). Province and District dropdowns are driven by named ranges in LK_DropdownLists — all sourced from this table. Update Col G (Is Remote) or Col H (Is Hazardous) as MoHA classifications change.
A3: Country | B3: Country Key | C3: Province Key | D3: Province / Posting | E3: District Key | F3: District | G3: Is Remote (Yes/No) | H3: Is Hazardous (Yes/No) | I3: Notes | J3: Effective From (Date) | K3: Effective To (Date) | L3: Last Updated (Date) | M3: Last Updated By (Name/Code) | N3: Circular / Reference | O3: Change Remarks
A4: Lao PDR | B4: LAO | C4: VTE | D4: Vientiane Capital | E4: VTE_CHANTHAB | F4: Chanthabouli | G4: No | H4: No | J4: 46023 | L4: 46023 | M4: MoF System Update | N4: MoHA Gazette / Decree 292/GoL 2021 | O4: Updated per MoF Guideline 4904/MOF (Jan 2026)
A5: Lao PDR | B5: LAO | C5: VTE | D5: Vientiane Capital | E5: VTE_SIKHOTTA | F5: Sikhottabong | G5: No | H5: No | J5: 46023 | L5: 46023 | M5: MoF System Update | N5: MoHA Gazette / Decree 292/GoL 2021 | O5: Updated per MoF Guideline 4904/MOF (Jan 2026)
A6: Lao PDR | B6: LAO | C6: VTE | D6: Vientiane Capital | E6: VTE_XAYSETTH | F6: Xaysettha | G6: No | H6: No | J6: 46023 | L6: 46023 | M6: MoF System Update | N6: MoHA Gazette / Decree 292/GoL 2021 | O6: Updated per MoF Guideline 4904/MOF (Jan 2026)
A7: Lao PDR | B7: LAO | C7: VTE | D7: Vientiane Capital | E7: VTE_SAYSETTH | F7: Saysettha | G7: No | H7: No | J7: 46023 | L7: 46023 | M7: MoF System Update | N7: MoHA Gazette / Decree 292/GoL 2021 | O7: Updated per MoF Guideline 4904/MOF (Jan 2026)
A8: Lao PDR | B8: LAO | C8: VTE | D8: Vientiane Capital | E8: VTE_HADXAYFO | F8: Hadxayfong | G8: No | H8: No | J8: 46023 | L8: 46023 | M8: MoF System Update | N8: MoHA Gazette / Decree 292/GoL 2021 | O8: Updated per MoF Guideline 4904/MOF (Jan 2026)
A9: Lao PDR | B9: LAO | C9: VTE | D9: Vientiane Capital | E9: VTE_NAXAYTHO | F9: Naxaythong | G9: No | H9: No | J9: 46023 | L9: 46023 | M9: MoF System Update | N9: MoHA Gazette / Decree 292/GoL 2021 | O9: Updated per MoF Guideline 4904/MOF (Jan 2026)
A10: Lao PDR | B10: LAO | C10: VTE | D10: Vientiane Capital | E10: VTE_XAYTHANY | F10: Xaythany | G10: No | H10: No | J10: 46023 | L10: 46023 | M10: MoF System Update | N10: MoHA Gazette / Decree 292/GoL 2021 | O10: Updated per MoF Guideline 4904/MOF (Jan 2026)
A11: Lao PDR | B11: LAO | C11: VTE | D11: Vientiane Capital | E11: VTE_SANGTHON | F11: Sangthong | G11: No | H11: No | J11: 46023 | L11: 46023 | M11: MoF System Update | N11: MoHA Gazette / Decree 292/GoL 2021 | O11: Updated per MoF Guideline 4904/MOF (Jan 2026)
A12: Lao PDR | B12: LAO | C12: VTE | D12: Vientiane Capital | E12: VTE_MAYPARKN | F12: Mayparkngum | G12: No | H12: No | J12: 46023 | L12: 46023 | M12: MoF System Update | N12: MoHA Gazette / Decree 292/GoL 2021 | O12: Updated per MoF Guideline 4904/MOF (Jan 2026)
A13: Lao PDR | B13: LAO | C13: PGS | D13: Phongsali | E13: PGS_PHONGSAL | F13: Phongsali | G13: Yes | H13: No | I13: Remote / Difficult Area | J13: 46023 | L13: 46023 | M13: MoF System Update | N13: MoHA Gazette / Decree 292/GoL 2021 | O13: Updated per MoF Guideline 4904/MOF (Jan 2026)
A14: Lao PDR | B14: LAO | C14: PGS | D14: Phongsali | E14: PGS_BOUNNEUA | F14: Boun Neua | G14: Yes | H14: No | I14: Remote / Difficult Area | J14: 46023 | L14: 46023 | M14: MoF System Update | N14: MoHA Gazette / Decree 292/GoL 2021 | O14: Updated per MoF Guideline 4904/MOF (Jan 2026)
A15: Lao PDR | B15: LAO | C15: PGS | D15: Phongsali | E15: PGS_MAY | F15: May | G15: Yes | H15: No | I15: Remote / Difficult Area | J15: 46023 | L15: 46023 | M15: MoF System Update | N15: MoHA Gazette / Decree 292/GoL 2021 | O15: Updated per MoF Guideline 4904/MOF (Jan 2026)
A16: Lao PDR | B16: LAO | C16: PGS | D16: Phongsali | E16: PGS_KHUA | F16: Khua | G16: Yes | H16: No | I16: Remote / Difficult Area | J16: 46023 | L16: 46023 | M16: MoF System Update | N16: MoHA Gazette / Decree 292/GoL 2021 | O16: Updated per MoF Guideline 4904/MOF (Jan 2026)
A17: Lao PDR | B17: LAO | C17: PGS | D17: Phongsali | E17: PGS_SAMPHANH | F17: Samphanh | G17: Yes | H17: No | I17: Remote / Difficult Area | J17: 46023 | L17: 46023 | M17: MoF System Update | N17: MoHA Gazette / Decree 292/GoL 2021 | O17: Updated per MoF Guideline 4904/MOF (Jan 2026)
A18: Lao PDR | B18: LAO | C18: PGS | D18: Phongsali | E18: PGS_BOUNTAI | F18: Boun Tai | G18: Yes | H18: No | I18: Remote / Difficult Area | J18: 46023 | L18: 46023 | M18: MoF System Update | N18: MoHA Gazette / Decree 292/GoL 2021 | O18: Updated per MoF Guideline 4904/MOF (Jan 2026)
A19: Lao PDR | B19: LAO | C19: PGS | D19: Phongsali | E19: PGS_NHOTOU | F19: Nhot Ou | G19: Yes | H19: No | I19: Remote / Difficult Area | J19: 46023 | L19: 46023 | M19: MoF System Update | N19: MoHA Gazette / Decree 292/GoL 2021 | O19: Updated per MoF Guideline 4904/MOF (Jan 2026)
A20: Lao PDR | B20: LAO | C20: LNT | D20: Luang Namtha | E20: LNT_LUANGNAM | F20: Luang Namtha | G20: Yes | H20: No | I20: Remote / Difficult Area | J20: 46023 | L20: 46023 | M20: MoF System Update | N20: MoHA Gazette / Decree 292/GoL 2021 | O20: Updated per MoF Guideline 4904/MOF (Jan 2026)
A21: Lao PDR | B21: LAO | C21: LNT | D21: Luang Namtha | E21: LNT_SING | F21: Sing | G21: Yes | H21: No | I21: Remote / Difficult Area | J21: 46023 | L21: 46023 | M21: MoF System Update | N21: MoHA Gazette / Decree 292/GoL 2021 | O21: Updated per MoF Guideline 4904/MOF (Jan 2026)
A22: Lao PDR | B22: LAO | C22: LNT | D22: Luang Namtha | E22: LNT_LONG | F22: Long | G22: Yes | H22: No | I22: Remote / Difficult Area | J22: 46023 | L22: 46023 | M22: MoF System Update | N22: MoHA Gazette / Decree 292/GoL 2021 | O22: Updated per MoF Guideline 4904/MOF (Jan 2026)
A23: Lao PDR | B23: LAO | C23: LNT | D23: Luang Namtha | E23: LNT_VIENGPHO | F23: Viengphoukha | G23: Yes | H23: No | I23: Remote / Difficult Area | J23: 46023 | L23: 46023 | M23: MoF System Update | N23: MoHA Gazette / Decree 292/GoL 2021 | O23: Updated per MoF Guideline 4904/MOF (Jan 2026)
A24: Lao PDR | B24: LAO | C24: LNT | D24: Luang Namtha | E24: LNT_NALAE | F24: Nalae | G24: Yes | H24: No | I24: Remote / Difficult Area | J24: 46023 | L24: 46023 | M24: MoF System Update | N24: MoHA Gazette / Decree 292/GoL 2021 | O24: Updated per MoF Guideline 4904/MOF (Jan 2026)
A25: Lao PDR | B25: LAO | C25: ODX | D25: Oudomxay | E25: ODX_XAY | F25: Xay | G25: No | H25: No | J25: 46023 | L25: 46023 | M25: MoF System Update | N25: MoHA Gazette / Decree 292/GoL 2021 | O25: Updated per MoF Guideline 4904/MOF (Jan 2026)
A26: Lao PDR | B26: LAO | C26: ODX | D26: Oudomxay | E26: ODX_LA | F26: La | G26: No | H26: No | J26: 46023 | L26: 46023 | M26: MoF System Update | N26: MoHA Gazette / Decree 292/GoL 2021 | O26: Updated per MoF Guideline 4904/MOF (Jan 2026)
A27: Lao PDR | B27: LAO | C27: ODX | D27: Oudomxay | E27: ODX_BENG | F27: Beng | G27: No | H27: No | J27: 46023 | L27: 46023 | M27: MoF System Update | N27: MoHA Gazette / Decree 292/GoL 2021 | O27: Updated per MoF Guideline 4904/MOF (Jan 2026)
A28: Lao PDR | B28: LAO | C28: ODX | D28: Oudomxay | E28: ODX_NAMOR | F28: Namor | G28: No | H28: No | J28: 46023 | L28: 46023 | M28: MoF System Update | N28: MoHA Gazette / Decree 292/GoL 2021 | O28: Updated per MoF Guideline 4904/MOF (Jan 2026)
A29: Lao PDR | B29: LAO | C29: ODX | D29: Oudomxay | E29: ODX_NGA | F29: Nga | G29: No | H29: No | J29: 46023 | L29: 46023 | M29: MoF System Update | N29: MoHA Gazette / Decree 292/GoL 2021 | O29: Updated per MoF Guideline 4904/MOF (Jan 2026)
A30: Lao PDR | B30: LAO | C30: ODX | D30: Oudomxay | E30: ODX_HOUN | F30: Houn | G30: No | H30: No | J30: 46023 | L30: 46023 | M30: MoF System Update | N30: MoHA Gazette / Decree 292/GoL 2021 | O30: Updated per MoF Guideline 4904/MOF (Jan 2026)
A31: Lao PDR | B31: LAO | C31: ODX | D31: Oudomxay | E31: ODX_PAKBENG | F31: Pakbeng | G31: No | H31: No | J31: 46023 | L31: 46023 | M31: MoF System Update | N31: MoHA Gazette / Decree 292/GoL 2021 | O31: Updated per MoF Guideline 4904/MOF (Jan 2026)
A32: Lao PDR | B32: LAO | C32: BKO | D32: Bokeo | E32: BKO_HUOIXAI | F32: Huoixai | G32: Yes | H32: No | I32: Remote / Difficult Area | J32: 46023 | L32: 46023 | M32: MoF System Update | N32: MoHA Gazette / Decree 292/GoL 2021 | O32: Updated per MoF Guideline 4904/MOF (Jan 2026)
A33: Lao PDR | B33: LAO | C33: BKO | D33: Bokeo | E33: BKO_TONPHEUN | F33: Ton Pheung | G33: Yes | H33: No | I33: Remote / Difficult Area | J33: 46023 | L33: 46023 | M33: MoF System Update | N33: MoHA Gazette / Decree 292/GoL 2021 | O33: Updated per MoF Guideline 4904/MOF (Jan 2026)
A34: Lao PDR | B34: LAO | C34: BKO | D34: Bokeo | E34: BKO_PHAOUDOM | F34: Pha Oudom | G34: Yes | H34: No | I34: Remote / Difficult Area | J34: 46023 | L34: 46023 | M34: MoF System Update | N34: MoHA Gazette / Decree 292/GoL 2021 | O34: Updated per MoF Guideline 4904/MOF (Jan 2026)
A35: Lao PDR | B35: LAO | C35: BKO | D35: Bokeo | E35: BKO_MEUNG | F35: Meung | G35: Yes | H35: No | I35: Remote / Difficult Area | J35: 46023 | L35: 46023 | M35: MoF System Update | N35: MoHA Gazette / Decree 292/GoL 2021 | O35: Updated per MoF Guideline 4904/MOF (Jan 2026)
A36: Lao PDR | B36: LAO | C36: BKO | D36: Bokeo | E36: BKO_PAKTHA | F36: Pak Tha | G36: Yes | H36: No | I36: Remote / Difficult Area | J36: 46023 | L36: 46023 | M36: MoF System Update | N36: MoHA Gazette / Decree 292/GoL 2021 | O36: Updated per MoF Guideline 4904/MOF (Jan 2026)
A37: Lao PDR | B37: LAO | C37: LPB | D37: Luang Prabang | E37: LPB_LUANGPRA | F37: Luang Prabang | G37: No | H37: No | J37: 46023 | L37: 46023 | M37: MoF System Update | N37: MoHA Gazette / Decree 292/GoL 2021 | O37: Updated per MoF Guideline 4904/MOF (Jan 2026)
A38: Lao PDR | B38: LAO | C38: LPB | D38: Luang Prabang | E38: LPB_XIENGNGE | F38: Xieng Ngeun | G38: No | H38: No | J38: 46023 | L38: 46023 | M38: MoF System Update | N38: MoHA Gazette / Decree 292/GoL 2021 | O38: Updated per MoF Guideline 4904/MOF (Jan 2026)
A39: Lao PDR | B39: LAO | C39: LPB | D39: Luang Prabang | E39: LPB_NAN | F39: Nan | G39: No | H39: No | J39: 46023 | L39: 46023 | M39: MoF System Update | N39: MoHA Gazette / Decree 292/GoL 2021 | O39: Updated per MoF Guideline 4904/MOF (Jan 2026)
A40: Lao PDR | B40: LAO | C40: LPB | D40: Luang Prabang | E40: LPB_PAKOU | F40: Pak Ou | G40: No | H40: No | J40: 46023 | L40: 46023 | M40: MoF System Update | N40: MoHA Gazette / Decree 292/GoL 2021 | O40: Updated per MoF Guideline 4904/MOF (Jan 2026)
A41: Lao PDR | B41: LAO | C41: LPB | D41: Luang Prabang | E41: LPB_NAMBAK | F41: Nambak | G41: No | H41: No | J41: 46023 | L41: 46023 | M41: MoF System Update | N41: MoHA Gazette / Decree 292/GoL 2021 | O41: Updated per MoF Guideline 4904/MOF (Jan 2026)
A42: Lao PDR | B42: LAO | C42: LPB | D42: Luang Prabang | E42: LPB_NGOI | F42: Ngoi | G42: No | H42: No | J42: 46023 | L42: 46023 | M42: MoF System Update | N42: MoHA Gazette / Decree 292/GoL 2021 | O42: Updated per MoF Guideline 4904/MOF (Jan 2026)
A43: Lao PDR | B43: LAO | C43: LPB | D43: Luang Prabang | E43: LPB_PAKXENG | F43: Pakxeng | G43: No | H43: No | J43: 46023 | L43: 46023 | M43: MoF System Update | N43: MoHA Gazette / Decree 292/GoL 2021 | O43: Updated per MoF Guideline 4904/MOF (Jan 2026)
A44: Lao PDR | B44: LAO | C44: LPB | D44: Luang Prabang | E44: LPB_PHONXAY | F44: Phonxay | G44: No | H44: No | J44: 46023 | L44: 46023 | M44: MoF System Update | N44: MoHA Gazette / Decree 292/GoL 2021 | O44: Updated per MoF Guideline 4904/MOF (Jan 2026)
A45: Lao PDR | B45: LAO | C45: LPB | D45: Luang Prabang | E45: LPB_CHOMPHET | F45: Chomphet | G45: No | H45: No | J45: 46023 | L45: 46023 | M45: MoF System Update | N45: MoHA Gazette / Decree 292/GoL 2021 | O45: Updated per MoF Guideline 4904/MOF (Jan 2026)
A46: Lao PDR | B46: LAO | C46: LPB | D46: Luang Prabang | E46: LPB_VIENGKHA | F46: Viengkham | G46: No | H46: No | J46: 46023 | L46: 46023 | M46: MoF System Update | N46: MoHA Gazette / Decree 292/GoL 2021 | O46: Updated per MoF Guideline 4904/MOF (Jan 2026)
A47: Lao PDR | B47: LAO | C47: LPB | D47: Luang Prabang | E47: LPB_PHOUKHOU | F47: Phoukhoune | G47: No | H47: No | J47: 46023 | L47: 46023 | M47: MoF System Update | N47: MoHA Gazette / Decree 292/GoL 2021 | O47: Updated per MoF Guideline 4904/MOF (Jan 2026)
A48: Lao PDR | B48: LAO | C48: HUA | D48: Huaphan | E48: HUA_XAMNEUA | F48: Xamneua | G48: Yes | H48: Yes | I48: Remote + Hazardous (UXO affected) | J48: 46023 | L48: 46023 | M48: MoF System Update | N48: MoHA Gazette / Decree 292/GoL 2021 | O48: Updated per MoF Guideline 4904/MOF (Jan 2026)
A49: Lao PDR | B49: LAO | C49: HUA | D49: Huaphan | E49: HUA_XIENGKHO | F49: Xiengkho | G49: Yes | H49: Yes | I49: Remote + Hazardous (UXO affected) | J49: 46023 | L49: 46023 | M49: MoF System Update | N49: MoHA Gazette / Decree 292/GoL 2021 | O49: Updated per MoF Guideline 4904/MOF (Jan 2026)
A50: Lao PDR | B50: LAO | C50: HUA | D50: Huaphan | E50: HUA_VIENGXAY | F50: Viengxay | G50: Yes | H50: Yes | I50: Remote + Hazardous (UXO affected) | J50: 46023 | L50: 46023 | M50: MoF System Update | N50: MoHA Gazette / Decree 292/GoL 2021 | O50: Updated per MoF Guideline 4904/MOF (Jan 2026)
A51: Lao PDR | B51: LAO | C51: HUA | D51: Huaphan | E51: HUA_HUAMUANG | F51: Huamuang | G51: Yes | H51: Yes | I51: Remote + Hazardous (UXO affected) | J51: 46023 | L51: 46023 | M51: MoF System Update | N51: MoHA Gazette / Decree 292/GoL 2021 | O51: Updated per MoF Guideline 4904/MOF (Jan 2026)
A52: Lao PDR | B52: LAO | C52: HUA | D52: Huaphan | E52: HUA_XAMTAI | F52: Xam Tai | G52: Yes | H52: Yes | I52: Remote + Hazardous (UXO affected) | J52: 46023 | L52: 46023 | M52: MoF System Update | N52: MoHA Gazette / Decree 292/GoL 2021 | O52: Updated per MoF Guideline 4904/MOF (Jan 2026)
A53: Lao PDR | B53: LAO | C53: HUA | D53: Huaphan | E53: HUA_KUAN | F53: Kuan | G53: Yes | H53: Yes | I53: Remote + Hazardous (UXO affected) | J53: 46023 | L53: 46023 | M53: MoF System Update | N53: MoHA Gazette / Decree 292/GoL 2021 | O53: Updated per MoF Guideline 4904/MOF (Jan 2026)
A54: Lao PDR | B54: LAO | C54: HUA | D54: Huaphan | E54: HUA_HAET | F54: Haet | G54: Yes | H54: Yes | I54: Remote + Hazardous (UXO affected) | J54: 46023 | L54: 46023 | M54: MoF System Update | N54: MoHA Gazette / Decree 292/GoL 2021 | O54: Updated per MoF Guideline 4904/MOF (Jan 2026)
A55: Lao PDR | B55: LAO | C55: SAY | D55: Sayabouli | E55: SAY_SAYABOUL | F55: Sayabouli | G55: Yes | H55: No | I55: Remote / Difficult Area | J55: 46023 | L55: 46023 | M55: MoF System Update | N55: MoHA Gazette / Decree 292/GoL 2021 | O55: Updated per MoF Guideline 4904/MOF (Jan 2026)
A56: Lao PDR | B56: LAO | C56: SAY | D56: Sayabouli | E56: SAY_KHOP | F56: Khop | G56: Yes | H56: No | I56: Remote / Difficult Area | J56: 46023 | L56: 46023 | M56: MoF System Update | N56: MoHA Gazette / Decree 292/GoL 2021 | O56: Updated per MoF Guideline 4904/MOF (Jan 2026)
A57: Lao PDR | B57: LAO | C57: SAY | D57: Sayabouli | E57: SAY_HONGSA | F57: Hongsa | G57: Yes | H57: No | I57: Remote / Difficult Area | J57: 46023 | L57: 46023 | M57: MoF System Update | N57: MoHA Gazette / Decree 292/GoL 2021 | O57: Updated per MoF Guideline 4904/MOF (Jan 2026)
A58: Lao PDR | B58: LAO | C58: SAY | D58: Sayabouli | E58: SAY_NGEUN | F58: Ngeun | G58: Yes | H58: No | I58: Remote / Difficult Area | J58: 46023 | L58: 46023 | M58: MoF System Update | N58: MoHA Gazette / Decree 292/GoL 2021 | O58: Updated per MoF Guideline 4904/MOF (Jan 2026)
A59: Lao PDR | B59: LAO | C59: SAY | D59: Sayabouli | E59: SAY_XIENGHON | F59: Xienghon | G59: Yes | H59: No | I59: Remote / Difficult Area | J59: 46023 | L59: 46023 | M59: MoF System Update | N59: MoHA Gazette / Decree 292/GoL 2021 | O59: Updated per MoF Guideline 4904/MOF (Jan 2026)
... A70: Lao PDR | B70: LAO | C70: XKH | D70: Xiengkhuang | E70: XKH_PHOOKOOD | F70: Phookood | G70: Yes | H70: Yes | I70: Remote + Hazardous (UXO affected) | J70: 46023 | L70: 46023 | M70: MoF System Update | N70: MoHA Gazette / Decree 292/GoL 2021 | O70: Updated per MoF Guideline 4904/MOF (Jan 2026)
A71: Lao PDR | B71: LAO | C71: VTP | D71: Vientiane Province | E71: VTP_PHONHONG | F71: Phon Hong | G71: No | H71: No | J71: 46023 | L71: 46023 | M71: MoF System Update | N71: MoHA Gazette / Decree 292/GoL 2021 | O71: Updated per MoF Guideline 4904/MOF (Jan 2026)
A72: Lao PDR | B72: LAO | C72: VTP | D72: Vientiane Province | E72: VTP_THOULAKH | F72: Thoulakhom | G72: No | H72: No | J72: 46023 | L72: 46023 | M72: MoF System Update | N72: MoHA Gazette / Decree 292/GoL 2021 | O72: Updated per MoF Guideline 4904/MOF (Jan 2026)
A73: Lao PDR | B73: LAO | C73: VTP | D73: Vientiane Province | E73: VTP_KEOOUDOM | F73: Keo Oudom | G73: No | H73: No | J73: 46023 | L73: 46023 | M73: MoF System Update | N73: MoHA Gazette / Decree 292/GoL 2021 | O73: Updated per MoF Guideline 4904/MOF (Jan 2026)
A74: Lao PDR | B74: LAO | C74: VTP | D74: Vientiane Province | E74: VTP_KASY | F74: Kasy | G74: No | H74: No | J74: 46023 | L74: 46023 | M74: MoF System Update | N74: MoHA Gazette / Decree 292/GoL 2021 | O74: Updated per MoF Guideline 4904/MOF (Jan 2026)
A75: Lao PDR | B75: LAO | C75: VTP | D75: Vientiane Province | E75: VTP_VANGVIEN | F75: Vang Vieng | G75: No | H75: No | J75: 46023 | L75: 46023 | M75: MoF System Update | N75: MoHA Gazette / Decree 292/GoL 2021 | O75: Updated per MoF Guideline 4904/MOF (Jan 2026)
A76: Lao PDR | B76: LAO | C76: VTP | D76: Vientiane Province | E76: VTP_FEUANG | F76: Feuang | G76: No | H76: No | J76: 46023 | L76: 46023 | M76: MoF System Update | N76: MoHA Gazette / Decree 292/GoL 2021 | O76: Updated per MoF Guideline 4904/MOF (Jan 2026)
A77: Lao PDR | B77: LAO | C77: VTP | D77: Vientiane Province | E77: VTP_XANAKHAR | F77: Xanakharm | G77: No | H77: No | J77: 46023 | L77: 46023 | M77: MoF System Update | N77: MoHA Gazette / Decree 292/GoL 2021 | O77: Updated per MoF Guideline 4904/MOF (Jan 2026)
A78: Lao PDR | B78: LAO | C78: VTP | D78: Vientiane Province | E78: VTP_MAD | F78: Mad | G78: No | H78: No | J78: 46023 | L78: 46023 | M78: MoF System Update | N78: MoHA Gazette / Decree 292/GoL 2021 | O78: Updated per MoF Guideline 4904/MOF (Jan 2026)
A79: Lao PDR | B79: LAO | C79: VTP | D79: Vientiane Province | E79: VTP_HINHEUP | F79: Hinheup | G79: No | H79: No | J79: 46023 | L79: 46023 | M79: MoF System Update | N79: MoHA Gazette / Decree 292/GoL 2021 | O79: Updated per MoF Guideline 4904/MOF (Jan 2026)
A80: Lao PDR | B80: LAO | C80: BLK | D80: Bolikhamxay | E80: BLK_PAKXAN | F80: Pakxan | G80: No | H80: No | J80: 46023 | L80: 46023 | M80: MoF System Update | N80: MoHA Gazette / Decree 292/GoL 2021 | O80: Updated per MoF Guideline 4904/MOF (Jan 2026)
A81: Lao PDR | B81: LAO | C81: BLK | D81: Bolikhamxay | E81: BLK_THAPHABA | F81: Thaphabath | G81: No | H81: No | J81: 46023 | L81: 46023 | M81: MoF System Update | N81: MoHA Gazette / Decree 292/GoL 2021 | O81: Updated per MoF Guideline 4904/MOF (Jan 2026)
A82: Lao PDR | B82: LAO | C82: BLK | D82: Bolikhamxay | E82: BLK_PAKKADIN | F82: Pakkading | G82: No | H82: No | J82: 46023 | L82: 46023 | M82: MoF System Update | N82: MoHA Gazette / Decree 292/GoL 2021 | O82: Updated per MoF Guideline 4904/MOF (Jan 2026)
... A85: Lao PDR | B85: LAO | C85: BLK | D85: Bolikhamxay | E85: BLK_XAYCHAMP | F85: Xaychamphone | G85: No | H85: No | J85: 46023 | L85: 46023 | M85: MoF System Update | N85: MoHA Gazette / Decree 292/GoL 2021 | O85: Updated per MoF Guideline 4904/MOF (Jan 2026)
A86: Lao PDR | B86: LAO | C86: KMN | D86: Khammuane | E86: KMN_THAKHEK | F86: Thakhek | G86: No | H86: Yes | I86: Hazardous (UXO / border security) | J86: 46023 | L86: 46023 | M86: MoF System Update | N86: MoHA Gazette / Decree 292/GoL 2021 | O86: Updated per MoF Guideline 4904/MOF (Jan 2026)
A87: Lao PDR | B87: LAO | C87: KMN | D87: Khammuane | E87: KMN_MAHAXAY | F87: Mahaxay | G87: No | H87: Yes | I87: Hazardous (UXO / border security) | J87: 46023 | L87: 46023 | M87: MoF System Update | N87: MoHA Gazette / Decree 292/GoL 2021 | O87: Updated per MoF Guideline 4904/MOF (Jan 2026)
A88: Lao PDR | B88: LAO | C88: KMN | D88: Khammuane | E88: KMN_NONGBOK | F88: Nongbok | G88: No | H88: Yes | I88: Hazardous (UXO / border security) | J88: 46023 | L88: 46023 | M88: MoF System Update | N88: MoHA Gazette / Decree 292/GoL 2021 | O88: Updated per MoF Guideline 4904/MOF (Jan 2026)
A89: Lao PDR | B89: LAO | C89: KMN | D89: Khammuane | E89: KMN_HINBOUN | F89: Hinboun | G89: No | H89: Yes | I89: Hazardous (UXO / border security) | J89: 46023 | L89: 46023 | M89: MoF System Update | N89: MoHA Gazette / Decree 292/GoL 2021 | O89: Updated per MoF Guideline 4904/MOF (Jan 2026)
A90: Lao PDR | B90: LAO | C90: KMN | D90: Khammuane | E90: KMN_NHOMMALA | F90: Nhommalath | G90: No | H90: Yes | I90: Hazardous (UXO / border security) | J90: 46023 | L90: 46023 | M90: MoF System Update | N90: MoHA Gazette / Decree 292/GoL 2021 | O90: Updated per MoF Guideline 4904/MOF (Jan 2026)
A91: Lao PDR | B91: LAO | C91: KMN | D91: Khammuane | E91: KMN_BUALAPHA | F91: Bualapha | G91: No | H91: Yes | I91: Hazardous (UXO / border security) | J91: 46023 | L91: 46023 | M91: MoF System Update | N91: MoHA Gazette / Decree 292/GoL 2021 | O91: Updated per MoF Guideline 4904/MOF (Jan 2026)
A92: Lao PDR | B92: LAO | C92: KMN | D92: Khammuane | E92: KMN_YOMMALAT | F92: Yommalath | G92: No | H92: Yes | I92: Hazardous (UXO / border security) | J92: 46023 | L92: 46023 | M92: MoF System Update | N92: MoHA Gazette / Decree 292/GoL 2021 | O92: Updated per MoF Guideline 4904/MOF (Jan 2026)
A93: Lao PDR | B93: LAO | C93: KMN | D93: Khammuane | E93: KMN_XEBANGFA | F93: Xebangfai | G93: No | H93: Yes | I93: Hazardous (UXO / border security) | J93: 46023 | L93: 46023 | M93: MoF System Update | N93: MoHA Gazette / Decree 292/GoL 2021 | O93: Updated per MoF Guideline 4904/MOF (Jan 2026)
A94: Lao PDR | B94: LAO | C94: KMN | D94: Khammuane | E94: KMN_XAIBULI | F94: Xaibuli | G94: No | H94: Yes | I94: Hazardous (UXO / border security) | J94: 46023 | L94: 46023 | M94: MoF System Update | N94: MoHA Gazette / Decree 292/GoL 2021 | O94: Updated per MoF Guideline 4904/MOF (Jan 2026)
A95: Lao PDR | B95: LAO | C95: KMN | D95: Khammuane | E95: KMN_NAKAI | F95: Nakai | G95: No | H95: Yes | I95: Hazardous (UXO / border security) | J95: 46023 | L95: 46023 | M95: MoF System Update | N95: MoHA Gazette / Decree 292/GoL 2021 | O95: Updated per MoF Guideline 4904/MOF (Jan 2026)
A96: Lao PDR | B96: LAO | C96: SVK | D96: Savannakhet | E96: SVK_KAYSONEP | F96: Kaysone Phomvihane | G96: No | H96: Yes | I96: Hazardous (UXO / border security) | J96: 46023 | L96: 46023 | M96: MoF System Update | N96: MoHA Gazette / Decree 292/GoL 2021 | O96: Updated per MoF Guideline 4904/MOF (Jan 2026)
A97: Lao PDR | B97: LAO | C97: SVK | D97: Savannakhet | E97: SVK_OUTHOUMP | F97: Outhoumphone | G97: No | H97: Yes | I97: Hazardous (UXO / border security) | J97: 46023 | L97: 46023 | M97: MoF System Update | N97: MoHA Gazette / Decree 292/GoL 2021 | O97: Updated per MoF Guideline 4904/MOF (Jan 2026)
... A108: Lao PDR | B108: LAO | C108: SVK | D108: Savannakhet | E108: SVK_PHALANXA | F108: Phalanxay | G108: No | H108: Yes | I108: Hazardous (UXO / border security) | J108: 46023 | L108: 46023 | M108: MoF System Update | N108: MoHA Gazette / Decree 292/GoL 2021 | O108: Updated per MoF Guideline 4904/MOF (Jan 2026)
A109: Lao PDR | B109: LAO | C109: SLV | D109: Salavan | E109: SLV_SALAVAN | F109: Salavan | G109: No | H109: No | J109: 46023 | L109: 46023 | M109: MoF System Update | N109: MoHA Gazette / Decree 292/GoL 2021 | O109: Updated per MoF Guideline 4904/MOF (Jan 2026)
A110: Lao PDR | B110: LAO | C110: SLV | D110: Salavan | E110: SLV_TOOMLARN | F110: Toomlarn | G110: No | H110: No | J110: 46023 | L110: 46023 | M110: MoF System Update | N110: MoHA Gazette / Decree 292/GoL 2021 | O110: Updated per MoF Guideline 4904/MOF (Jan 2026)
A111: Lao PDR | B111: LAO | C111: SLV | D111: Salavan | E111: SLV_LAKHONEP | F111: Lakhonepheng | G111: No | H111: No | J111: 46023 | L111: 46023 | M111: MoF System Update | N111: MoHA Gazette / Decree 292/GoL 2021 | O111: Updated per MoF Guideline 4904/MOF (Jan 2026)
A112: Lao PDR | B112: LAO | C112: SLV | D112: Salavan | E112: SLV_VAPI | F112: Vapi | G112: No | H112: No | J112: 46023 | L112: 46023 | M112: MoF System Update | N112: MoHA Gazette / Decree 292/GoL 2021 | O112: Updated per MoF Guideline 4904/MOF (Jan 2026)
A113: Lao PDR | B113: LAO | C113: SLV | D113: Salavan | E113: SLV_KHONGXED | F113: Khongxedone | G113: No | H113: No | J113: 46023 | L113: 46023 | M113: MoF System Update | N113: MoHA Gazette / Decree 292/GoL 2021 | O113: Updated per MoF Guideline 4904/MOF (Jan 2026)
A114: Lao PDR | B114: LAO | C114: SLV | D114: Salavan | E114: SLV_TAOI | F114: Ta-Oi | G114: No | H114: No | J114: 46023 | L114: 46023 | M114: MoF System Update | N114: MoHA Gazette / Decree 292/GoL 2021 | O114: Updated per MoF Guideline 4904/MOF (Jan 2026)
A115: Lao PDR | B115: LAO | C115: SLV | D115: Salavan | E115: SLV_LAONGAM | F115: Laongam | G115: No | H115: No | J115: 46023 | L115: 46023 | M115: MoF System Update | N115: MoHA Gazette / Decree 292/GoL 2021 | O115: Updated per MoF Guideline 4904/MOF (Jan 2026)
A116: Lao PDR | B116: LAO | C116: SLV | D116: Salavan | E116: SLV_SAMUOI | F116: Samuoi | G116: No | H116: No | J116: 46023 | L116: 46023 | M116: MoF System Update | N116: MoHA Gazette / Decree 292/GoL 2021 | O116: Updated per MoF Guideline 4904/MOF (Jan 2026)
A117: Lao PDR | B117: LAO | C117: SKG | D117: Sekong | E117: SKG_LAMAM | F117: Lamam | G117: Yes | H117: Yes | I117: Remote + Hazardous (UXO affected) | J117: 46023 | L117: 46023 | M117: MoF System Update | N117: MoHA Gazette / Decree 292/GoL 2021 | O117: Updated per MoF Guideline 4904/MOF (Jan 2026)
A118: Lao PDR | B118: LAO | C118: SKG | D118: Sekong | E118: SKG_KALEUM | F118: Kaleum | G118: Yes | H118: Yes | I118: Remote + Hazardous (UXO affected) | J118: 46023 | L118: 46023 | M118: MoF System Update | N118: MoHA Gazette / Decree 292/GoL 2021 | O118: Updated per MoF Guideline 4904/MOF (Jan 2026)
A119: Lao PDR | B119: LAO | C119: SKG | D119: Sekong | E119: SKG_THATENG | F119: Thateng | G119: Yes | H119: Yes | I119: Remote + Hazardous (UXO affected) | J119: 46023 | L119: 46023 | M119: MoF System Update | N119: MoHA Gazette / Decree 292/GoL 2021 | O119: Updated per MoF Guideline 4904/MOF (Jan 2026)
A120: Lao PDR | B120: LAO | C120: SKG | D120: Sekong | E120: SKG_DAKCHEUN | F120: Dak Cheung | G120: Yes | H120: Yes | I120: Remote + Hazardous (UXO affected) | J120: 46023 | L120: 46023 | M120: MoF System Update | N120: MoHA Gazette / Decree 292/GoL 2021 | O120: Updated per MoF Guideline 4904/MOF (Jan 2026)
A121: Lao PDR | B121: LAO | C121: CHP | D121: Champasak | E121: CHP_PAKSE | F121: Pakse | G121: No | H121: No | J121: 46023 | L121: 46023 | M121: MoF System Update | N121: MoHA Gazette / Decree 292/GoL 2021 | O121: Updated per MoF Guideline 4904/MOF (Jan 2026)
A122: Lao PDR | B122: LAO | C122: CHP | D122: Champasak | E122: CHP_SANASOMB | F122: Sanasomboon | G122: No | H122: No | J122: 46023 | L122: 46023 | M122: MoF System Update | N122: MoHA Gazette / Decree 292/GoL 2021 | O122: Updated per MoF Guideline 4904/MOF (Jan 2026)
...

Sheet LK_BankMaster
A1: BANK MASTER — All Licensed Banks in Lao PDR | LK_BankMaster
A2: Comprehensive list of all licensed commercial banks in Lao PDR as registered with Bank of the Lao PDR (BOL). Categories: A=State-Owned, B=Joint-State, C=Private Lao, D=Foreign Subsidiary, E=Foreign Branch. SWIFT codes sourced from SWIFT registry and BOL records. Col D (Bank Key) and Col F (Branch Name) are VLOOKUP keys — do NOT change. Update Col I (SWIFT) if bank issues new BIC. Add new branches as new rows.
A3: =HYPERLINK("#HOME!A1","🏠 HOME | Back to Navigation") -> 🏠 HOME | Back to Navigation | P3: 🕐 AUDIT TRAIL — Effective Dates & Change History (DO NOT leave blank)
A4: # | B4: Bank Name (Full Official Name) | C4: Abbrev | D4: Bank Key (Named Range Key) | E4: Category | F4: Branch Name | G4: Branch Code | H4: City | I4: SWIFT / BIC Code | J4: Branch Address | K4: Bank HQ Address | L4: Telephone | M4: Ownership | N4: Established | O4: Website | P4: Effective From (Date) | Q4: Effective To (Date) | R4: Last Updated (Date) | S4: Last Updated By (Name/Code) | T4: Circular / Reference | U4: Change Remarks
A5: 🏦 State-Owned Commercial Banks (4 banks) | P5: 46023 | R5: 46023 | S5: MoF System Update | T5: BOL Bank Registry / Bank of Lao PDR | U5: Updated per MoF Guideline 4904/MOF (Jan 2026)
A6: 1 | B6: Banque pour le Commerce Exterieur Lao Public (BCEL) | C6: BCEL | D6: BCEL | E6: State-Owned Commercial Bank | F6: BCEL Head Office — Vientiane | G6: BCEL001 | H6: Vientiane Capital | I6: COEBLALAXXX | J6: No.1 Pangkham St, Chanthabouli District | K6: No.1 Pangkham Street, Vientiane Capital | L6: +856 21 213 200 | M6: 100% Lao Government (60% State, 10% Strategic Partner, 30% Public) | N6: 1975 | O6: www.bcel.com.la | P6: 46023 | R6: 46023 | S6: MoF System Update | T6: BOL Bank Registry / Bank of Lao PDR | U6: Updated per MoF Guideline 4904/MOF (Jan 2026)
A7: 2 | B7: Banque pour le Commerce Exterieur Lao Public (BCEL) | C7: BCEL | D7: BCEL | E7: State-Owned Commercial Bank | F7: BCEL Samsenthai Branch | G7: BCEL002 | H7: Vientiane Capital | I7: COEBLALAXXX | J7: Samsenthai Road, Vientiane Capital | K7: ↑ same bank | P7: 46023 | R7: 46023 | S7: MoF System Update | T7: BOL Bank Registry / Bank of Lao PDR | U7: Updated per MoF Guideline 4904/MOF (Jan 2026)
A8: 3 | B8: Banque pour le Commerce Exterieur Lao Public (BCEL) | C8: BCEL | D8: BCEL | E8: State-Owned Commercial Bank | F8: BCEL Dongpalane Branch | G8: BCEL003 | H8: Vientiane Capital | I8: COEBLALAXXX | J8: Dongpalane Road, Saysettha District | K8: ↑ same bank | P8: 46023 | R8: 46023 | S8: MoF System Update | T8: BOL Bank Registry / Bank of Lao PDR | U8: Updated per MoF Guideline 4904/MOF (Jan 2026)
A9: 4 | B9: Banque pour le Commerce Exterieur Lao Public (BCEL) | C9: BCEL | D9: BCEL | E9: State-Owned Commercial Bank | F9: BCEL Savannakhet Branch | G9: BCEL004 | H9: Savannakhet | I9: COEBLALAXXX | J9: Kaysone Phomvihane Road, Kaysone District | K9: ↑ same bank | P9: 46023 | R9: 46023 | S9: MoF System Update | T9: BOL Bank Registry / Bank of Lao PDR | U9: Updated per MoF Guideline 4904/MOF (Jan 2026)
A10: 5 | B10: Banque pour le Commerce Exterieur Lao Public (BCEL) | C10: BCEL | D10: BCEL | E10: State-Owned Commercial Bank | F10: BCEL Luang Prabang Branch | G10: BCEL005 | H10: Luang Prabang | I10: COEBLALAXXX | J10: Sisavangvong Road, Luang Prabang District | K10: ↑ same bank | P10: 46023 | R10: 46023 | S10: MoF System Update | T10: BOL Bank Registry / Bank of Lao PDR | U10: Updated per MoF Guideline 4904/MOF (Jan 2026)
A11: 6 | B11: Banque pour le Commerce Exterieur Lao Public (BCEL) | C11: BCEL | D11: BCEL | E11: State-Owned Commercial Bank | F11: BCEL Champasak / Pakse Branch | G11: BCEL006 | H11: Champasak | I11: COEBLALAXXX | J11: Route 13, Pakse City, Champasak | K11: ↑ same bank | P11: 46023 | R11: 46023 | S11: MoF System Update | T11: BOL Bank Registry / Bank of Lao PDR | U11: Updated per MoF Guideline 4904/MOF (Jan 2026)
A12: 7 | B12: Banque pour le Commerce Exterieur Lao Public (BCEL) | C12: BCEL | D12: BCEL | E12: State-Owned Commercial Bank | F12: BCEL Khammuane / Thakhek Branch | G12: BCEL007 | H12: Khammuane | I12: COEBLALAXXX | J12: Setthathirath Road, Thakhek | K12: ↑ same bank | P12: 46023 | R12: 46023 | S12: MoF System Update | T12: BOL Bank Registry / Bank of Lao PDR | U12: Updated per MoF Guideline 4904/MOF (Jan 2026)
A13: 8 | B13: Banque pour le Commerce Exterieur Lao Public (BCEL) | C13: BCEL | D13: BCEL | E13: State-Owned Commercial Bank | F13: BCEL Bolikhamxay / Pakxan Branch | G13: BCEL008 | H13: Bolikhamxay | I13: COEBLALAXXX | J13: Pakxan Town Centre, Bolikhamxay | K13: ↑ same bank | P13: 46023 | R13: 46023 | S13: MoF System Update | T13: BOL Bank Registry / Bank of Lao PDR | U13: Updated per MoF Guideline 4904/MOF (Jan 2026)
A14: 9 | B14: Banque pour le Commerce Exterieur Lao Public (BCEL) | C14: BCEL | D14: BCEL | E14: State-Owned Commercial Bank | F14: BCEL Xiengkhuang / Phonsavan Branch | G14: BCEL009 | H14: Xiengkhuang | I14: COEBLALAXXX | J14: Phonsavan Town, Xiengkhuang Province | K14: ↑ same bank | P14: 46023 | R14: 46023 | S14: MoF System Update | T14: BOL Bank Registry / Bank of Lao PDR | U14: Updated per MoF Guideline 4904/MOF (Jan 2026)
A15: 10 | B15: Banque pour le Commerce Exterieur Lao Public (BCEL) | C15: BCEL | D15: BCEL | E15: State-Owned Commercial Bank | F15: BCEL Oudomxay / Muang Xay Branch | G15: BCEL010 | H15: Oudomxay | I15: COEBLALAXXX | J15: Muang Xay Town Centre, Oudomxay | K15: ↑ same bank | P15: 46023 | R15: 46023 | S15: MoF System Update | T15: BOL Bank Registry / Bank of Lao PDR | U15: Updated per MoF Guideline 4904/MOF (Jan 2026)
A16: 11 | B16: Banque pour le Commerce Exterieur Lao Public (BCEL) | C16: BCEL | D16: BCEL | E16: State-Owned Commercial Bank | F16: BCEL Luang Namtha Branch | G16: BCEL011 | H16: Luang Namtha | I16: COEBLALAXXX | J16: Luang Namtha Town Centre | K16: ↑ same bank | P16: 46023 | R16: 46023 | S16: MoF System Update | T16: BOL Bank Registry / Bank of Lao PDR | U16: Updated per MoF Guideline 4904/MOF (Jan 2026)
A17: 12 | B17: Banque pour le Commerce Exterieur Lao Public (BCEL) | C17: BCEL | D17: BCEL | E17: State-Owned Commercial Bank | F17: BCEL Attapeu Branch | G17: BCEL012 | H17: Attapeu | I17: COEBLALAXXX | J17: Samakkhixay District, Attapeu Province | K17: ↑ same bank | P17: 46023 | R17: 46023 | S17: MoF System Update | T17: BOL Bank Registry / Bank of Lao PDR | U17: Updated per MoF Guideline 4904/MOF (Jan 2026)
A18: 13 | B18: Lao Development Bank (LDB) | C18: LDB | D18: LDB | E18: State-Owned Commercial Bank | F18: LDB Head Office — Vientiane | G18: LDB001 | H18: Vientiane Capital | I18: LDBBLALAXXX | J18: 33/1 Lane Xang Avenue, Hatsady District | K18: 33/1 Lane Xang Avenue, Hatsady District, Vientiane Capital | L18: +856 21 213 300 | M18: 100% Ministry of Finance, Lao PDR | N18: 2003 | O18: www.ldblao.la | P18: 46023 | R18: 46023 | S18: MoF System Update | T18: BOL Bank Registry / Bank of Lao PDR | U18: Updated per MoF Guideline 4904/MOF (Jan 2026)
A19: 14 | B19: Lao Development Bank (LDB) | C19: LDB | D19: LDB | E19: State-Owned Commercial Bank | F19: LDB Nong Bone Branch | G19: LDB002 | H19: Vientiane Capital | I19: LDBBLALAXXX | J19: Nong Bone Road, Xaysettha District | K19: ↑ same bank | P19: 46023 | R19: 46023 | S19: MoF System Update | T19: BOL Bank Registry / Bank of Lao PDR | U19: Updated per MoF Guideline 4904/MOF (Jan 2026)
A20: 15 | B20: Lao Development Bank (LDB) | C20: LDB | D20: LDB | E20: State-Owned Commercial Bank | F20: LDB Savannakhet Branch | G20: LDB003 | H20: Savannakhet | I20: LDBBLALAXXX | J20: Kaysone Phomvihane Town, Savannakhet | K20: ↑ same bank | P20: 46023 | R20: 46023 | S20: MoF System Update | T20: BOL Bank Registry / Bank of Lao PDR | U20: Updated per MoF Guideline 4904/MOF (Jan 2026)
A21: 16 | B21: Lao Development Bank (LDB) | C21: LDB | D21: LDB | E21: State-Owned Commercial Bank | F21: LDB Champasak / Pakse Branch | G21: LDB004 | H21: Champasak | I21: LDBBLALAXXX | J21: Pakse City, Champasak Province | K21: ↑ same bank | P21: 46023 | R21: 46023 | S21: MoF System Update | T21: BOL Bank Registry / Bank of Lao PDR | U21: Updated per MoF Guideline 4904/MOF (Jan 2026)
A22: 17 | B22: Lao Development Bank (LDB) | C22: LDB | D22: LDB | E22: State-Owned Commercial Bank | F22: LDB Luang Prabang Branch | G22: LDB005 | H22: Luang Prabang | I22: LDBBLALAXXX | J22: Luang Prabang Town Centre | K22: ↑ same bank | P22: 46023 | R22: 46023 | S22: MoF System Update | T22: BOL Bank Registry / Bank of Lao PDR | U22: Updated per MoF Guideline 4904/MOF (Jan 2026)
A23: 18 | B23: Lao Development Bank (LDB) | C23: LDB | D23: LDB | E23: State-Owned Commercial Bank | F23: LDB Luang Namtha Branch | G23: LDB006 | H23: Luang Namtha | I23: LDBBLALAXXX | J23: Luang Namtha Town, Luang Namtha Province | K23: ↑ same bank | P23: 46023 | R23: 46023 | S23: MoF System Update | T23: BOL Bank Registry / Bank of Lao PDR | U23: Updated per MoF Guideline 4904/MOF (Jan 2026)
A24: 19 | B24: Lao Development Bank (LDB) | C24: LDB | D24: LDB | E24: State-Owned Commercial Bank | F24: LDB Khammuane Branch | G24: LDB007 | H24: Khammuane | I24: LDBBLALAXXX | J24: Thakhek Town, Khammuane Province | K24: ↑ same bank | P24: 46023 | R24: 46023 | S24: MoF System Update | T24: BOL Bank Registry / Bank of Lao PDR | U24: Updated per MoF Guideline 4904/MOF (Jan 2026)
A25: 20 | B25: Agricultural Promotion Bank (APB) | C25: APB | D25: APB | E25: State-Owned Commercial Bank | F25: APB Head Office — Vientiane | G25: APB001 | H25: Vientiane Capital | I25: AGPBLALAXXX | J25: No.58 Hengboun Street, Ban Haysoke | K25: No.58 Hengboun Street, Ban Haysoke, Vientiane Capital | L25: +856 21 212 024 | M25: 100% Lao Government (Ministry of Finance) | N25: 1993 | O25: www.apb.com.la | P25: 46023 | R25: 46023 | S25: MoF System Update | T25: BOL Bank Registry / Bank of Lao PDR | U25: Updated per MoF Guideline 4904/MOF (Jan 2026)
A26: 21 | B26: Agricultural Promotion Bank (APB) | C26: APB | D26: APB | E26: State-Owned Commercial Bank | F26: APB Savannakhet Branch | G26: APB002 | H26: Savannakhet | I26: AGPBLALAXXX | J26: Kaysone Phomvihane Road, Savannakhet | K26: ↑ same bank | P26: 46023 | R26: 46023 | S26: MoF System Update | T26: BOL Bank Registry / Bank of Lao PDR | U26: Updated per MoF Guideline 4904/MOF (Jan 2026)
A27: 22 | B27: Agricultural Promotion Bank (APB) | C27: APB | D27: APB | E27: State-Owned Commercial Bank | F27: APB Luang Prabang Branch | G27: APB003 | H27: Luang Prabang | I27: AGPBLALAXXX | J27: Luang Prabang Town | K27: ↑ same bank | P27: 46023 | R27: 46023 | S27: MoF System Update | T27: BOL Bank Registry / Bank of Lao PDR | U27: Updated per MoF Guideline 4904/MOF (Jan 2026)
A28: 23 | B28: Agricultural Promotion Bank (APB) | C28: APB | D28: APB | E28: State-Owned Commercial Bank | F28: APB Champasak Branch | G28: APB004 | H28: Champasak | I28: AGPBLALAXXX | J28: Pakse, Champasak Province | K28: ↑ same bank | P28: 46023 | R28: 46023 | S28: MoF System Update | T28: BOL Bank Registry / Bank of Lao PDR | U28: Updated per MoF Guideline 4904/MOF (Jan 2026)
A29: 24 | B29: Agricultural Promotion Bank (APB) | C29: APB | D29: APB | E29: State-Owned Commercial Bank | F29: APB Khammuane Branch | G29: APB005 | H29: Khammuane | I29: AGPBLALAXXX | J29: Thakhek, Khammuane Province | K29: ↑ same bank | P29: 46023 | R29: 46023 | S29: MoF System Update | T29: BOL Bank Registry / Bank of Lao PDR | U29: Updated per MoF Guideline 4904/MOF (Jan 2026)
A30: 25 | B30: Agricultural Promotion Bank (APB) | C30: APB | D30: APB | E30: State-Owned Commercial Bank | F30: APB Xiengkhuang Branch | G30: APB006 | H30: Xiengkhuang | I30: AGPBLALAXXX | J30: Phonsavan Town, Xiengkhuang | K30: ↑ same bank | P30: 46023 | R30: 46023 | S30: MoF System Update | T30: BOL Bank Registry / Bank of Lao PDR | U30: Updated per MoF Guideline 4904/MOF (Jan 2026)
A31: 26 | B31: Agricultural Promotion Bank (APB) | C31: APB | D31: APB | E31: State-Owned Commercial Bank | F31: APB Oudomxay Branch | G31: APB007 | H31: Oudomxay | I31: AGPBLALAXXX | J31: Muang Xay, Oudomxay Province | K31: ↑ same bank | P31: 46023 | R31: 46023 | S31: MoF System Update | T31: BOL Bank Registry / Bank of Lao PDR | U31: Updated per MoF Guideline 4904/MOF (Jan 2026)
A32: 27 | B32: Nayoby Bank (NBB) — Specialized Development Bank | C32: NBB | D32: NBB | E32: Specialized State Bank | F32: NBB Head Office — Vientiane | G32: NBB001 | H32: Vientiane Capital | I32: NAOBLALAXXX | J32: Lane Xang Avenue, Vientiane Capital | K32: Lane Xang Avenue, Vientiane Capital | L32: +856 21 222 222 | M32: 100% Lao Government — microfinance and rural credit focus | N32: 2006 | O32: www.nbb.com.la | P32: 46023 | R32: 46023 | S32: MoF System Update | T32: BOL Bank Registry / Bank of Lao PDR | U32: Updated per MoF Guideline 4904/MOF (Jan 2026)
A33: 28 | B33: Nayoby Bank (NBB) — Specialized Development Bank | C33: NBB | D33: NBB | E33: Specialized State Bank | F33: NBB Savannakhet Branch | G33: NBB002 | H33: Savannakhet | I33: NAOBLALAXXX | J33: Savannakhet Town, Savannakhet | K33: ↑ same bank | P33: 46023 | R33: 46023 | S33: MoF System Update | T33: BOL Bank Registry / Bank of Lao PDR | U33: Updated per MoF Guideline 4904/MOF (Jan 2026)
A34: 29 | B34: Nayoby Bank (NBB) — Specialized Development Bank | C34: NBB | D34: NBB | E34: Specialized State Bank | F34: NBB Luang Prabang Branch | G34: NBB003 | H34: Luang Prabang | I34: NAOBLALAXXX | J34: Luang Prabang Town | K34: ↑ same bank | P34: 46023 | R34: 46023 | S34: MoF System Update | T34: BOL Bank Registry / Bank of Lao PDR | U34: Updated per MoF Guideline 4904/MOF (Jan 2026)
A35: 🏛️ Joint-State Commercial Banks (4 banks) | P35: 46023 | R35: 46023 | S35: MoF System Update | T35: BOL Bank Registry / Bank of Lao PDR | U35: Updated per MoF Guideline 4904/MOF (Jan 2026)
A36: 30 | B36: Joint Development Bank (JDB) | C36: JDB | D36: JDB | E36: Joint-State Commercial Bank | F36: JDB Head Office — Vientiane | G36: JDB001 | H36: Vientiane Capital | I36: JDBLLAOLXXX | J36: No.33 Lane Xang Avenue, Vientiane | K36: No.33 Lane Xang Avenue, Vientiane Capital | L36: +856 21 213 500 | M36: Lao PDR Govt 50% + Private shareholders 50% | N36: 1989 | O36: www.jdblao.com | P36: 46023 | R36: 46023 | S36: MoF System Update | T36: BOL Bank Registry / Bank of Lao PDR | U36: Updated per MoF Guideline 4904/MOF (Jan 2026)
A37: 31 | B37: Joint Development Bank (JDB) | C37: JDB | D37: JDB | E37: Joint-State Commercial Bank | F37: JDB Samsenthai Branch | G37: JDB002 | H37: Vientiane Capital | I37: JDBLLAOLXXX | J37: Samsenthai Road, Vientiane Capital | K37: ↑ same bank | P37: 46023 | R37: 46023 | S37: MoF System Update | T37: BOL Bank Registry / Bank of Lao PDR | U37: Updated per MoF Guideline 4904/MOF (Jan 2026)
A38: 32 | B38: Joint Development Bank (JDB) | C38: JDB | D38: JDB | E38: Joint-State Commercial Bank | F38: JDB Savannakhet Branch | G38: JDB003 | H38: Savannakhet | I38: JDBLLAOLXXX | J38: Savannakhet Town Centre | K38: ↑ same bank | P38: 46023 | R38: 46023 | S38: MoF System Update | T38: BOL Bank Registry / Bank of Lao PDR | U38: Updated per MoF Guideline 4904/MOF (Jan 2026)
A39: 33 | B39: Joint Development Bank (JDB) | C39: JDB | D39: JDB | E39: Joint-State Commercial Bank | F39: JDB Champasak Branch | G39: JDB004 | H39: Champasak | I39: JDBLLAOLXXX | J39: Pakse City, Champasak | K39: ↑ same bank | P39: 46023 | R39: 46023 | S39: MoF System Update | T39: BOL Bank Registry / Bank of Lao PDR | U39: Updated per MoF Guideline 4904/MOF (Jan 2026)
A40: 34 | B40: Joint Development Bank (JDB) | C40: JDB | D40: JDB | E40: Joint-State Commercial Bank | F40: JDB Luang Prabang Branch | G40: JDB005 | H40: Luang Prabang | I40: JDBLLAOLXXX | J40: Luang Prabang Town | K40: ↑ same bank | P40: 46023 | R40: 46023 | S40: MoF System Update | T40: BOL Bank Registry / Bank of Lao PDR | U40: Updated per MoF Guideline 4904/MOF (Jan 2026)
A41: 35 | B41: Lao-Viet Bank (LVB) | C41: LVB | D41: LVB | E41: Joint-State Commercial Bank | F41: LVB Head Office — Vientiane | G41: LVB001 | H41: Vientiane Capital | I41: LVBKLALAXXX | J41: No.41 Thadeua Road, Vientiane | K41: No.41 Thadeua Road, Vientiane Capital | L41: +856 21 480 777 | M41: BCEL 50% (Lao) + BIDV 50% (Vietnam) | N41: 1999 | O41: www.laovietbank.com.la | P41: 46023 | R41: 46023 | S41: MoF System Update | T41: BOL Bank Registry / Bank of Lao PDR | U41: Updated per MoF Guideline 4904/MOF (Jan 2026)
A42: 36 | B42: Lao-Viet Bank (LVB) | C42: LVB | D42: LVB | E42: Joint-State Commercial Bank | F42: LVB Savannakhet Branch | G42: LVB002 | H42: Savannakhet | I42: LVBKLALAXXX | J42: Savannakhet Province | K42: ↑ same bank | P42: 46023 | R42: 46023 | S42: MoF System Update | T42: BOL Bank Registry / Bank of Lao PDR | U42: Updated per MoF Guideline 4904/MOF (Jan 2026)
A43: 37 | B43: Lao-Viet Bank (LVB) | C43: LVB | D43: LVB | E43: Joint-State Commercial Bank | F43: LVB Champasak Branch | G43: LVB003 | H43: Champasak | I43: LVBKLALAXXX | J43: Pakse, Champasak Province | K43: ↑ same bank | P43: 46023 | R43: 46023 | S43: MoF System Update | T43: BOL Bank Registry / Bank of Lao PDR | U43: Updated per MoF Guideline 4904/MOF (Jan 2026)
A44: 38 | B44: Banque Franco-Lao (BFL) | C44: BFL | D44: BFL | E44: Joint-State Commercial Bank | F44: BFL Head Office — Vientiane | G44: BFL001 | H44: Vientiane Capital | I44: BFLLLALAXXX | J44: Avenue Lane Xang, Ban Hatsady, Chanthabouli | K44: Avenue Lane Xang, Ban Hatsady, Chanthabouli, Vientiane Capital | L44: +856 21 285 111 | M44: BCEL/Lao Govt 46% + BRED Banque Populaire (France) 54% | N44: 2008 | O44: www.bfl-bred.com | P44: 46023 | R44: 46023 | S44: MoF System Update | T44: BOL Bank Registry / Bank of Lao PDR | U44: Updated per MoF Guideline 4904/MOF (Jan 2026)
A45: 39 | B45: Banque Franco-Lao (BFL) | C45: BFL | D45: BFL | E45: Joint-State Commercial Bank | F45: BFL Savannakhet Branch | G45: BFL002 | H45: Savannakhet | I45: BFLLLALAXXX | J45: Savannakhet Town | K45: ↑ same bank | P45: 46023 | R45: 46023 | S45: MoF System Update | T45: BOL Bank Registry / Bank of Lao PDR | U45: Updated per MoF Guideline 4904/MOF (Jan 2026)
A46: 40 | B46: Lao China Bank (LCNB) | C46: LCNB | D46: LCNB | E46: Joint-State Commercial Bank | F46: LCNB Head Office — Vientiane | G46: LCNB001 | H46: Vientiane Capital | I46: LCNBLALAXXX | J46: Phonhong Road, Vientiane Capital | K46: Phonhong Road, Vientiane Capital | L46: +856 21 255 999 | M46: BCEL (Lao) + Fudian Bank (China) | N46: 2014 | O46: www.lcnb.la | P46: 46023 | R46: 46023 | S46: MoF System Update | T46: BOL Bank Registry / Bank of Lao PDR | U46: Updated per MoF Guideline 4904/MOF (Jan 2026)
A47: 41 | B47: Lao China Bank (LCNB) | C47: LCNB | D47: LCNB | E47: Joint-State Commercial Bank | F47: LCNB Luang Prabang Branch | G47: LCNB002 | H47: Luang Prabang | I47: LCNBLALAXXX | J47: Luang Prabang Town | K47: ↑ same bank | P47: 46023 | R47: 46023 | S47: MoF System Update | T47: BOL Bank Registry / Bank of Lao PDR | U47: Updated per MoF Guideline 4904/MOF (Jan 2026)
A48: 42 | B48: Lao China Bank (LCNB) | C48: LCNB | D48: LCNB | E48: Joint-State Commercial Bank | F48: LCNB Boten SEZ Branch | G48: LCNB003 | H48: Luang Namtha | I48: LCNBLALAXXX | J48: Boten Special Economic Zone, Luang Namtha | K48: ↑ same bank | P48: 46023 | R48: 46023 | S48: MoF System Update | T48: BOL Bank Registry / Bank of Lao PDR | U48: Updated per MoF Guideline 4904/MOF (Jan 2026)
A49: 🏢 Private Lao Commercial Banks (5 banks) | P49: 46023 | R49: 46023 | S49: MoF System Update | T49: BOL Bank Registry / Bank of Lao PDR | U49: Updated per MoF Guideline 4904/MOF (Jan 2026)
A50: 43 | B50: Phongsavanh Bank (PSV) | C50: PSV | D50: PSV | E50: Private Lao Commercial Bank | F50: PSV Head Office — Vientiane | G50: PSV001 | H50: Vientiane Capital | I50: PSVBLALAXXX | J50: No.42 Samsenthai Road, Vientiane | K50: No.42 Samsenthai Road, Vientiane Capital | L50: +856 21 213 444 | M50: Lao private shareholders (Phongsavanh Group) | N50: 2007 | O50: www.psvbank.com | P50: 46023 | R50: 46023 | S50: MoF System Update | T50: BOL Bank Registry / Bank of Lao PDR | U50: Updated per MoF Guideline 4904/MOF (Jan 2026)
A51: 44 | B51: Phongsavanh Bank (PSV) | C51: PSV | D51: PSV | E51: Private Lao Commercial Bank | F51: PSV Saysettha Branch | G51: PSV002 | H51: Vientiane Capital | I51: PSVBLALAXXX | J51: Nong Bone Road, Saysettha District | K51: ↑ same bank | P51: 46023 | R51: 46023 | S51: MoF System Update | T51: BOL Bank Registry / Bank of Lao PDR | U51: Updated per MoF Guideline 4904/MOF (Jan 2026)
A52: 45 | B52: Phongsavanh Bank (PSV) | C52: PSV | D52: PSV | E52: Private Lao Commercial Bank | F52: PSV Savannakhet Branch | G52: PSV003 | H52: Savannakhet | I52: PSVBLALAXXX | J52: Kaysone Phomvihane, Savannakhet | K52: ↑ same bank | P52: 46023 | R52: 46023 | S52: MoF System Update | T52: BOL Bank Registry / Bank of Lao PDR | U52: Updated per MoF Guideline 4904/MOF (Jan 2026)
A53: 46 | B53: Phongsavanh Bank (PSV) | C53: PSV | D53: PSV | E53: Private Lao Commercial Bank | F53: PSV Champasak Branch | G53: PSV004 | H53: Champasak | I53: PSVBLALAXXX | J53: Pakse City, Champasak | K53: ↑ same bank | P53: 46023 | R53: 46023 | S53: MoF System Update | T53: BOL Bank Registry / Bank of Lao PDR | U53: Updated per MoF Guideline 4904/MOF (Jan 2026)
A54: 47 | B54: Phongsavanh Bank (PSV) | C54: PSV | D54: PSV | E54: Private Lao Commercial Bank | F54: PSV Luang Prabang Branch | G54: PSV005 | H54: Luang Prabang | I54: PSVBLALAXXX | J54: Luang Prabang Town | K54: ↑ same bank | P54: 46023 | R54: 46023 | S54: MoF System Update | T54: BOL Bank Registry / Bank of Lao PDR | U54: Updated per MoF Guideline 4904/MOF (Jan 2026)
A55: 48 | B55: Phongsavanh Bank (PSV) | C55: PSV | D55: PSV | E55: Private Lao Commercial Bank | F55: PSV Oudomxay Branch | G55: PSV006 | H55: Oudomxay | I55: PSVBLALAXXX | J55: Muang Xay, Oudomxay Province | K55: ↑ same bank | P55: 46023 | R55: 46023 | S55: MoF System Update | T55: BOL Bank Registry / Bank of Lao PDR | U55: Updated per MoF Guideline 4904/MOF (Jan 2026)
A56: 49 | B56: BIC Bank Lao | C56: BIC | D56: BIC | E56: Private Lao Commercial Bank | F56: BIC Head Office — Vientiane | G56: BIC001 | H56: Vientiane Capital | I56: BICBLALAXXX | J56: Nong Bone Road, Xaysettha District | K56: Nong Bone Road, Xaysettha District, Vientiane Capital | L56: +856 21 414 333 | M56: Lao private shareholders (formerly ICB Lao, renamed 2011) | N56: 2008 | O56: www.bicbank.com.la | P56: 46023 | R56: 46023 | S56: MoF System Update | T56: BOL Bank Registry / Bank of Lao PDR | U56: Updated per MoF Guideline 4904/MOF (Jan 2026)
A57: 50 | B57: BIC Bank Lao | C57: BIC | D57: BIC | E57: Private Lao Commercial Bank | F57: BIC Savannakhet Branch | G57: BIC002 | H57: Savannakhet | I57: BICBLALAXXX | J57: Savannakhet Province | K57: ↑ same bank | P57: 46023 | R57: 46023 | S57: MoF System Update | T57: BOL Bank Registry / Bank of Lao PDR | U57: Updated per MoF Guideline 4904/MOF (Jan 2026)
A58: 51 | B58: ST Bank (STB) | C58: STB | D58: STB | E58: Private Lao Commercial Bank | F58: STB Head Office — Vientiane | G58: STB001 | H58: Vientiane Capital | I58: STBDLALAXXX | J58: No.144 Samsenthai Road, Ban Anou, Chanthabouly | K58: No.144 Samsenthai Road, Ban Anou, Chanthabouly, Vientiane Capital | L58: +856 21 241 559 | M58: Lao private shareholders | N58: 2008 | O58: www.stb.com.la | P58: 46023 | R58: 46023 | S58: MoF System Update | T58: BOL Bank Registry / Bank of Lao PDR | U58: Updated per MoF Guideline 4904/MOF (Jan 2026)
A59: 52 | B59: ST Bank (STB) | C59: STB | D59: STB | E59: Private Lao Commercial Bank | F59: STB Champasak Branch | G59: STB002 | H59: Champasak | I59: STBDLALAXXX | J59: Pakse City, Champasak | K59: ↑ same bank | P59: 46023 | R59: 46023 | S59: MoF System Update | T59: BOL Bank Registry / Bank of Lao PDR | U59: Updated per MoF Guideline 4904/MOF (Jan 2026)
A60: 53 | B60: Indochina Bank Lao | C60: ICB | D60: ICB | E60: Private Lao Commercial Bank | F60: Indochina Bank HO — Vientiane | G60: ICB001 | H60: Vientiane Capital | I60: INDCLALAXXX | J60: Khounbulom Road, Vientiane Capital | K60: Khounbulom Road, Vientiane Capital | L60: +856 21 213 600 | M60: Lao private shareholders | N60: 2008 | O60: www.indochinabank.la | P60: 46023 | R60: 46023 | S60: MoF System Update | T60: BOL Bank Registry / Bank of Lao PDR | U60: Updated per MoF Guideline 4904/MOF (Jan 2026)
A61: 54 | B61: Lao Microfinance Institution (LMI) | C61: LMI | D61: LMI | E61: Private Lao Commercial Bank | F61: LMI Head Office — Vientiane | G61: LMI001 | H61: Vientiane Capital | I61: LMFILALAXXX | J61: Vientiane Capital | K61: Vientiane Capital | L61: +856 21 220 000 | M61: Lao private shareholders | N61: 2010 | O61: www.lmi.la | P61: 46023 | R61: 46023 | S61: MoF System Update | T61: BOL Bank Registry / Bank of Lao PDR | U61: Updated per MoF Guideline 4904/MOF (Jan 2026)
A62: 🌏 Foreign Bank Subsidiaries (7 banks) | P62: 46023 | R62: 46023 | S62: MoF System Update | T62: BOL Bank Registry / Bank of Lao PDR | U62: Updated per MoF Guideline 4904/MOF (Jan 2026)
A63: 55 | B63: Maruhan Japan Bank Lao (MJBL) | C63: MJBL | D63: MJBL | E63: Foreign Subsidiary Bank | F63: MJBL Head Office — Vientiane | G63: MJBL001 | H63: Vientiane Capital | I63: MJBLLALAXXX | J63: Sikhottabong District, Vientiane Capital | K63: Sikhottabong District, Vientiane Capital | L63: +856 21 900 100 | M63: Maruhan Corporation (Japan) 100% | N63: 2014 | O63: www.maruhan-lao.com | P63: 46023 | R63: 46023 | S63: MoF System Update | T63: BOL Bank Registry / Bank of Lao PDR | U63: Updated per MoF Guideline 4904/MOF (Jan 2026)
A64: 56 | B64: Maruhan Japan Bank Lao (MJBL) | C64: MJBL | D64: MJBL | E64: Foreign Subsidiary Bank | F64: MJBL Savannakhet Branch | G64: MJBL002 | H64: Savannakhet | I64: MJBLLALAXXX | J64: Kaysone Phomvihane, Savannakhet | K64: ↑ same bank | P64: 46023 | R64: 46023 | S64: MoF System Update | T64: BOL Bank Registry / Bank of Lao PDR | U64: Updated per MoF Guideline 4904/MOF (Jan 2026)
A65: 57 | B65: ACLEDA Bank Lao Ltd (ABL) | C65: ABL | D65: ABL | E65: Foreign Subsidiary Bank | F65: ABL Head Office — Vientiane | G65: ABL001 | H65: Vientiane Capital | I65: ACBLLALAXXX | J65: Sikhottabong District, Vientiane | K65: Sikhottabong District, Vientiane Capital | L65: +856 21 223 506 | M65: ACLEDA Bank Plc (Cambodia) majority — Cambodia/Lao joint subsidiary | N65: 2019 | O65: www.acledabank.com.la | P65: 46023 | R65: 46023 | S65: MoF System Update | T65: BOL Bank Registry / Bank of Lao PDR | U65: Updated per MoF Guideline 4904/MOF (Jan 2026)
A66: 58 | B66: ACLEDA Bank Lao Ltd (ABL) | C66: ABL | D66: ABL | E66: Foreign Subsidiary Bank | F66: ABL Savannakhet Branch | G66: ABL002 | H66: Savannakhet | I66: ACBLLALAXXX | J66: Savannakhet Province | K66: ↑ same bank | P66: 46023 | R66: 46023 | S66: MoF System Update | T66: BOL Bank Registry / Bank of Lao PDR | U66: Updated per MoF Guideline 4904/MOF (Jan 2026)
A67: 59 | B67: ACLEDA Bank Lao Ltd (ABL) | C67: ABL | D67: ABL | E67: Foreign Subsidiary Bank | F67: ABL Champasak Branch | G67: ABL003 | H67: Champasak | I67: ACBLLALAXXX | J67: Pakse, Champasak Province | K67: ↑ same bank | P67: 46023 | R67: 46023 | S67: MoF System Update | T67: BOL Bank Registry / Bank of Lao PDR | U67: Updated per MoF Guideline 4904/MOF (Jan 2026)
A68: 60 | B68: Canadia Bank Lao Co., Ltd. | C68: CAB | D68: CAB | E68: Foreign Subsidiary Bank | F68: Canadia Bank HO — Vientiane | G68: CAB001 | H68: Vientiane Capital | I68: CABLALAXXX | J68: Vientiane Capital | K68: Vientiane Capital | L68: +856 21 260 999 | M68: Canadia Bank Plc (Cambodia) 100% | N68: 2015 | O68: www.canadiabank.com.la | P68: 46023 | R68: 46023 | S68: MoF System Update | T68: BOL Bank Registry / Bank of Lao PDR | U68: Updated per MoF Guideline 4904/MOF (Jan 2026)
A69: 61 | B69: Public Bank Lao Ltd. | C69: PBL | D69: PBL | E69: Foreign Subsidiary Bank | F69: PBL Head Office — Vientiane | G69: PBL001 | H69: Vientiane Capital | I69: PBLLLALAXXX | J69: Vientiane Capital | K69: Vientiane Capital | L69: +856 21 255 333 | M69: Public Bank Berhad (Malaysia) majority | N69: 2011 | O69: www.publicbanklaos.com | P69: 46023 | R69: 46023 | S69: MoF System Update | T69: BOL Bank Registry / Bank of Lao PDR | U69: Updated per MoF Guideline 4904/MOF (Jan 2026)
A70: 62 | B70: Sacombank Lao | C70: SCL | D70: SCL | E70: Foreign Subsidiary Bank | F70: Sacombank Lao HO — Vientiane | G70: SCL001 | H70: Vientiane Capital | I70: SGTBLALAXXX | J70: Vientiane Capital | K70: Vientiane Capital | L70: +856 21 412 333 | M70: Sacombank (Vietnam) 100% | N70: 2008 | O70: www.sacombanklao.com | P70: 46023 | R70: 46023 | S70: MoF System Update | T70: BOL Bank Registry / Bank of Lao PDR | U70: Updated per MoF Guideline 4904/MOF (Jan 2026)
A71: 63 | B71: Sacombank Lao | C71: SCL | D71: SCL | E71: Foreign Subsidiary Bank | F71: Sacombank Lao Savannakhet | G71: SCL002 | H71: Savannakhet | I71: SGTBLALAXXX | J71: Savannakhet Province | K71: ↑ same bank | P71: 46023 | R71: 46023 | S71: MoF System Update | T71: BOL Bank Registry / Bank of Lao PDR | U71: Updated per MoF Guideline 4904/MOF (Jan 2026)
A72: 64 | B72: SHB Laos | C72: SHB | D72: SHB | E72: Foreign Subsidiary Bank | F72: SHB Laos HO — Vientiane | G72: SHB001 | H72: Vientiane Capital | I72: SHBLLALAXXX | J72: Vientiane Capital | K72: Vientiane Capital | L72: +856 21 900 999 | M72: Saigon-Hanoi Commercial Joint Stock Bank (Vietnam) 100% | N72: 2016 | O72: www.shb.com.vn | P72: 46023 | R72: 46023 | S72: MoF System Update | T72: BOL Bank Registry / Bank of Lao PDR | U72: Updated per MoF Guideline 4904/MOF (Jan 2026)
A73: 65 | B73: Vietcombank Laos Ltd. | C73: VCB | D73: VCB | E73: Foreign Subsidiary Bank | F73: Vietcombank Laos HO — Vientiane | G73: VCB001 | H73: Vientiane Capital | I73: BFTVLALAXXX | J73: Vientiane Capital | K73: Vientiane Capital | L73: +856 21 450 000 | M73: Joint Stock Commercial Bank for Foreign Trade of Vietnam (Vietcombank) 100% | N73: 2018 | O73: www.vcblaos.com | P73: 46023 | R73: 46023 | S73: MoF System Update | T73: BOL Bank Registry / Bank of Lao PDR | U73: Updated per MoF Guideline 4904/MOF (Jan 2026)
A74: 🌐 Foreign Bank Branches (8 banks) | P74: 46023 | R74: 46023 | S74: MoF System Update | T74: BOL Bank Registry / Bank of Lao PDR | U74: Updated per MoF Guideline 4904/MOF (Jan 2026)
A75: 66 | B75: Vietinbank (Lao Branch) | C75: VTB | D75: VTB | E75: Foreign Bank Branch | F75: Vietinbank Vientiane Branch | G75: VTB001 | H75: Vientiane Capital | I75: ICBVLAL1XXX | J75: 029 Khounbulom Road, Chanthabouli | K75: 029 Khounbulom Road, Ban Vatchan, Chanthabouli, Vientiane Capital | L75: +856 21 263 997 | M75: Vietnam Joint Stock Commercial Bank for Industry and Trade — Branch | N75: 2011 | O75: www.vietinbank.vn | P75: 46023 | R75: 46023 | S75: MoF System Update | T75: BOL Bank Registry / Bank of Lao PDR | U75: Updated per MoF Guideline 4904/MOF (Jan 2026)
A76: 67 | B76: Bangkok Bank Public Co. Ltd — Vientiane Branch | C76: BBL | D76: BBL | E76: Foreign Bank Branch | F76: Bangkok Bank Vientiane Branch | G76: BBL001 | H76: Vientiane Capital | I76: BKKBLALAXXX | J76: Lane Xang Avenue, Vientiane Capital | K76: Lane Xang Avenue, Vientiane Capital | L76: +856 21 213 560 | M76: Bangkok Bank Public Company Limited (Thailand) — Branch | N76: 1993 | O76: www.bangkokbank.com | P76: 46023 | R76: 46023 | S76: MoF System Update | T76: BOL Bank Registry / Bank of Lao PDR | U76: Updated per MoF Guideline 4904/MOF (Jan 2026)
A77: 68 | B77: Bank of Ayudhya (Krungsri) — Vientiane Branch | C77: BAY | D77: BAY | E77: Foreign Bank Branch | F77: Krungsri Vientiane Branch | G77: BAY001 | H77: Vientiane Capital | I77: AYUDLALAXXX | J77: 084/1 Lane Xang Avenue, Vientiane | K77: 084/1 Lane Xang Avenue, Vientiane Capital | L77: +856 21 222 700 | M77: Bank of Ayudhya / Krungsri (Thailand, MUFG Group) — Branch | N77: 2008 | O77: www.krungsri.com | P77: 46023 | R77: 46023 | S77: MoF System Update | T77: BOL Bank Registry / Bank of Lao PDR | U77: Updated per MoF Guideline 4904/MOF (Jan 2026)
A78: 69 | B78: Krung Thai Bank (KTB) — Vientiane Branch | C78: KTB | D78: KTB | E78: Foreign Bank Branch | F78: KTB Vientiane Branch | G78: KTB001 | H78: Vientiane Capital | I78: KRTHLAOLXXX | J78: Vientiane Capital | K78: Vientiane Capital | L78: +856 21 222 800 | M78: Krung Thai Bank (Thailand, state-owned) — Branch | N78: 2010 | O78: www.ktb.co.th | P78: 46023 | R78: 46023 | S78: MoF System Update | T78: BOL Bank Registry / Bank of Lao PDR | U78: Updated per MoF Guideline 4904/MOF (Jan 2026)
A79: 70 | B79: Siam Commercial Bank (SCB) — Vientiane Branch | C79: SCB | D79: SCBV | E79: Foreign Bank Branch | F79: SCB Vientiane Branch | G79: SCBV001 | H79: Vientiane Capital | I79: SICOTHBXXXX | J79: Vientiane Capital | K79: Vientiane Capital | L79: +856 21 222 900 | M79: Siam Commercial Bank (Thailand) — Branch | N79: 2008 | O79: www.scb.co.th | P79: 46023 | R79: 46023 | S79: MoF System Update | T79: BOL Bank Registry / Bank of Lao PDR | U79: Updated per MoF Guideline 4904/MOF (Jan 2026)
A80: 71 | B80: ANZ (Lao Branch) | C80: ANZ | D80: ANZ | E80: Foreign Bank Branch | F80: ANZ Vientiane Branch | G80: ANZ001 | H80: Vientiane Capital | I80: ANZBLAOLXXX | J80: Lane Xang Avenue, Vientiane Capital | K80: Lane Xang Avenue, Vientiane Capital | L80: +856 21 222 700 | M80: Australia and New Zealand Banking Group (Australia) — Branch since 2019 | N80: 2007 | O80: www.anz.com | P80: 46023 | R80: 46023 | S80: MoF System Update | T80: BOL Bank Registry / Bank of Lao PDR | U80: Updated per MoF Guideline 4904/MOF (Jan 2026)
A81: 72 | B81: ICBC (Industrial & Commercial Bank of China) — Lao Branch | C81: ICBC | D81: ICBC | E81: Foreign Bank Branch | F81: ICBC Vientiane Branch | G81: ICBC001 | H81: Vientiane Capital | I81: ICBKLAOLXXX | J81: Vientiane Capital | K81: Vientiane Capital | L81: +856 21 263 000 | M81: Industrial and Commercial Bank of China (ICBC) — Branch | N81: 2012 | O81: www.icbc-ltd.com | P81: 46023 | R81: 46023 | S81: MoF System Update | T81: BOL Bank Registry / Bank of Lao PDR | U81: Updated per MoF Guideline 4904/MOF (Jan 2026)
A82: 73 | B82: Bank of China (Lao Branch) | C82: BOC | D82: BOC | E82: Foreign Bank Branch | F82: Bank of China Vientiane Branch | G82: BOC001 | H82: Vientiane Capital | I82: BKCHLAOLXXX | J82: Vientiane Capital | K82: Vientiane Capital | L82: +856 21 250 000 | M82: Bank of China (PRC) — Branch | N82: 2012 | O82: www.boc.cn | P82: 46023 | R82: 46023 | S82: MoF System Update | T82: BOL Bank Registry / Bank of Lao PDR | U82: Updated per MoF Guideline 4904/MOF (Jan 2026)
A83: TOTAL: 28 banks | 73 branches | 4 State + 4 Joint + 5 Private + 7 Foreign Subsidiaries + 8 Foreign Branches

Sheet LK_GradeDerivation
A1: GRADE & STEP DERIVATION — Education × Prior Experience (LK_GradeDerivation)
A2: ⭐ UPDATED PER MoF No. 4904/MOF (Dec 2025). Maps Education Level × Prior Experience → Grade/Step. STRUCTURE: Grades 1-5 for regular staff (15 steps each). Grade 6 is leadership by appointment, not derived. Rule: Base grade set by education; each 2 years of prior experience advances 1 step; overflow to next grade. PhD starts at Grade 5 Step 6. Update Col D/E if Civil Service Authority revises entry rules.
A3: Education Level | B3: Min Prior Exp (Yrs) | C3: Max Prior Exp (Yrs) | D3: Derived Grade | E3: Derived Step | F3: Rule Description | G3: Effective From (Date) | H3: Effective To (Date) | I3: Last Updated (Date) | J3: Last Updated By (Name/Code) | K3: Circular / Reference | L3: Change Remarks
A4: Below Secondary | B4: 0 | C4: 1 | D4: 1 | E4: 1 | F4: Edu: Below Secondary | Exp 0–1 yrs → G1 S1 | G4: 46023 | I4: 46023 | J4: MoF System Update | K4: MoF No. 4904/MOF, 26 Dec 2025 + CSA Entry Grade Rules | L4: Updated per MoF Guideline 4904/MOF (Jan 2026)
A5: Below Secondary | B5: 2 | C5: 3 | D5: 1 | E5: 2 | F5: Edu: Below Secondary | Exp 2–3 yrs → G1 S2 | G5: 46023 | I5: 46023 | J5: MoF System Update | K5: MoF No. 4904/MOF, 26 Dec 2025 + CSA Entry Grade Rules | L5: Updated per MoF Guideline 4904/MOF (Jan 2026)
A6: Below Secondary | B6: 4 | C6: 5 | D6: 1 | E6: 3 | F6: Edu: Below Secondary | Exp 4–5 yrs → G1 S3 | G6: 46023 | I6: 46023 | J6: MoF System Update | K6: MoF No. 4904/MOF, 26 Dec 2025 + CSA Entry Grade Rules | L6: Updated per MoF Guideline 4904/MOF (Jan 2026)
A7: Below Secondary | B7: 6 | C7: 7 | D7: 1 | E7: 4 | F7: Edu: Below Secondary | Exp 6–7 yrs → G1 S4 | G7: 46023 | I7: 46023 | J7: MoF System Update | K7: MoF No. 4904/MOF, 26 Dec 2025 + CSA Entry Grade Rules | L7: Updated per MoF Guideline 4904/MOF (Jan 2026)
A8: Below Secondary | B8: 8 | C8: 9 | D8: 1 | E8: 5 | F8: Edu: Below Secondary | Exp 8–9 yrs → G1 S5 | G8: 46023 | I8: 46023 | J8: MoF System Update | K8: MoF No. 4904/MOF, 26 Dec 2025 + CSA Entry Grade Rules | L8: Updated per MoF Guideline 4904/MOF (Jan 2026)
A9: Below Secondary | B9: 10 | C9: 11 | D9: 1 | E9: 6 | F9: Edu: Below Secondary | Exp 10–11 yrs → G1 S6 | G9: 46023 | I9: 46023 | J9: MoF System Update | K9: MoF No. 4904/MOF, 26 Dec 2025 + CSA Entry Grade Rules | L9: Updated per MoF Guideline 4904/MOF (Jan 2026)
A10: Below Secondary | B10: 12 | C10: 13 | D10: 1 | E10: 7 | F10: Edu: Below Secondary | Exp 12–13 yrs → G1 S7 | G10: 46023 | I10: 46023 | J10: MoF System Update | K10: MoF No. 4904/MOF, 26 Dec 2025 + CSA Entry Grade Rules | L10: Updated per MoF Guideline 4904/MOF (Jan 2026)
A11: Below Secondary | B11: 14 | C11: 15 | D11: 1 | E11: 8 | F11: Edu: Below Secondary | Exp 14–15 yrs → G1 S8 | G11: 46023 | I11: 46023 | J11: MoF System Update | K11: MoF No. 4904/MOF, 26 Dec 2025 + CSA Entry Grade Rules | L11: Updated per MoF Guideline 4904/MOF (Jan 2026)
A12: Below Secondary | B12: 16 | C12: 17 | D12: 1 | E12: 9 | F12: Edu: Below Secondary | Exp 16–17 yrs → G1 S9 | G12: 46023 | I12: 46023 | J12: MoF System Update | K12: MoF No. 4904/MOF, 26 Dec 2025 + CSA Entry Grade Rules | L12: Updated per MoF Guideline 4904/MOF (Jan 2026)
A13: Below Secondary | B13: 18 | C13: 19 | D13: 1 | E13: 10 | F13: Edu: Below Secondary | Exp 18–19 yrs → G1 S10 | G13: 46023 | I13: 46023 | J13: MoF System Update | K13: MoF No. 4904/MOF, 26 Dec 2025 + CSA Entry Grade Rules | L13: Updated per MoF Guideline 4904/MOF (Jan 2026)
A14: Below Secondary | B14: 20 | C14: 21 | D14: 1 | E14: 11 | F14: Edu: Below Secondary | Exp 20–21 yrs → G1 S11 | G14: 46023 | I14: 46023 | J14: MoF System Update | K14: MoF No. 4904/MOF, 26 Dec 2025 + CSA Entry Grade Rules | L14: Updated per MoF Guideline 4904/MOF (Jan 2026)
A15: Below Secondary | B15: 22 | C15: 23 | D15: 1 | E15: 12 | F15: Edu: Below Secondary | Exp 22–23 yrs → G1 S12 | G15: 46023 | I15: 46023 | J15: MoF System Update | K15: MoF No. 4904/MOF, 26 Dec 2025 + CSA Entry Grade Rules | L15: Updated per MoF Guideline 4904/MOF (Jan 2026)
... A135: Doctorate (PhD) | B135: 42 | C135: 99 | D135: 5 | E135: 12 | F135: Edu: Doctorate (PhD) | Exp 42–40+ yrs → G5 S12 | G135: 46023 | I135: 46023 | J135: MoF System Update | K135: MoF No. 4904/MOF, 26 Dec 2025 + CSA Entry Grade Rules | L135: Updated per MoF Guideline 4904/MOF (Jan 2026)

Sheet LK_GradeStep
A1: GRADE & STEP MULTIPLIER TABLE (LK_GradeStep)
A2: ⭐ UPDATED PER MoF No. 4904/MOF (Dec 2025). TWO INPUT COLUMNS: Col D = Grade/Step Index (from MoF matrix, 260-1200) | Col E = Salary Index Rate (LAK per index point, default 10,000). Basic Salary = Grade/Step Index × Salary Index Rate. STRUCTURE: 5 Grades × 15 Steps (regular staff) + Grade 6 × 7 Steps (leadership/appointed). UPDATE Col E when MoF revises the ຄ່າດັດສະນີ monetary rate. UPDATE Col D values if MoF revises the index matrix.
A3: Grade | B3: Step | C3: Grade-Step Key | D3: Grade/Step Index (MoF Matrix) | E3: Salary Index Rate (LAK per Index Point) | F3: Min. Education | G3: Min. Prior Exp (Yrs) | H3: Notes | I3: Effective From (Date) | J3: Effective To (Date) | K3: Last Updated (Date) | L3: Last Updated By (Name/Code) | M3: Circular / Reference | N3: Change Remarks
A4: 1 | B4: 1 | C4: ="G"&TEXT(A4,"00")&"-S"&TEXT(B4,"00") -> G01-S01 | D4: 260 | E4: 10000 | F4: Below Secondary | G4: 0 | H4: Basic=260×10,000=2,600,000 LAK | I4: 46023 | K4: 46023 | L4: MoF System Update | M4: MoF No. 4904/MOF, 26 Dec 2025 | N4: Updated per MoF Guideline 4904/MOF (Jan 2026)
A5: 1 | B5: 2 | C5: ="G"&TEXT(A5,"00")&"-S"&TEXT(B5,"00") -> G01-S02 | D5: 261 | E5: 10000 | F5: Below Secondary | G5: 2 | H5: Basic=261×10,000=2,610,000 LAK | I5: 46023 | K5: 46023 | L5: MoF System Update | M5: MoF No. 4904/MOF, 26 Dec 2025 | N5: Updated per MoF Guideline 4904/MOF (Jan 2026)
A6: 1 | B6: 3 | C6: ="G"&TEXT(A6,"00")&"-S"&TEXT(B6,"00") -> G01-S03 | D6: 262 | E6: 10000 | F6: Below Secondary | G6: 4 | H6: Basic=262×10,000=2,620,000 LAK | I6: 46023 | K6: 46023 | L6: MoF System Update | M6: MoF No. 4904/MOF, 26 Dec 2025 | N6: Updated per MoF Guideline 4904/MOF (Jan 2026)
A7: 1 | B7: 4 | C7: ="G"&TEXT(A7,"00")&"-S"&TEXT(B7,"00") -> G01-S04 | D7: 263 | E7: 10000 | F7: Below Secondary | G7: 6 | H7: Basic=263×10,000=2,630,000 LAK | I7: 46023 | K7: 46023 | L7: MoF System Update | M7: MoF No. 4904/MOF, 26 Dec 2025 | N7: Updated per MoF Guideline 4904/MOF (Jan 2026)
A8: 1 | B8: 5 | C8: ="G"&TEXT(A8,"00")&"-S"&TEXT(B8,"00") -> G01-S05 | D8: 264 | E8: 10000 | F8: Below Secondary | G8: 8 | H8: Basic=264×10,000=2,640,000 LAK | I8: 46023 | K8: 46023 | L8: MoF System Update | M8: MoF No. 4904/MOF, 26 Dec 2025 | N8: Updated per MoF Guideline 4904/MOF (Jan 2026)
A9: 1 | B9: 6 | C9: ="G"&TEXT(A9,"00")&"-S"&TEXT(B9,"00") -> G01-S06 | D9: 265 | E9: 10000 | F9: Below Secondary | G9: 10 | H9: Basic=265×10,000=2,650,000 LAK | I9: 46023 | K9: 46023 | L9: MoF System Update | M9: MoF No. 4904/MOF, 26 Dec 2025 | N9: Updated per MoF Guideline 4904/MOF (Jan 2026)
A10: 1 | B10: 7 | C10: ="G"&TEXT(A10,"00")&"-S"&TEXT(B10,"00") -> G01-S07 | D10: 266 | E10: 10000 | F10: Below Secondary | G10: 12 | H10: Basic=266×10,000=2,660,000 LAK | I10: 46023 | K10: 46023 | L10: MoF System Update | M10: MoF No. 4904/MOF, 26 Dec 2025 | N10: Updated per MoF Guideline 4904/MOF (Jan 2026)
A11: 1 | B11: 8 | C11: ="G"&TEXT(A11,"00")&"-S"&TEXT(B11,"00") -> G01-S08 | D11: 267 | E11: 10000 | F11: Below Secondary | G11: 14 | H11: Basic=267×10,000=2,670,000 LAK | I11: 46023 | K11: 46023 | L11: MoF System Update | M11: MoF No. 4904/MOF, 26 Dec 2025 | N11: Updated per MoF Guideline 4904/MOF (Jan 2026)
A12: 1 | B12: 9 | C12: ="G"&TEXT(A12,"00")&"-S"&TEXT(B12,"00") -> G01-S09 | D12: 268 | E12: 10000 | F12: Below Secondary | G12: 16 | H12: Basic=268×10,000=2,680,000 LAK | I12: 46023 | K12: 46023 | L12: MoF System Update | M12: MoF No. 4904/MOF, 26 Dec 2025 | N12: Updated per MoF Guideline 4904/MOF (Jan 2026)
A13: 1 | B13: 10 | C13: ="G"&TEXT(A13,"00")&"-S"&TEXT(B13,"00") -> G01-S10 | D13: 269 | E13: 10000 | F13: Below Secondary | G13: 18 | H13: Basic=269×10,000=2,690,000 LAK | I13: 46023 | K13: 46023 | L13: MoF System Update | M13: MoF No. 4904/MOF, 26 Dec 2025 | N13: Updated per MoF Guideline 4904/MOF (Jan 2026)
A14: 1 | B14: 11 | C14: ="G"&TEXT(A14,"00")&"-S"&TEXT(B14,"00") -> G01-S11 | D14: 270 | E14: 10000 | F14: Below Secondary | G14: 20 | H14: Basic=270×10,000=2,700,000 LAK | I14: 46023 | K14: 46023 | L14: MoF System Update | M14: MoF No. 4904/MOF, 26 Dec 2025 | N14: Updated per MoF Guideline 4904/MOF (Jan 2026)
A15: 1 | B15: 12 | C15: ="G"&TEXT(A15,"00")&"-S"&TEXT(B15,"00") -> G01-S12 | D15: 271 | E15: 10000 | F15: Below Secondary | G15: 22 | H15: Basic=271×10,000=2,710,000 LAK | I15: 46023 | K15: 46023 | L15: MoF System Update | M15: MoF No. 4904/MOF, 26 Dec 2025 | N15: Updated per MoF Guideline 4904/MOF (Jan 2026)
... A78: 5 | B78: 15 | C78: ="G"&TEXT(A78,"00")&"-S"&TEXT(B78,"00") -> G05-S15 | D78: 418 | E78: 10000 | F78: Master's / PhD | G78: 28 | H78: Basic=418×10,000=4,180,000 LAK | I78: 46023 | K78: 46023 | L78: MoF System Update | M78: MoF No. 4904/MOF, 26 Dec 2025 | N78: Updated per MoF Guideline 4904/MOF (Jan 2026)
A79: 6 | B79: 1 | C79: ="G"&TEXT(A79,"00")&"-S"&TEXT(B79,"00") -> G06-S01 | D79: 600 | E79: 10000 | F79: Appointed Leadership | G79: Appointed | H79: Leadership position. Index 600. Basic=6,000,000 LAK | I79: 46023 | K79: 46023 | L79: MoF System Update | M79: MoF No. 4904/MOF, 26 Dec 2025 | N79: Updated per MoF Guideline 4904/MOF (Jan 2026)
A80: 6 | B80: 2 | C80: ="G"&TEXT(A80,"00")&"-S"&TEXT(B80,"00") -> G06-S02 | D80: 700 | E80: 10000 | F80: Appointed Leadership | G80: Appointed | H80: Leadership position. Index 700. Basic=7,000,000 LAK | I80: 46023 | K80: 46023 | L80: MoF System Update | M80: MoF No. 4904/MOF, 26 Dec 2025 | N80: Updated per MoF Guideline 4904/MOF (Jan 2026)
A81: 6 | B81: 3 | C81: ="G"&TEXT(A81,"00")&"-S"&TEXT(B81,"00") -> G06-S03 | D81: 800 | E81: 10000 | F81: Appointed Leadership | G81: Appointed | H81: Leadership position. Index 800. Basic=8,000,000 LAK | I81: 46023 | K81: 46023 | L81: MoF System Update | M81: MoF No. 4904/MOF, 26 Dec 2025 | N81: Updated per MoF Guideline 4904/MOF (Jan 2026)
A82: 6 | B82: 4 | C82: ="G"&TEXT(A82,"00")&"-S"&TEXT(B82,"00") -> G06-S04 | D82: 900 | E82: 10000 | F82: Appointed Leadership | G82: Appointed | H82: Leadership position. Index 900. Basic=9,000,000 LAK | I82: 46023 | K82: 46023 | L82: MoF System Update | M82: MoF No. 4904/MOF, 26 Dec 2025 | N82: Updated per MoF Guideline 4904/MOF (Jan 2026)
A83: 6 | B83: 5 | C83: ="G"&TEXT(A83,"00")&"-S"&TEXT(B83,"00") -> G06-S05 | D83: 1000 | E83: 10000 | F83: Appointed Leadership | G83: Appointed | H83: Leadership position. Index 1000. Basic=10,000,000 LAK | I83: 46023 | K83: 46023 | L83: MoF System Update | M83: MoF No. 4904/MOF, 26 Dec 2025 | N83: Updated per MoF Guideline 4904/MOF (Jan 2026)
A84: 6 | B84: 6 | C84: ="G"&TEXT(A84,"00")&"-S"&TEXT(B84,"00") -> G06-S06 | D84: 1100 | E84: 10000 | F84: Appointed Leadership | G84: Appointed | H84: Leadership position. Index 1100. Basic=11,000,000 LAK | I84: 46023 | K84: 46023 | L84: MoF System Update | M84: MoF No. 4904/MOF, 26 Dec 2025 | N84: Updated per MoF Guideline 4904/MOF (Jan 2026)
A85: 6 | B85: 7 | C85: ="G"&TEXT(A85,"00")&"-S"&TEXT(B85,"00") -> G06-S07 | D85: 1200 | E85: 10000 | F85: Appointed Leadership | G85: Appointed | H85: Leadership position. Index 1200. Basic=12,000,000 LAK | I85: 46023 | K85: 46023 | L85: MoF System Update | M85: MoF No. 4904/MOF, 26 Dec 2025 | N85: Updated per MoF Guideline 4904/MOF (Jan 2026)

Sheet LK_AllowanceRates
A1: ALLOWANCE RATES TABLE (LK_AllowanceRates)
A2: ⭐ UPDATED PER MoF No. 4904/MOF, 26 December 2025. IMPORTANT CHANGES: (1) Row 4 = Salary Index Rate (LAK per index point) — was 'Index Value'. (2) Position Allowances restructured to MoF 8-Type system. (3) Years of Service now per-year rates (rows 12-15). (4) Teaching (row 16) and Remote (row 20) stored as % of basic salary (e.g. 0.20 = 20%). (5) Medical=500K, NA=1M, Hazardous=1M, Spouse=200K, Child=200K LAK. UPDATE Col B (Amount) when MoF issues further circulars. DO NOT change Col A names — they are VLOOKUP keys used by PAYROLL_CALC.
A3: Allowance / Rate Name | B3: Amount (LAK) or Rate | C3: Eligibility | D3: Description & Notes | E3: Effective From (Date) | F3: Effective To (Date) | G3: Last Updated (Date) | H3: Last Updated By (Name/Code) | I3: Circular / Reference | J3: Change Remarks
A4: Salary Index Rate (ຄ່າດັດສະນີ — LAK per Index Point) | B4: 10000 | C4: All Civil Servants | D4: Monetary rate per salary index point. Basic Salary = Grade/Step Index × this rate. Update when MoF issues revised ຄ່າດັດສະນີ circular. Current: 10,000 LAK/index point per MoF 4904/MOF indicative rate. | E4: 46023 | G4: 46023 | H4: MoF System Update | I4: MoF No. 4904/MOF, 26 Dec 2025 | J4: Updated per MoF Guideline 4904/MOF (Jan 2026)
A5: Position Allowance - General Staff | B5: 900000 | C5: Technical and general civil servants without administrative position | D5: Professional/technical (general staff) allowance per MoF 4904/MOF. 900,000 LAK/person/month. | E5: 46023 | G5: 46023 | H5: MoF System Update | I5: MoF No. 4904/MOF, 26 Dec 2025 | J5: Updated per MoF Guideline 4904/MOF (Jan 2026)
A6: Position Allowance - Section Chief | B6: 1500000 | C6: Section Chief / Type 3 administrative position | D6: Administrative position Type 3 per MoF 4904/MOF. 1,500,000 LAK/person/month. | E6: 46023 | G6: 46023 | H6: MoF System Update | I6: MoF No. 4904/MOF, 26 Dec 2025 | J6: Updated per MoF Guideline 4904/MOF (Jan 2026)
A7: Position Allowance - Division Chief | B7: 1900000 | C7: Division Chief / Type 5 administrative position | D7: Administrative position Type 5 per MoF 4904/MOF. 1,900,000 LAK/person/month. | E7: 46023 | G7: 46023 | H7: MoF System Update | I7: MoF No. 4904/MOF, 26 Dec 2025 | J7: Updated per MoF Guideline 4904/MOF (Jan 2026)
A8: Position Allowance - Deputy Director | B8: 2300000 | C8: Deputy Director / Type 7 administrative position | D8: Administrative position Type 7 per MoF 4904/MOF. 2,300,000 LAK/person/month. | E8: 46023 | G8: 46023 | H8: MoF System Update | I8: MoF No. 4904/MOF, 26 Dec 2025 | J8: Updated per MoF Guideline 4904/MOF (Jan 2026)
A9: Position Allowance - Director | B9: 2500000 | C9: Department Director / Type 8 administrative position | D9: Administrative position Type 8 per MoF 4904/MOF. 2,500,000 LAK/person/month. | E9: 46023 | G9: 46023 | H9: MoF System Update | I9: MoF No. 4904/MOF, 26 Dec 2025 | J9: Updated per MoF Guideline 4904/MOF (Jan 2026)
A10: Position Allowance - Deputy Minister | B10: 4000000 | C10: Deputy Minister / Grade 6 Step 2 leadership | D10: Grade 6 Step 2 leadership allowance per MoF 4904/MOF. 4,000,000 LAK/person/month. | E10: 46023 | G10: 46023 | H10: MoF System Update | I10: MoF No. 4904/MOF, 26 Dec 2025 | J10: Updated per MoF Guideline 4904/MOF (Jan 2026)
A11: Position Allowance - Minister | B11: 9000000 | C11: Minister / Grade 6 Step 7 highest leadership | D11: Grade 6 Step 7 leadership allowance per MoF 4904/MOF. 9,000,000 LAK/person/month. | E11: 46023 | G11: 46023 | H11: MoF System Update | I11: MoF No. 4904/MOF, 26 Dec 2025 | J11: Updated per MoF Guideline 4904/MOF (Jan 2026)
A12: Years of Service Rate — 1 to 5 Years (LAK/year) | B12: 10000 | C12: Staff with 1-5 completed years. Formula: years × 10,000 LAK/year. | D12: Per MoF 4904/MOF Sec 2.2.2. Rate of 10,000 LAK per year for first 5 years of service. | E12: 46023 | G12: 46023 | H12: MoF System Update | I12: MoF No. 4904/MOF, 26 Dec 2025 | J12: Updated per MoF Guideline 4904/MOF (Jan 2026)
A13: Years of Service Rate — 6 to 15 Years (LAK/year) | B13: 20000 | C13: Staff with 6-15 completed years. Formula: years × 20,000 LAK/year. | D13: Per MoF 4904/MOF Sec 2.2.2. Rate of 20,000 LAK per year for years 6-15. | E13: 46023 | G13: 46023 | H13: MoF System Update | I13: MoF No. 4904/MOF, 26 Dec 2025 | J13: Updated per MoF Guideline 4904/MOF (Jan 2026)
A14: Years of Service Rate — 16 to 25 Years (LAK/year) | B14: 30000 | C14: Staff with 16-25 completed years. Formula: years × 30,000 LAK/year. | D14: Per MoF 4904/MOF Sec 2.2.2. Rate of 30,000 LAK per year for years 16-25. | E14: 46023 | G14: 46023 | H14: MoF System Update | I14: MoF No. 4904/MOF, 26 Dec 2025 | J14: Updated per MoF Guideline 4904/MOF (Jan 2026)
A15: Years of Service Rate — 26+ Years (LAK/year) | B15: 40000 | C15: Staff with 26 or more completed years. Formula: years × 40,000 LAK/year. | D15: Per MoF 4904/MOF Sec 2.2.2. Rate of 40,000 LAK per year for 26+ years. | E15: 46023 | G15: 46023 | H15: MoF System Update | I15: MoF No. 4904/MOF, 26 Dec 2025 | J15: Updated per MoF Guideline 4904/MOF (Jan 2026)
... A26: SSO Employer Contribution Rate (%) | B26: 6 | C26: Government (employer) contribution — not deducted from employee salary. | D26: Reference only. Employer SSO contribution borne by government. | E26: 46023 | G26: 46023 | H26: MoF System Update | I26: MoF No. 4904/MOF, 26 Dec 2025 | J26: Updated per MoF Guideline 4904/MOF (Jan 2026)

Sheet LK_PIT
A1: PERSONAL INCOME TAX (PIT) BRACKETS — Lao PDR (LK_PIT)
A2: PIT is calculated on Taxable Income = Gross Earnings – SSO Employee Contribution. Tax is progressive. Col F = cumulative tax at the lower bound. Update Col D (Rate) and Col F (Cumulative) per current GDT circular.
A3: Bracket | B3: From (LAK) | C3: To (LAK) | D3: Rate % | E3: Description | F3: Cumulative Tax at Lower Bound | G3: Calculation Formula | H3: Effective From (Date) | I3: Effective To (Date) | J3: Last Updated (Date) | K3: Last Updated By (Name/Code) | L3: Circular / Reference | M3: Change Remarks
A4: 1 | B4: 0 | C4: 1300000 | D4: 0 | E4: Exempt | F4: 0 | G4: Tax: 0 (exempt) | H4: 46023 | J4: 46023 | K4: MoF System Update | L4: GDT / MoF PIT Rates (current) | M4: Updated per MoF Guideline 4904/MOF (Jan 2026)
A5: 2 | B5: 1300001 | C5: 5000000 | D5: 5 | E5: 5% on amount over 1,300,000 | F5: 0 | G5: Tax: (Income − 1,300,000) × 5% | H5: 46023 | J5: 46023 | K5: MoF System Update | L5: GDT / MoF PIT Rates (current) | M5: Updated per MoF Guideline 4904/MOF (Jan 2026)
A6: 3 | B6: 5000001 | C6: 10000000 | D6: 10 | E6: 10% on amount over 5,000,000 | F6: 185000 | G6: Tax: 185,000 + (Income − 5,000,000) × 10% | H6: 46023 | J6: 46023 | K6: MoF System Update | L6: GDT / MoF PIT Rates (current) | M6: Updated per MoF Guideline 4904/MOF (Jan 2026)
A7: 4 | B7: 10000001 | C7: 20000000 | D7: 15 | E7: 15% on amount over 10,000,000 | F7: 685000 | G7: Tax: 685,000 + (Income − 10,000,000) × 15% | H7: 46023 | J7: 46023 | K7: MoF System Update | L7: GDT / MoF PIT Rates (current) | M7: Updated per MoF Guideline 4904/MOF (Jan 2026)
A8: 5 | B8: 20000001 | C8: 40000000 | D8: 20 | E8: 20% on amount over 20,000,000 | F8: 2185000 | G8: Tax: 2,185,000 + (Income − 20,000,000) × 20% | H8: 46023 | J8: 46023 | K8: MoF System Update | L8: GDT / MoF PIT Rates (current) | M8: Updated per MoF Guideline 4904/MOF (Jan 2026)
A9: 6 | B9: 40000001 | C9: No Limit | D9: 24 | E9: 24% on amount over 40,000,000 | F9: 6185000 | G9: Tax: 6,185,000 + (Income − 40,000,000) × 24% | H9: 46023 | J9: 46023 | K9: MoF System Update | L9: GDT / MoF PIT Rates (current) | M9: Updated per MoF Guideline 4904/MOF (Jan 2026)

Sheet LK_DropdownLists
A1: MINISTRY_LIST | B1: MINISTRY_KEYS | C1: DEPT_MOF | D1: DEPT_MOH | E1: DEPT_MOES | F1: DEPT_MOHA | G1: DEPT_MPWT | H1: DEPT_MFA | I1: DEPT_MOAF | J1: DEPT_MLSW | K1: DEPT_MONRE | L1: DEPT_MOIC | M1: DEPT_MOJ | N1: DEPT_MPI | O1: DEPT_NA | P1: DEPT_VTCAP | Q1: DEPT_CHAM | R1: DEPT_LUANGPB | S1: DEPT_SAVAN | T1: DEPT_KHAMM | U1: ALL_DEPT_NAMES | V1: ALL_DEPT_KEYS | W1: DIV_MOF_BUD | X1: DIV_MOF_TAX | Y1: DIV_MOF_TRY | Z1: DIV_MOF_CUS | AA1: DIV_MOF_FIN | AB1: DIV_MOF_AST | AC1: DIV_MOH_CUR | AD1: DIV_MOH_HYG | AE1: DIV_MOH_FDD | AF1: DIV_MOH_EQP | AG1: DIV_MOH_PER | AH1: DIV_MOH_PLN | AI1: DIV_MOES_PRI | AJ1: DIV_MOES_SEC | AK1: DIV_MOES_HED | AL1: DIV_MOES_TVE | AM1: DIV_MOES_NFE | AN1: DIV_MOES_PLN | AO1: DIV_MOHA_PER | AP1: DIV_MOHA_ADM | AQ1: DIV_MOHA_LOC | AR1: DIV_MOHA_CIV | AS1: DIV_MOHA_COM | AT1: DIV_MPWT_ROD | AU1: DIV_MPWT_TRP | AV1: DIV_MPWT_HOU | AW1: DIV_MPWT_PUB | AX1: DIV_MPWT_MET | AY1: DIV_MFA_BIL | AZ1: DIV_MFA_MUL | BA1: DIV_MFA_ASN | BB1: DIV_MFA_PRO | BC1: DIV_MFA_CON | BD1: DIV_MOAF_AGR | BE1: DIV_MOAF_FOR | BF1: DIV_MOAF_IRR | BG1: DIV_MOAF_LIV | BH1: DIV_MOAF_LND | BI1: DIV_MLSW_LAB | BJ1: DIV_MLSW_SOC | BK1: DIV_MLSW_SKL | BL1: DIV_MLSW_SSO | BM1: DIV_MLSW_EMP | BN1: DIV_MONRE_NAT | BO1: DIV_MONRE_ENV | BP1: DIV_MONRE_LSV | BQ1: DIV_MONRE_CLM | BR1: DIV_MOIC_IND | BS1: DIV_MOIC_DOM | BT1: DIV_MOIC_IMP | BU1: DIV_MOIC_SME | BV1: DIV_MOJ_LEG | BW1: DIV_MOJ_JUD | BX1: DIV_MOJ_ANC | BY1: DIV_MOJ_INT | BZ1: DIV_MPI_PLN | CA1: DIV_MPI_INV | CB1: DIV_MPI_STA | CC1: DIV_MPI_INT | CD1: DIV_NA_SEC | CE1: DIV_NA_LAW | CF1: DIV_NA_ECF | CG1: DIV_NA_CSA | CH1: DIV_NA_NSC | CI1: DIV_NA_ADM | CJ1: DIV_VTC_FIN | CK1: DIV_VTC_EDU | CL1: DIV_VTC_HLT | CM1: DIV_VTC_PUB | CN1: DIV_VTC_ADM | CO1: DIV_CHP_FIN | CP1: DIV_CHP_EDU | CQ1: DIV_CHP_HLT | CR1: DIV_CHP_AGR | CS1: DIV_LPB_FIN | CT1: DIV_LPB_EDU | CU1: DIV_LPB_HLT | CV1: DIV_LPB_TCO | CW1: DIV_SVK_FIN | CX1: DIV_SVK_EDU | CY1: DIV_SVK_HLT | CZ1: DIV_SVK_IC | DA1: DIV_KMN_FIN | DB1: DIV_KMN_EDU | DC1: DIV_KMN_HLT | DD1: DIV_KMN_AGR | DE1: COUNTRY_LIST | DF1: COUNTRY_KEYS | DG1: PROV_LAO | DH1: PROV_FOR | DI1: ALL_PROV_NAMES | DJ1: ALL_PROV_KEYS | DK1: DIST_VTE | DL1: DIST_PGS | DM1: DIST_LNT | DN1: DIST_ODX | DO1: DIST_BKO | DP1: DIST_LPB | DQ1: DIST_HUA | DR1: DIST_SAY | DS1: DIST_XKH | DT1: DIST_VTP | DU1: DIST_BLK | DV1: DIST_KMN | DW1: DIST_SVK | DX1: DIST_SLV | DY1: DIST_SKG | DZ1: DIST_CHP | EA1: DIST_ATP | EB1: DIST_XYS | EC1: DIST_FOR_THA | ED1: DIST_FOR_VNM | EE1: DIST_FOR_CHN | EF1: DIST_FOR_FRA | EG1: DIST_FOR_USA | EH1: DIST_FOR_JPN | EI1: DIST_FOR_AUS | EJ1: DIST_FOR_DEU | EK1: DIST_FOR_RUS | EL1: DIST_FOR_KOR | EM1: DIST_FOR_IND | EN1: DIST_FOR_MMR | EO1: DIST_FOR_KHM | EP1: DIST_FOR_MYS | EQ1: DIST_FOR_SGP | ER1: DIST_FOR_IDN | ES1: DIST_FOR_CHE | FD1: POS_TEACHER | FE1: POS_MEDICAL | FF1: POS_FINANCE | FG1: POS_ADMINISTRATI | FH1: POS_TECHNICAL | FI1: POS_LEGAL | FJ1: POS_DIPLOMATIC | FK1: POS_GENERAL | FL1: BANK_LIST | FM1: BRANCH_BCEL | FN1: BRANCH_LDB | FO1: BRANCH_APB | FP1: BRANCH_NBB | FQ1: BRANCH_JDB | FR1: BRANCH_LVB | FS1: BRANCH_BFL | FT1: BRANCH_LCNB | FU1: BRANCH_PSV | FV1: BRANCH_BIC | FW1: BRANCH_STB | FX1: BRANCH_ICB | FY1: BRANCH_LMI | FZ1: BRANCH_MJBL | GA1: BRANCH_ABL | GB1: BRANCH_CAB | GC1: BRANCH_PBL | GD1: BRANCH_SCL | GE1: BRANCH_SHB | GF1: BRANCH_VCB | GG1: BRANCH_VTB | GH1: BRANCH_BBL | GI1: BRANCH_BAY | GJ1: BRANCH_KTB | GK1: BRANCH_SCBV | GL1: BRANCH_ANZ | GM1: BRANCH_ICBC | GN1: BRANCH_BOC
A2: Ministry of Finance (MoF) | B2: MOF | C2: Department of Budget | D2: Department of Curative Medicine | E2: Department of Primary Education | F2: Department of Personnel | G2: Department of Roads | H2: Department of Bilateral Cooperation | I2: Department of Agriculture | J2: Department of Labour | K2: Department of Natural Resources | L2: Department of Industry | M2: Department of Legislative Affairs | N2: Department of Planning | O2: NA Secretariat | P2: Department of Finance | Q2: Provincial Finance Office | R2: Provincial Finance Office | S2: Provincial Finance Office | T2: Provincial Finance Office | U2: Department of Budget | V2: MOF_BUD | W2: Revenue Planning Division | X2: Tax Policy Division | Y2: Cash Management Division | Z2: Import Control Division | AA2: Banking Supervision Division | AB2: Asset Registration Division | AC2: Hospital Services Division | AD2: Disease Prevention Division | AE2: Food Safety Division | AF2: Equipment Procurement Division | AG2: Recruitment Division | AH2: Health Planning Division | AI2: Curriculum Division | AJ2: Curriculum Division | AK2: University Affairs Division | AL2: TVET Policy Division | AM2: Adult Literacy Division | AN2: Education Planning Division | AO2: Civil Service Policy Division | AP2: Government Administration Division | AQ2: Provincial Affairs Division | AR2: Birth & Death Registration Division | AS2: Community Affairs Division | AT2: Road Planning Division | AU2: Land Transport Division | AV2: Urban Planning Division | AW2: Infrastructure Division | AX2: Weather Forecasting Division | AY2: ASEAN Relations Division | AZ2: UN Affairs Division | BA2: ASEAN Political Division | BB2: State Visits Division | BC2: Visa Division | BD2: Crop Production Division | BE2: Forest Management Division | BF2: Irrigation Infrastructure Division | BG2: Livestock Production Division | BH2: Land Use Planning Division | BI2: Labour Policy Division | BJ2: Social Protection Division | BK2: Skills Policy Division | BL2: SSO Policy Division | BM2: Employment Policy Division | BN2: Mineral Resources Division | BO2: Environmental Assessment Division | BP2: Cadastral Survey Division | BQ2: Climate Policy Division | BR2: Industrial Policy Division | BS2: Market Regulation Division | BT2: Import Management Division | BU2: SME Policy Division | BV2: Law Drafting Division | BW2: Court Administration Division | BX2: Investigation Division | BY2: Treaty Division | BZ2: Macro-Economic Planning Division | CA2: Domestic Investment Division | CB2: National Accounts Division | CC2: ODA Management Division | CD2: Session Management Division | CE2: Law Review Division | CF2: Budget Review Division | CG2: Culture Division | CH2: Security Affairs Division | CI2: Human Resources Division | CJ2: Budget Division | CK2: Primary Education Division | CL2: Curative Services Division | CM2: Roads Division | CN2: Personnel Division | CO2: Budget Division | CP2: Primary Division | CQ2: Hospital Division | CR2: Crop Division | CS2: Budget Division | CT2: Primary Division | CU2: Hospital Division | CV2: Tourism Division | CW2: Budget Division | CX2: Primary Division | CY2: Hospital Division | CZ2: Industry Division | DA2: Budget Division | DB2: Primary Division | DC2: Hospital Division | DD2: Crop Division | DE2: Lao PDR | DF2: LAO | DG2: Vientiane Capital | DH2: Thailand - Bangkok | DI2: Vientiane Capital | DJ2: VTE | DK2: Chanthabouli | DL2: Phongsali | DM2: Luang Namtha | DN2: Xay | DO2: Huoixai | DP2: Luang Prabang | DQ2: Xamneua | DR2: Sayabouli | DS2: Phonsavan | DT2: Phon Hong | DU2: Pakxan | DV2: Thakhek | DW2: Kaysone Phomvihane | DX2: Salavan | DY2: Lamam | DZ2: Pakse | EA2: Samakkhixay | EB2: Anouvong | EC2: Bangkok | ED2: Hanoi | EE2: Beijing | EF2: Paris | EG2: Washington DC | EH2: Tokyo | EI2: Canberra | EJ2: Berlin | EK2: Moscow | EL2: Seoul | EM2: New Delhi | EN2: Naypyidaw | EO2: Phnom Penh | EP2: Kuala Lumpur | EQ2: Singapore City | ER2: Jakarta | ES2: Geneva | FD2: Primary School Teacher | FE2: Medical Doctor | FF2: Finance Officer | FG2: Administrative Officer | FH2: Engineer | FI2: Legal Officer | FJ2: Foreign Affairs Officer | FK2: Policy Officer | FL2: Banque pour le Commerce Exterieur Lao Public (BCEL) | FM2: BCEL Head Office — Vientiane | FN2: LDB Head Office — Vientiane | FO2: APB Head Office — Vientiane | FP2: NBB Head Office — Vientiane | FQ2: JDB Head Office — Vientiane | FR2: LVB Head Office — Vientiane | FS2: BFL Head Office — Vientiane | FT2: LCNB Head Office — Vientiane | FU2: PSV Head Office — Vientiane | FV2: BIC Head Office — Vientiane | FW2: STB Head Office — Vientiane | FX2: Indochina Bank HO — Vientiane | FY2: LMI Head Office — Vientiane | FZ2: MJBL Head Office — Vientiane | GA2: ABL Head Office — Vientiane | GB2: Canadia Bank HO — Vientiane | GC2: PBL Head Office — Vientiane | GD2: Sacombank Lao HO — Vientiane | GE2: SHB Laos HO — Vientiane | GF2: Vietcombank Laos HO — Vientiane | GG2: Vietinbank Vientiane Branch | GH2: Bangkok Bank Vientiane Branch | GI2: Krungsri Vientiane Branch | GJ2: KTB Vientiane Branch | GK2: SCB Vientiane Branch | GL2: ANZ Vientiane Branch | GM2: ICBC Vientiane Branch | GN2: Bank of China Vientiane Branch
A3: Ministry of Health (MoH) | B3: MOH | C3: Department of Taxation | D3: Department of Hygiene & Health Promotion | E3: Department of Secondary Education | F3: Department of Administration | G3: Department of Transport | H3: Department of Multilateral Cooperation | I3: Department of Forestry | J3: Department of Social Welfare | K3: Department of Environment | L3: Department of Domestic Trade | M3: Department of Judicial Administration | N3: Department of Investment Promotion | O3: Committee on Laws | P3: Department of Education | Q3: Provincial Education Office | R3: Provincial Education Office | S3: Provincial Education Office | T3: Provincial Education Office | U3: Department of Taxation | V3: MOF_TAX | W3: Expenditure Control Division | X3: Revenue Collection Division | Y3: Government Securities Division | Z3: Export Control Division | AA3: Insurance Regulation Division | AB3: Asset Valuation Division | AC3: Specialist Care Division | AD3: Health Education Division | AE3: Drug Registration Division | AF3: Maintenance Division | AG3: Training & Development Division | AH3: Health Financing Division | AI3: Teacher Training Division | AJ3: Examinations Division | AK3: Academic Standards Division | AL3: Skills Standards Division | AM3: Community Learning Division | AN3: Statistics Division | AO3: Recruitment Division | AP3: Records Division | AQ3: District Affairs Division | AR3: ID Card Division | AS3: Social Development Division | AT3: Road Construction Division | AU3: Aviation Division | AV3: Housing Development Division | AW3: Quality Control Division | AX3: Climate Division | AY3: East Asia Division | AZ3: International Organisations Division | BA3: ASEAN Economic Division | BB3: Diplomatic Accreditation Division | BC3: Lao Diaspora Division | BD3: Agri-Input Division | BE3: Forest Inspection Division | BF3: Water Management Division | BG3: Veterinary Services Division | BH3: Land Classification Division | BI3: Labour Inspection Division | BJ3: Disability Affairs Division | BK3: Training Centre Division | BL3: Benefits Administration Division | BM3: Job Matching Division | BN3: Water Resources Division | BO3: Pollution Control Division | BP3: Topographic Division | BQ3: Adaptation Division | BR3: Manufacturing Division | BS3: Consumer Protection Division | BT3: Export Promotion Division | BU3: Business Development Division | BV3: Law Review Division | BW3: Enforcement Division | BX3: Prevention Division | BY3: International Arbitration Division | BZ3: Sector Planning Division | CA3: FDI Division | CB3: Survey Division | CC3: South-South Cooperation Division | CD3: Documentation Division | CE3: Legal Drafting Division | CF3: Economic Affairs Division | CG3: Social Policy Division | CH3: Defence Oversight Division | CI3: Finance Division | CJ3: Revenue Division | CK3: Secondary Division | CL3: Preventive Health Division | CM3: Urban Planning Division | CN3: Records Division | CO3: Revenue Division | CP3: Secondary Division | CQ3: Preventive Health Division | CR3: Livestock Division | CS3: Revenue Division | CT3: Secondary Division | CU3: Preventive Health Division | CV3: Cultural Heritage Division | CW3: Revenue Division | CX3: Secondary Division | CY3: Preventive Health Division | CZ3: Trade Division | DA3: Revenue Division | DB3: Secondary Division | DC3: Preventive Health Division | DD3: Livestock Division | DE3: Foreign / International | DF3: FOR | DG3: Phongsali | DH3: Vietnam - Hanoi | DI3: Phongsali | DJ3: PGS | DK3: Sikhottabong | DL3: Boun Neua | DM3: Sing | DN3: La | DO3: Ton Pheung | DP3: Xieng Ngeun | DQ3: Xiengkho | DR3: Khop | DS3: Kham | DT3: Thoulakhom | DU3: Thaphabath | DV3: Mahaxay | DW3: Outhoumphone | DX3: Toomlarn | DY3: Kaleum | DZ3: Sanasomboon | EA3: Sanamxay | EB3: Longxan | FD3: Secondary School Teacher | FE3: Nurse | FF3: Senior Finance Officer | FG3: Senior Administrative Officer | FH3: Senior Engineer | FI3: Senior Legal Officer | FJ3: First Secretary | FK3: Research Officer | FL3: Lao Development Bank (LDB) | FM3: BCEL Samsenthai Branch | FN3: LDB Nong Bone Branch | FO3: APB Savannakhet Branch | FP3: NBB Savannakhet Branch | FQ3: JDB Samsenthai Branch | FR3: LVB Savannakhet Branch | FS3: BFL Savannakhet Branch | FT3: LCNB Luang Prabang Branch | FU3: PSV Saysettha Branch | FV3: BIC Savannakhet Branch | FW3: STB Champasak Branch | FZ3: MJBL Savannakhet Branch | GA3: ABL Savannakhet Branch | GD3: Sacombank Lao Savannakhet
A4: Ministry of Education and Sports (MoES) | B4: MOES | C4: Department of Treasury | D4: Department of Food and Drug | E4: Department of Higher Education | F4: Department of Local Administration | G4: Department of Housing & Urban Planning | H4: Department of ASEAN Affairs | I4: Department of Irrigation | J4: Department of Skills Development | K4: Department of Land Survey | L4: Department of Import-Export | M4: Department of Anti-Corruption | N4: Department of Statistics | O4: Committee on Economy & Finance | P4: Department of Health | Q4: Provincial Health Office | R4: Provincial Health Office | S4: Provincial Health Office | T4: Provincial Health Office | U4: Department of Treasury | V4: MOF_TRY | W4: Budget Analysis Division | X4: Tax Audit & Inspection Division | Y4: State Accounting Division | Z4: Customs Inspection Division | AA4: Capital Markets Division | AB4: Asset Disposal Division | AC4: Emergency Medicine Division | AD4: Environmental Health Division | AE4: Drug Inspection Division | AF4: Standards Division | AG4: Performance Division | AH4: Statistics Division | AI4: School Quality Division | AJ4: School Development Division | AK4: Research Division | AL4: Industry Linkage Division | AM4: Equivalency Division | AN4: Finance Division | AO4: Classification Division | AP4: Archives Division | AQ4: Village Affairs Division | AR4: Marriage Registration Division | AS4: Women Affairs Division | AT4: Road Maintenance Division | AU4: River Transport Division | AV4: Building Standards Division | AW4: Survey Division | AX4: Hydrology Division | AY4: Europe & Americas Division | AZ4: Global Issues Division | BA4: ASEAN Socio-Cultural Division | BB4: Ceremonial Division | BC4: Consular Services Division | BD4: Agri-Technology Division | BE4: Reforestation Division | BF4: Dam Safety Division | BG4: Fishery Division | BH4: Land Survey Division | BI4: Occupational Safety Division | BJ4: Elderly Care Division | BK4: Certification Division | BL4: Contribution Collection Division | BM4: Labour Migration Division | BN4: Biodiversity Division | BO4: Green Economy Division | BP4: Geo-Information Division | BQ4: GHG Inventory Division | BR4: Quality Standards Division | BS4: Price Control Division | BT4: Trade Facilitation Division | BU4: Finance Access Division | BV4: Constitutional Affairs Division | BW4: Legal Aid Division | BX4: Asset Recovery Division | BY4: Extradition Division | BZ4: Regional Planning Division | CA4: Special Economic Zones Division | CB4: Data Management Division | CC4: Aid Effectiveness Division | CD4: Member Services Division | CE4: Legislative Research Division | CF4: Finance Oversight Division | CG4: Education Oversight Division | CH4: Intelligence Review Division | CI4: Logistics Division | CJ4: Accounting Division | CK4: Administration Division | CL4: Pharmacy Division | CM4: Utilities Division | CN4: IT Division | CO4: Accounting Division | CP4: Non-Formal Division | CQ4: Pharmacy Division | CR4: Forestry Division | CS4: Accounting Division | CT4: Higher Education Division | CU4: Maternal Health Division | CV4: Arts Division | CW4: Accounting Division | CX4: TVET Division | CY4: Pharmacy Division | CZ4: SME Division | DA4: Accounting Division | DB4: Non-Formal Division | DC4: Environmental Health Division | DD4: Irrigation Division | DG4: Luang Namtha | DH4: China - Beijing | DI4: Luang Namtha | DJ4: LNT | DK4: Xaysettha | DL4: May | DM4: Long | DN4: Beng | DO4: Pha Oudom | DP4: Nan | DQ4: Viengxay | DR4: Hongsa | DS4: Nonghet | DT4: Keo Oudom | DU4: Pakkading | DV4: Nongbok | DW4: Atsaphon | DX4: Lakhonepheng | DY4: Thateng | DZ4: Bachiangchaleunsook | EA4: Sanxay | EB4: Hom | FD4: University Lecturer | FE4: Pharmacist | FF4: Budget Officer | FG4: Department Director | FH4: Technical Officer | FI4: Legislative Officer | FJ4: Second Secretary | FK4: Planning Officer | FL4: Agricultural Promotion Bank (APB) | FM4: BCEL Dongpalane Branch | FN4: LDB Savannakhet Branch | FO4: APB Luang Prabang Branch | FP4: NBB Luang Prabang Branch | FQ4: JDB Savannakhet Branch | FR4: LVB Champasak Branch | FT4: LCNB Boten SEZ Branch | FU4: PSV Savannakhet Branch | GA4: ABL Champasak Branch
